Workbook
Name AreaUnderMACYN: #REF!
Name BioenergyCropsYN: #REF!
Name BurdenSharing: #REF!
Name CapitalYN: #REF!
Name ClimateChange: #REF!
Name CoalYN: #REF!
Name ConsumptionLossYN: #REF!
Name ElectricityYN: #REF!
Name EmissionsPermitsYN: #REF!
Name EnergySystemCostMarkUpYN: #REF!
Name EquivalentVariationYN: #REF!
Name FoodCropsYN: #REF!
Name GasYN: #REF!
Name GDPLossYN: #REF!
Name ModelTypeSolutionConcept: #REF!
Name ModelTypeSolutionHorizon: #REF!
Name ModelTypeSolutionMethod: #REF!
Name ModelVersionStatus: #REF!
Name OilYN: #REF!
Name Overshoot: #REF!
Name ProcessedGoodsYN: #REF!
Name RegionalCoverage: #REF!
Name ScenarioType: #REF!
Name TechFlex: #REF!
Name UraniumYN: #REF!
Name WelfareLossYN: #REF!
Name WhatFlex: #REF!
Name WhenFlex: #REF!
Name WhenFlex2: #REF!
Name YN: #REF!

Sheet Listing_template
A1: Model | B1: Scenario | C1: Region | D1: Item | E1: Variable | F1: Year | G1: Unit | H1: Value
A2: … | B2: … | C2: WLD | D2: TOT | E2: POPT | F2: 2000 | G2: million
A3: … | B3: … | C3: … | D3: … | E3: … | F3: … | G3: …

Sheet Variables
C2: NEW LAMASUS SUGGESTIONS
B5: Variable | C5: Description | D5: Unit | E5: Total | F5: Rice | G5: Wheat | H5: Coarse grains | I5: Maize | J5: other coarse grains | K5: Oilseeds | L5: soya, rapeseed, sunflower | M5: other oilseeds and oil crops | N5: Sugar crops | O5: Vegetables, fruits & nuts | P5: Vegetables | Q5: Fruits | R5: Nuts | S5: Roots & tubers | T5: Pulses | U5: Plant based fibres | V5: Cotton | W5: other plant based fibres | X5: Energy crops | Y5: Other crops | Z5: All crops | AA5: Arable crops | AB5: Permanent crops | AC5: Ruminant meat | AD5: beef | AE5: Other ruminant | AF5: Non-ruminant meat | AG5: Pork meat | AH5: Poultry meat | AI5: Poultry eggs | AJ5: Other non-ruminant | AK5: Dairy | AL5: Other animal products | AM5: Livestock | AN5: Fish | AO5: Agriculture | AP5: Grass | AQ5: Other feed | AR5: Forest | AS5: Strict protection | AT5: Protected coniferous | AU5: Protected non-coniferous | AV5: Low intensity coniferous | AW5: Low intensity non-coniferous | AX5: High intensity coniferous | AY5: High intensity non-coniferous | AZ5: Restored protected coniferous | BA5: Restored protected non-coniferous | BB5: Restored unprotected coniferous | BC5: Restored unprotected non-coniferous | BD5: Managed Forest | BE5: Primary Forest | BF5: Woodchips Conifereous | BG5: Woodchips Non-conifereous | BH5: Sawdust Conifereous | BI5: Sawdust Non-conifereous | BJ5: Pulplogs Conifereous | BK5: Pulplogs Non-conifereous | BL5: Sawlogs Conifereous | BM5: Sawlogs Non-conifereous | BN5: Bark | BO5: Black Liquor | BP5: Agriculture and Forestry | BQ5: Other natural vegetation | BR5: Non arable land | BS5: Built-up area | BT5: Land-use change | BU5: Agriculture, Forestry, Land use-change | BV5: Wetland emissions | BW5: Enteric Fermentation | BX5: Manure applied to soils | BY5: Manure dropped on pasture | BZ5: Manure mangement | CA5: Rice cultivation | CB5: Synthetic fertilizer application | CC5: Labor | CD5: Capital | CE5: Fertiliser | CF5: Fossil fuel | CG5: Electricity | CH5: Primary agriculture & fish | CI5: Processed food sectors | CJ5: Food services | CK5: Non food sectors
E6: TOT | F6: RIC | G6: WHT | H6: CGR | I6: CGR|MAI | J6: CGR|OCG | K6: OSD | L6: OSD|SRS | M6: OSD|OOC | N6: SGC | O6: VFN | P6: VFN|VEG | Q6: VFN|FRU | R6: VFN|NUT | S6: VFN|ROOT | T6: VFN|PULS | U6: PFB | V6: PFB|COT | W6: PFB|OPF | X6: ECP | Y6: OCR | Z6: CRP | AA6: CRP|ARA | AB6: CRP|PRM | AC6: RUM | AD6: RUM|BEF | AE6: RUM|ORU | AF6: NRM | AG6: NRM|PRK | AH6: NRM|PTM | AI6: NRM|EGG | AJ6: NRM|ONR | AK6: DRY | AL6: OAP | AM6: LSP | AN6: FSH | AO6: AGR | AP6: GRS | AQ6: OFD | AR6: FOR | AS6: FOR|PRO | AT6: FOR|LOC | AU6: FOR|LON | AV6: FOR|MIC | AW6: FOR|MIN | AX6: FOR|HIC | AY6: FOR|HIN | AZ6: FOR|LRC | BA6: FOR|LRN | BB6: FOR|RUC | BC6: FOR|RUN | BD6: FOR|MAN | BE6: FOR|PRIM | BF6: FOR|WCC | BG6: FOR|WCN | BH6: FOR|SDC | BI6: FOR|SDN | BJ6: FOR|PLC | BK6: FOR|PLN | BL6: FOR|SLC | BM6: FOR|SLN | BN6: FOR|BRK | BO6: FOR|BLI | BP6: AFO | BQ6: ONV | BR6: NLD | BS6: BUA | BT6: LUC | BU6: AFOLU | BV6: WEM | BW6: ENT | BX6: MAS | BY6: MGR | BZ6: MMG | CA6: RCC | CB6: SFR | CC6: LAB | CD6: CAP | CE6: FRT | CF6: FF | CG6: ELEC | CH6: PRAG | CI6: PRFD | CJ6: PDSV | CK6: NONF | CL6: BC20
B7: POPT | C7: Total population | D7: million | E7: X
B8: GDPT | C8: Total GDP (MER) | D8: bn USD 2005 MER | E8: X
B9: XPRP | C9: Real producer price/input price | D9: USD/t | F9: X | G9: X | H9: X | K9: X | N9: X | O9: X | U9: X | X9: X | Y9: X | Z9: X | AC9: X | AF9: X | AK9: X | AL9: X | AM9: X | AN9: X | AO9: X | AR9: X
B10: XPRP_dm | C10: Real producer price/input price per unit dry matter content | D10: USD/t | F10: X | G10: X | H10: X | K10: X | N10: X | O10: X | U10: X | X10: X | Y10: X | Z10: X | AC10: X | AF10: X | AK10: X | AL10: X | AM10: X | AN10: X | AO10: X | AR10: X
B11: XPRX | C11: Real export price | D11: USD/t | F11: X | G11: X | H11: X | K11: X | N11: X | O11: X | U11: X | X11: X | Y11: X | Z11: X | AC11: X | AF11: X | AK11: X | AL11: X | AM11: X | AN11: X | AO11: X | AR11: X
B12: XPRX_dm | C12: Real export price per unit dry matter | D12: USD/t | F12: X | G12: X | H12: X | K12: X | N12: X | O12: X | U12: X | X12: X | Y12: X | Z12: X | AC12: X | AF12: X | AK12: X | AL12: X | AM12: X | AN12: X | AO12: X | AR12: X
B13: AREA | C13: Area harvested | D13: 1000 ha | E13: X | F13: X | G13: X | H13: X | I13: X | J13: X | K13: X | L13: X | M13: X | N13: X | O13: X | P13: X | Q13: X | R13: X | S13: X | T13: X | U13: X | V13: X | W13: X | X13: X | Y13: X | Z13: X | AA13: X | AB13: X | AC13: X | AD13: X | AE13: X | AF13: X | AG13: X | AH13: X | AI13: X | AJ13: X | AK13: X | AL13: X | AM13: X | AO13: X | AR13: X | AS13: X | AT13: X | AU13: X | AV13: X | AW13: X | AX13: X | AY13: X | AZ13: X | BA13: X | BB13: X | BC13: X | BD13: X | BE13: X
B14: ARRF | C14: Area harvested - rainfed | D14: 1000 ha | F14: X | G14: X | H14: X | I14: X | J14: X | K14: X | L14: X | M14: X | N14: X | O14: X | P14: X | Q14: X | R14: X | S14: X | T14: X | U14: X | V14: X | W14: X | X14: X | Y14: X | Z14: X | AA14: X | AB14: X
B15: ARIR | C15: Area harvested - irrigated | D15: 1000 ha | F15: X | G15: X | H15: X | I15: X | J15: X | K15: X | L15: X | M15: X | N15: X | O15: X | P15: X | Q15: X | R15: X | S15: X | T15: X | U15: X | V15: X | W15: X | X15: X | Y15: X | Z15: X | AA15: X | AB15: X
B16: LAND | C16: Land cover | D16: 1000 ha | E16: X | X16: X | Z16: X | AA16: X | AB16: X | AO16: X | AP16: X | AR16: X | BP16: X | BQ16: X | BS16: X
B17: YILD | C17: Crop yield | D17: t/ha | F17: X | G17: X | H17: X | K17: X | N17: X | O17: X | U17: X | X17: X | Y17: X | Z17: X | AP17: X
B18: YILD_dm | C18: Crop yield in dry matter content | D18: t/ha | F18: X | G18: X | H18: X | K18: X | N18: X | O18: X | U18: X | X18: X | Y18: X | Z18: X | AP18: X
B19: YIRF | C19: Crop yield - rainfed | D19: t/ha | F19: X | G19: X | H19: X | K19: X | N19: X | O19: X | U19: X | X19: X | Y19: X | Z19: X
B20: YIRF_dm | C20: Crop yield in dry matter content - rainfed | D20: t/ha | F20: X | G20: X | H20: X | K20: X | N20: X | O20: X | U20: X | X20: X | Y20: X | Z20: X
B21: YIIR | C21: Crop yield - irrigated | D21: t/ha | F21: X | G21: X | H21: X | K21: X | N21: X | O21: X | U21: X | X21: X | Y21: X | Z21: X
B22: YIIR_dm | C22: Crop yield in dry matter content - irrigated | D22: t/ha | F22: X | G22: X | H22: X | K22: X | N22: X | O22: X | U22: X | X22: X | Y22: X | Z22: X
B23: YEXO | C23: Exogenous crop yield (including climate shifter) | D23: t/ha | F23: X | G23: X | H23: X | K23: X | N23: X | O23: X | U23: X | X23: X | Y23: X | Z23: X | AP23: X
B24: YEXO_dm | C24: Exogenous crop yield in dry matter content (including climate shifter) | D24: t/ha | F24: X | G24: X | H24: X | K24: X | N24: X | O24: X | U24: X | X24: X | Y24: X | Z24: X | AP24: X
B25: YEXO_I | C25: Exogenous crop yield - Irrigated | D25: t/ha | F25: X | G25: X | H25: X | K25: X | N25: X | O25: X | U25: X | X25: X | Y25: X | Z25: X
B26: YEXO_I_dm | C26: Exogenous crop yield in dry matter content - Irrigated | D26: t/ha | F26: X | G26: X | H26: X | K26: X | N26: X | O26: X | U26: X | X26: X | Y26: X | Z26: X
B27: YEXO_R | C27: Exogenous crop yield - Rainfed | D27: t/ha | F27: X | G27: X | H27: X | K27: X | N27: X | O27: X | U27: X | X27: X | Y27: X | Z27: X
B28: YEXO_R_dm | C28: Exogenous crop yield in dry matter content - Rainfed | D28: t/ha | F28: X | G28: X | H28: X | K28: X | N28: X | O28: X | U28: X | X28: X | Y28: X | Z28: X
B29: YECC | C29: Climate change shifter on crop yield | D29: multiplier (unitless) | F29: X | G29: X | H29: X | K29: X | N29: X | O29: X | U29: X | X29: X | Y29: X | Z29: X | AP29: X
B30: YECC_I | C30: Climate change shifter on crop yield_Irrigated | D30: multiplier (unitless) | F30: X | G30: X | H30: X | K30: X | N30: X | O30: X | U30: X | X30: X | Y30: X | Z30: X
B31: YECC_R | C31: Climate change shifter on crop yield_Rainfed | D31: multiplier (unitless) | F31: X | G31: X | H31: X | K31: X | N31: X | O31: X | U31: X | X31: X | Y31: X | Z31: X
B32: LYLD | C32: Livestock yield (endogenous) | D32: kg prt/ha | AC32: X | AK32: X
B33: LYXO | C33: Exogenous livestock yield trend | D33: kg prt/ha | AC33: X | AK33: X
B34: FPROD | C34: Forestry production | D34: m3/yr | AR34: X | BD34: X | BF34: X | BG34: X | BH34: X | BI34: X | BJ34: X | BK34: X | BL34: X | BM34: X | BN34: X | BO34: X
B35: FCONS | C35: Forestry consumption | D35: m3/yr | AR35: X | BD35: X
B36: FNETT | C36: Forest products net trade | D36: m3/yr | AR36: X | BD36: X | BF36: X | BG36: X | BH36: X | BI36: X | BJ36: X | BK36: X | BL36: X | BM36: X | BN36: X | BO36: X
B37: FYLD | C37: Forestry yields | D37: m3/ha | AR37: X | BD37: X | BF37: X | BG37: X | BH37: X | BI37: X | BJ37: X | BK37: X | BL37: X | BM37: X | BN37: X | BO37: X
B38: FXPRP | C38: Real producer price/input price | D38: USD/m3 | AR38: X | BD38: x | BE38: x | BF38: X | BG38: X | BH38: X | BI38: X | BJ38: X | BK38: X | BL38: X | BM38: X | BN38: X | BO38: X
B39: FEEF | C39: Feed conversion efficiency (endogenous) | D39: kg prt/kg prt | AC39: X | AF39: X | AK39: X | AM39: X | AN39: X
B40: FOOD | C40: Food use | D40: 1000 t | F40: X | G40: X | H40: X | K40: X | N40: X | O40: X | U40: X | Y40: X | Z40: X | AC40: X | AF40: X | AK40: X | AL40: X | AM40: X | AN40: X | AO40: X
B41: FOOD_dm | C41: Food use in dry matter content | D41: 1000 t | F41: X | G41: X | H41: X | K41: X | N41: X | O41: X | U41: X | Y41: X | Z41: X | AC41: X | AF41: X | AK41: X | AL41: X | AM41: X | AN41: X | AO41: X
B42: FEED | C42: Feed use | D42: 1000 t | F42: X | G42: X | H42: X | K42: X | N42: X | O42: X | U42: X | Y42: X | Z42: X | AN42: X | AP42: X | AQ42: X
B43: FEED_dm | C43: Feed use in dry matter content | D43: 1000 t | F43: X | G43: X | H43: X | K43: X | N43: X | O43: X | U43: X | Y43: X | Z43: X | AN43: X | AP43: X | AQ43: X
B44: OTHU | C44: Other use | D44: 1000 t | F44: X | G44: X | H44: X | K44: X | N44: X | O44: X | U44: X | X44: X | Y44: X | Z44: X | AC44: X | AF44: X | AK44: X | AL44: X | AM44: X | AN44: X | AO44: X
B45: OTHU_dm | C45: Other use in dry matter content | D45: 1000 t | F45: X | G45: X | H45: X | K45: X | N45: X | O45: X | U45: X | X45: X | Y45: X | Z45: X | AC45: X | AF45: X | AK45: X | AL45: X | AM45: X | AN45: X | AO45: X
B46: IMPO | C46: Imports | D46: 1000 t | F46: X | G46: X | H46: X | K46: X | N46: X | O46: X | U46: X | X46: X | Y46: X | Z46: X | AC46: X | AF46: X | AK46: X | AL46: X | AM46: X | AN46: X | AO46: X
B47: IMPO_dm | C47: Imports in dry matter content | D47: 1000 t | F47: X | G47: X | H47: X | K47: X | N47: X | O47: X | U47: X | X47: X | Y47: X | Z47: X | AC47: X | AF47: X | AK47: X | AL47: X | AM47: X | AN47: X | AO47: X
B48: EXPO | C48: Exports | D48: 1000 t | F48: X | G48: X | H48: X | K48: X | N48: X | O48: X | U48: X | X48: X | Y48: X | Z48: X | AC48: X | AF48: X | AK48: X | AL48: X | AM48: X | AN48: X | AO48: X
B49: EXPO_dm | C49: Exports in dry matter content | D49: 1000 t | F49: X | G49: X | H49: X | K49: X | N49: X | O49: X | U49: X | X49: X | Y49: X | Z49: X | AC49: X | AF49: X | AK49: X | AL49: X | AM49: X | AN49: X | AO49: X
B50: WATR | C50: Water for irrigation (consumption) | D50: km3 | F50: X | G50: X | H50: X | K50: X | N50: X | O50: X | U50: X | X50: X | Y50: X | Z50: X
B51: WATW | C51: Water for irrigation (withdrawal) | D51: km3 | F51: X | G51: X | H51: X | K51: X | N51: X | O51: X | U51: X | X51: X | Y51: X | Z51: X
B52: CALO | C52: p.c. calory availability | D52: kcal/cap/d | F52: X | G52: X | H52: X | K52: X | N52: X | O52: X | U52: X | Y52: X | Z52: X | AC52: X | AF52: X | AK52: X | AL52: X | AM52: X | AN52: X | AO52: X
B53: CALI | C53: p.c. calory intake | D53: kcal/cap/d | F53: X | G53: X | H53: X | K53: X | N53: X | O53: X | U53: X | Y53: X | Z53: X | AC53: X | AF53: X | AK53: X | AL53: X | AM53: X | AN53: X | AO53: X
B54: PROD | C54: Production | D54: 1000 t | F54: X | G54: X | H54: X | I54: X | J54: X | K54: X | L54: X | M54: X | N54: X | O54: X | P54: X | Q54: X | R54: X | S54: X | T54: X | U54: X | V54: X | W54: X | X54: X | Y54: X | Z54: X | AC54: X | AD54: X | AE54: X | AF54: X | AG54: X | AH54: X | AI54: X | AJ54: X | AK54: X | AL54: X | AM54: X | AN54: X | AO54: X | AP54: X | CL54: x
B55: PROD_dm | C55: Production in dry matter content | D55: 1000 t | F55: X | G55: X | H55: X | I55: X | J55: X | K55: X | L55: X | M55: X | N55: X | O55: X | P55: X | Q55: X | R55: X | S55: X | T55: X | U55: X | V55: X | W55: X | X55: X | Y55: X | Z55: X | AC55: X | AD55: X | AE55: X | AF55: X | AG55: X | AH55: X | AI55: X | AJ55: X | AK55: X | AL55: X | AM55: X | AN55: X | AO55: X | AP55: X
B56: CONS | C56: Domestic use | D56: 1000 t | F56: X | G56: X | H56: X | I56: X | J56: X | K56: X | L56: X | M56: X | N56: X | O56: X | P56: X | Q56: X | R56: X | S56: X | T56: X | U56: X | V56: X | W56: X | X56: X | Y56: X | Z56: X | AC56: X | AD56: X | AE56: X | AF56: X | AG56: X | AH56: X | AI56: X | AJ56: X | AK56: X | AL56: X | AM56: X | AN56: X | AO56: X | CL56: x
B57: CONS_dm | C57: Domestic use in dry matter content | D57: 1000 t | F57: X | G57: X | H57: X | I57: X | J57: X | K57: X | L57: X | M57: X | N57: X | O57: X | P57: X | Q57: X | R57: X | S57: X | T57: X | U57: X | V57: X | W57: X | X57: X | Y57: X | Z57: X | AC57: X | AD57: X | AE57: X | AF57: X | AG57: X | AH57: X | AI57: X | AJ57: X | AK57: X | AL57: X | AM57: X | AN57: X | AO57: X
B58: NETT | C58: Net trade | D58: 1000 t | F58: X | G58: X | H58: X | K58: X | N58: X | O58: X | U58: X | X58: X | Y58: X | Z58: X | AC58: X | AF58: X | AK58: X | AL58: X | AM58: X | AN58: X | AO58: X | CL58: x
B59: FEXO | C59: Feed conversion efficiency trend | D59: kg prt/kg prt | AC59: X | AF59: X | AK59: X | AM59: X | AN59: X
B60: NETT_dm | C60: Net trade in dry matter content | D60: 1000 t | F60: X | G60: X | H60: X | K60: X | N60: X | O60: X | U60: X | X60: X | Y60: X | Z60: X | AC60: X | AF60: X | AK60: X | AL60: X | AM60: X | AN60: X | AO60: X
B61: ANNR | C61: Livestock animal numbers | D61: 1000 LSU | AC61: X | AF61: X | AK61: X | AL61: X | AM61: X
B62: FRUM | C62: Feed use ruminant meat | D62: 1000 t | F62: X | G62: X | H62: X | K62: X | N62: X | O62: X | U62: X | Y62: X | Z62: X | AO62: X | AP62: X | AQ62: X
B63: FRUM_dm | C63: Feed use ruminant meat in dry matter content | D63: 1000 t | F63: X | G63: X | H63: X | K63: X | N63: X | O63: X | U63: X | Y63: X | Z63: X | AO63: X | AP63: X | AQ63: X
B64: FRUM_prt | C64: Feed use ruminant meat in protein content | D64: 1000 t | F64: X | G64: X | H64: X | K64: X | N64: X | O64: X | U64: X | Y64: X | Z64: X | AO64: X | AP64: X | AQ64: X
B65: FNRM | C65: Feed use non-ruminant | D65: 1000 t | F65: X | G65: X | H65: X | K65: X | N65: X | O65: X | U65: X | Y65: X | Z65: X | AO65: X | AP65: X | AQ65: X
B66: FNRM_dm | C66: Feed use non-ruminant in dry matter content | D66: 1000 t | F66: X | G66: X | H66: X | K66: X | N66: X | O66: X | U66: X | Y66: X | Z66: X | AO66: X | AP66: X | AQ66: X
B67: FNRM_prt | C67: Feed use non-ruminant in protein content | D67: 1000 t | F67: X | G67: X | H67: X | K67: X | N67: X | O67: X | U67: X | Y67: X | Z67: X | AO67: X | AP67: X | AQ67: X
B68: FDRY | C68: Feed use dairy | D68: 1000 t | F68: X | G68: X | H68: X | K68: X | N68: X | O68: X | U68: X | Y68: X | Z68: X | AO68: X | AP68: X | AQ68: X
B69: FDRY_dm | C69: Feed use dairy in dry matter content | D69: 1000 t | F69: X | G69: X | H69: X | K69: X | N69: X | O69: X | U69: X | Y69: X | Z69: X | AO69: X | AP69: X | AQ69: X
B70: FDRY_prt | C70: Feed use dairy in protein content | D70: 1000 t | F70: X | G70: X | H70: X | K70: X | N70: X | O70: X | U70: X | Y70: X | Z70: X | AO70: X | AP70: X | AQ70: X
B71: FFSH | C71: Feed fish sector | D71: 1000 t | F71: X | G71: X | H71: X | K71: X | N71: X | O71: X | U71: X | Y71: X | Z71: X | AO71: X | AP71: X | AQ71: X
B72: FFSH_dm | C72: Feed fish sector in dry matter content | D72: 1000 t | F72: X | G72: X | H72: X | K72: X | N72: X | O72: X | U72: X | Y72: X | Z72: X | AO72: X | AP72: X | AQ72: X
B73: FFSH_prt | C73: Feed fish sector in protein content | D73: 1000 t | F73: X | G73: X | H73: X | K73: X | N73: X | O73: X | U73: X | Y73: X | Z73: X | AO73: X | AP73: X | AQ73: X
B74: EMIS | C74: Total GHG emissions | D74: MtCO2e | E74: X | F74: X | G74: X | H74: X | K74: X | N74: X | O74: X | U74: X | X74: X | Y74: X | Z74: X | AC74: X | AF74: X | AK74: X | AL74: X | AM74: X | AO74: X | AP74: X | AQ74: X | AR74: X | BP74: X | BQ74: X | BS74: X | BT74: X | BU74: X | BV74: X | BW74: X | BX74: X | BY74: X | BZ74: X | CA74: X | CB74: X
B75: ECO2 | C75: Total CO2 emissions | D75: MtCO2e | E75: X | X75: X | AR75: X | BP75: X | BQ75: X | BS75: X | BT75: X | BU75: X | BV75: X
B76: ECH4_eq | C76: Total CH4 emissions | D76: MtCO2e | E76: X | F76: X | Z76: X | AC76: X | AF76: X | AK76: X | AL76: X | AM76: X | AO76: X | BP76: X | BV76: X | BW76: X | BZ76: X | CA76: X
B77: EN2O_eq | C77: Total N2O emissions | D77: MtCO2e | E77: X | F77: X | G77: X | H77: X | K77: X | N77: X | O77: X | U77: X | X77: X | Y77: X | Z77: X | AC77: X | AF77: X | AK77: X | AL77: X | AM77: X | AO77: X | AP77: X | AQ77: X | BP77: X | BV77: X | BX77: X | BY77: X | BZ77: X | CB77: X
B78: ECH4 | C78: Total CH4 emissions | D78: KtCH4 | E78: X | F78: X | Z78: X | AC78: X | AF78: X | AK78: X | AL78: X | AM78: X | AO78: X | BP78: X | BV78: X | BW78: X | BZ78: X | CA78: X
B79: EN2O | C79: Total N2O emissions | D79: KtN2O | E79: X | F79: X | G79: X | H79: X | K79: X | N79: X | O79: X | U79: X | X79: X | Y79: X | Z79: X | AC79: X | AF79: X | AK79: X | AL79: X | AM79: X | AO79: X | AP79: X | AQ79: X | BP79: X | BV79: X | BX79: X | BY79: X | BZ79: X | CB79: X
B80: CTAX | C80: Carbon tax level | D80: USD/tCO2e | E80: X
B81: TGHG | C81: Emission reduction from mitigation technologies | D81: MtCO2e | E81: X | F81: X | G81: X | H81: X | K81: X | N81: X | O81: X | U81: X | X81: X | Y81: X | Z81: X | AC81: X | AF81: X | AK81: X | AL81: X | AM81: X | AO81: X | AP81: X | AQ81: X | BW81: X | BX81: X | BY81: X | BZ81: X | CA81: X | CB81: X
B82: VEGC | C82: Aboveground carbon stocks in vegetation | D82: tC/ha | E82: X | Z82: X | AO82: X | AP82: X | AR82: X | BQ82: X | BR82: X
B83: SOC | C83: Soil organic carbon stocks | D83: tC/ha | E83: X | Z83: X | AO83: X | AP83: X | AR83: X | BQ83: X | BR83: X
B84: BII | C84: Biodiversity Intactness Index (BII) | D84: index | E84: X | Z84: X | AO84: X | AP84: X | AR84: X | BQ84: X | BR84: X
B85: MSA_plants | C85: Terrestrial Mean Species Abundance (MSA) - Plants | D85: index | E85: X | Z85: X | AO85: X | AP85: X | AR85: X | BQ85: X | BR85: X
B86: MSA_vert | C86: Terrestrial Mean Species Abundance (MSA) - Vertebrates | D86: index | E86: X | Z86: X | AO86: X | AP86: X | AR86: X | BQ86: X | BR86: X
B87: FBI | C87: Farmland Birds Index (FBI) | D87: index (2000=1) | E87: X | Z87: X | AO87: X | AP87: X | AR87: X | BQ87: X | BR87: X
B88: FRRS | C88: Fraction of remaining species (cSAR) | D88: share | E88: X | Z88: X | AO88: X | AP88: X | AR88: X | BQ88: X | BR88: X
B89: BFP | C89: Biodiversity friendly practices Indicator (BFP) / Paracchini-Britz index | D89: index | E89: X | Z89: X | AO89: X | AP89: X | AR89: X | BQ89: X | BR89: X
B90: AREA_org | C90: Agricultural area under organic farming | D90: 1000 ha | E90: X | Z90: X | AO90: X | AP90: X
B91: CDI | C91: Crop diversity index | D91: index | Z91: X
B92: AREA_aem | C92: Area in Agri-Environmental Measures (excl. organic farming) | D92: 1000 ha | E92: X | Z92: X | AO92: X | AP92: X
B93: AREA_lft | C93: Agricultural land covered with landscape features | D93: 1000 ha | E93: X | Z93: X | AO93: X | AP93: X
B94: AREA_til | C94: Agricultural land with reduced tillage practices | D94: 1000 ha | E94: X | Z94: X | AO94: X | AP94: X
B95: AREA_wetland | C95: Agricultural land on wetland soils | D95: 1000 ha | E95: X | Z95: X | AO95: X | AP95: X
B96: AREA_biochar | C96: Agricultural land with biochar measures | D96: 1000 ha | E96: X | Z96: X | AO96: X | AP96: X
B97: AREA_agrofor | C97: Agricultural land with agroforestry or silvopastures | D97: 1000 ha | E97: X | Z97: X | AO97: X | AP97: X
B98: AREA_intensive | C98: Agricultural land under intensive management | D98: 1000 ha | E98: X | Z98: X | AO98: X | AP98: X
B99: AREA_extensive | C99: Agricultural land under extensive management | D99: 1000 ha | E99: X | Z99: X | AO99: X | AP99: X
B100: FRTN | C100: Fertilizer use nitrogen | D100: 1000 t | E100: X | F100: X | G100: X | H100: X | K100: X | N100: X | O100: X | U100: X | X100: X | Y100: X | Z100: X | AO100: X | AP100: X
B101: FRTIN | C101: Inorganic fertilizer use nitrogen | D101: 1000 t | E101: X | F101: X | G101: X | H101: X | K101: X | N101: X | O101: X | U101: X | X101: X | Y101: X | Z101: X | AO101: X | AP101: X
B102: FRTON | C102: Organic fertilizer use nitrogen | D102: 1000 t | E102: X | F102: X | G102: X | H102: X | K102: X | N102: X | O102: X | U102: X | X102: X | Y102: X | Z102: X | AO102: X | AP102: X
B103: NBAL | C103: Gross nitrogen balance | D103: 1000 t | E103: X | Z103: X | AO103: X | AP103: X
...

Sheet Regions
A1: REGIONS TO BE REPORTED AND VALIDATED IN ACCELERATOR
A2: Regions | G2: MAPPING | K2: AgMIP | N2: country-NUTS1-NUTS2 mapping
A3: Code | B3: Region | C3: Details | D3: Comment | G3: Country | H3: ISO2 | I3: ISO3 | J3: ISO# | K3: AggCode | N3: Code 2021 | O3: Country | P3: NUTS level 1 | Q3: NUTS level 2
A4: CAN | B4: Canada | C4: Canada | G4: Afghanistan | H4: AF | I4: AFG | J4: 4 | K4: OAS | N4: BE10 | O4: Belgique/België | P4: Région de Bruxelles-Capitale/Brussels Hoofdstedelijk Gewest | Q4: Région de Bruxelles-Capitale/ Brussels Hoofdstedelijk Gewest
A5: USA | B5: USA | C5: United States of America | G5: Albania | H5: AL | I5: ALB | J5: 8 | K5: EUR | N5: BE21 | O5: Belgique/België | P5: Vlaams Gewest | Q5: Prov. Antwerpen
A6: BRA | B6: Brazil | C6: Brazil | G6: Algeria | H6: DZ | I6: DZA | J6: 12 | K6: MEN | N6: BE22 | O6: Belgique/België | P6: Vlaams Gewest | Q6: Prov. Limburg (BE)
A7: OSA | B7: Other S&C America | C7: Other South, Central America & Caribbean (incl. Mexico) | G7: Andorra | H7: AD | I7: AND | J7: 20 | K7: EUR | N7: BE23 | O7: Belgique/België | P7: Vlaams Gewest | Q7: Prov. Oost-Vlaanderen
A8: FSU | B8: Former Soviet Union | C8: Former Soviet Union (European and Asian) | G8: Angola | H8: AO | I8: AGO | J8: 24 | K8: SSA | N8: BE24 | O8: Belgique/België | P8: Vlaams Gewest | Q8: Prov. Vlaams-Brabant
A9: EUR | B9: Europe | C9: Europe (excl. Turkey) | G9: Anguilla | H9: AI | I9: AIA | J9: 660 | K9: OSA | N9: BE25 | O9: Belgique/België | P9: Vlaams Gewest | Q9: Prov. West-Vlaanderen
A10: MEN | B10: Middle-East/North Afr. | C10: Middle-East / North Africa (incl. Turkey) | G10: Antigua and Barbuda | H10: AG | I10: ATG | J10: 28 | K10: OSA | N10: BE31 | O10: Belgique/België | P10: Région wallonne | Q10: Prov. Brabant Wallon
A11: SSA | B11: Sub-Saharan Afr. | C11: Sub-Saharan Africa | G11: Argentina | H11: AR | I11: ARG | J11: 32 | K11: OSA | N11: BE32 | O11: Belgique/België | P11: Région wallonne | Q11: Prov. Hainaut
A12: CHN | B12: China | C12: China (incl Hong-Kong, Macao) | G12: Armenia | H12: AM | I12: ARM | J12: 51 | K12: FSU | N12: BE33 | O12: Belgique/België | P12: Région wallonne | Q12: Prov. Liège
A13: IND | B13: India | C13: India | G13: Aruba | H13: AW | I13: ABW | J13: 533 | K13: OSA | N13: BE34 | O13: Belgique/België | P13: Région wallonne | Q13: Prov. Luxembourg (BE)
A14: SEA | B14: South-East Asia | C14: South-East Asia (incl. Japan, Taiwan) | G14: Australia | H14: AU | I14: AUS | J14: 36 | K14: ANZ | N14: BE35 | O14: Belgique/België | P14: Région wallonne | Q14: Prov. Namur
A15: OAS | B15: Other Asia | C15: Other Asia (incl. Other Oceania) | G15: Austria | H15: AT | I15: AUT | J15: 40 | K15: EUR | N15: BG31 | O15: Bulgaria | P15: Severna i Yugoiztochna Bulgaria | Q15: Severozapaden
A16: ANZ | B16: Australia/New Zealand | C16: Australia/New Zealand | G16: Azerbaijan | H16: AZ | I16: AZE | J16: 31 | K16: FSU | N16: BG32 | O16: Bulgaria | P16: Severna i Yugoiztochna Bulgaria | Q16: Severen tsentralen
G17: Bahamas | H17: BS | I17: BHS | J17: 44 | K17: OSA | N17: BG33 | O17: Bulgaria | P17: Severna i Yugoiztochna Bulgaria | Q17: Severoiztochen
A18: NAM | B18: North America | C18: North America (Canada & USA) | D18: CAN+USA | G18: Bahrain | H18: BH | I18: BHR | J18: 48 | K18: MEN | N18: BG34 | O18: Bulgaria | P18: Severna i Yugoiztochna Bulgaria | Q18: Yugoiztochen
A19: OAM | B19: S&C America | C19: Other Americas (South, Central & Caribbean) | D19: BRA+OSA | G19: Bangladesh | H19: BD | I19: BGD | J19: 50 | K19: OAS | N19: BG41 | O19: Bulgaria | P19: Yugozapadna i Yuzhna tsentralna Bulgaria | Q19: Yugozapaden
A20: AME | B20: Africa & Middle East | C20: Africa & Middle East | D20: MEN + SSA | G20: Barbados | H20: BB | I20: BRB | J20: 52 | K20: OSA | N20: BG42 | O20: Bulgaria | P20: Yugozapadna i Yuzhna tsentralna Bulgaria | Q20: Yuzhen tsentralen
A21: SAS | B21: Southern Asia | C21: Southern Asia | D21: CHN + IND +SEA + OAS | G21: Belarus | H21: BY | I21: BLR | J21: 112 | K21: FSU | N21: CZ01 | O21: Česko | P21: Česko | Q21: Praha
G22: Belgium | H22: BE | I22: BEL | J22: 56 | K22: EUR | N22: CZ02 | O22: Česko | P22: Česko | Q22: Střední Čechy
A23: WLD | B23: World | C23: World | G23: Belize | H23: BZ | I23: BLZ | J23: 84 | K23: OSA | N23: CZ03 | O23: Česko | P23: Česko | Q23: Jihozápad
G24: Benin | H24: BJ | I24: BEN | J24: 204 | K24: SSA | N24: CZ04 | O24: Česko | P24: Česko | Q24: Severozápad
A25: European Union | G25: Bermuda | H25: BM | I25: BMU | J25: 60 | K25: OSA | N25: CZ05 | O25: Česko | P25: Česko | Q25: Severovýchod
A26: EUE | B26: European Union | C26: EU27 Members States | G26: Bhutan | H26: BT | I26: BTN | J26: 64 | K26: OAS | N26: CZ06 | O26: Česko | P26: Česko | Q26: Jihovýchod
A27: AUT | B27: Austria | G27: Bolivia | H27: BO | I27: BOL | J27: 68 | K27: OSA | N27: CZ07 | O27: Česko | P27: Česko | Q27: Střední Morava
A28: BEL | B28: Belgium | G28: Bosnia and Herzegovina | H28: BA | I28: BIH | J28: 70 | K28: EUR | N28: CZ08 | O28: Česko | P28: Česko | Q28: Moravskoslezsko
A29: BGR | B29: Bulgaria | G29: Botswana | H29: BW | I29: BWA | J29: 72 | K29: SSA | N29: DK01 | O29: Danmark | P29: Danmark | Q29: Hovedstaden
A30: CYP | B30: Cyprus | G30: Brazil | H30: BR | I30: BRA | J30: 76 | K30: BRA | N30: DK02 | O30: Danmark | P30: Danmark | Q30: Sjælland
A31: CZE | B31: Czech Republic | G31: British Virgin Islands | H31: VG | I31: VGB | J31: 92 | K31: OSA | N31: DK03 | O31: Danmark | P31: Danmark | Q31: Syddanmark
A32: DEU | B32: Germany | G32: Brunei Darussalam | H32: BN | I32: BRN | J32: 96 | K32: SEA | N32: DK04 | O32: Danmark | P32: Danmark | Q32: Midtjylland
A33: DNK | B33: Denmark | G33: Bulgaria | H33: BG | I33: BGR | J33: 100 | K33: EUR | N33: DK05 | O33: Danmark | P33: Danmark | Q33: Nordjylland
A34: ESP | B34: Spain | G34: Burkina Faso | H34: BF | I34: BFA | J34: 854 | K34: SSA | N34: DE11 | O34: Deutschland | P34: Baden-Württemberg | Q34: Stuttgart
A35: EST | B35: Estonia | G35: Burundi | H35: BI | I35: BDI | J35: 108 | K35: SSA | N35: DE12 | O35: Deutschland | P35: Baden-Württemberg | Q35: Karlsruhe
A36: FIN | B36: Finland | G36: Cambodia | H36: KH | I36: KHM | J36: 116 | K36: SEA | N36: DE13 | O36: Deutschland | P36: Baden-Württemberg | Q36: Freiburg
A37: FRA | B37: France | G37: Cameroon | H37: CM | I37: CMR | J37: 120 | K37: SSA | N37: DE14 | O37: Deutschland | P37: Baden-Württemberg | Q37: Tübingen
A38: GRC | B38: Greece | G38: Canada | H38: CA | I38: CAN | J38: 124 | K38: CAN | N38: DE21 | O38: Deutschland | P38: Bayern | Q38: Oberbayern
... A58: REU | B58: Rest of Europe | G58: Djibouti | H58: DJ | I58: DJI | J58: 262 | K58: SSA | N58: DEA2 | O58: Deutschland | P58: Nordrhein-Westfalen | Q58: Köln
G59: Dominica | H59: DM | I59: DMA | J59: 212 | K59: OSA | N59: DEA3 | O59: Deutschland | P59: Nordrhein-Westfalen | Q59: Münster
A60: NUTS2 | B60: add English names! @Ipsita | G60: Dominican Republic | H60: DO | I60: DOM | J60: 214 | K60: OSA | N60: DEA4 | O60: Deutschland | P60: Nordrhein-Westfalen | Q60: Detmold
A61: BE10 | G61: Ecuador | H61: EC | I61: ECU | J61: 218 | K61: OSA | N61: DEA5 | O61: Deutschland | P61: Nordrhein-Westfalen | Q61: Arnsberg
A62: BE21 | G62: Egypt | H62: EG | I62: EGY | J62: 818 | K62: MEN | N62: DEB1 | O62: Deutschland | P62: Rheinland-Pfalz | Q62: Koblenz
A63: BE22 | G63: El Salvador | H63: SV | I63: SLV | J63: 222 | K63: OSA | N63: DEB2 | O63: Deutschland | P63: Rheinland-Pfalz | Q63: Trier
A64: BE23 | G64: Equatorial Guinea | H64: GQ | I64: GNQ | J64: 226 | K64: SSA | N64: DEB3 | O64: Deutschland | P64: Rheinland-Pfalz | Q64: Rheinhessen-Pfalz
A65: BE24 | G65: Eritrea | H65: ER | I65: ERI | J65: 232 | K65: SSA | N65: 36861 | O65: Deutschland | P65: Saarland | Q65: Saarland
A66: BE25 | G66: Estonia | H66: EE | I66: EST | J66: 233 | K66: EUR | N66: DED2 | O66: Deutschland | P66: Sachsen | Q66: Dresden
A67: BE31 | G67: Ethiopia | H67: ET | I67: ETH | J67: 231 | K67: SSA | N67: DED4 | O67: Deutschland | P67: Sachsen | Q67: Chemnitz
A68: BE32 | G68: Falkland Islands | H68: FK | I68: FLK | J68: 238 | K68: OSA | N68: DED5 | O68: Deutschland | P68: Sachsen | Q68: Leipzig
A69: BE33 | G69: Fiji | H69: FJ | I69: FJI | J69: 242 | K69: OAS | N69: DEE0 | O69: Deutschland | P69: Sachsen-Anhalt | Q69: Sachsen-Anhalt
A70: BE34 | G70: Finland | H70: FI | I70: FIN | J70: 246 | K70: EUR | N70: DEF0 | O70: Deutschland | P70: Schleswig-Holstein | Q70: Schleswig-Holstein
A71: BE35 | G71: France | H71: FR | I71: FRA | J71: 250 | K71: EUR | N71: DEG0 | O71: Deutschland | P71: Thüringen | Q71: Thüringen
A72: BG31 | G72: French Polynesia | H72: PF | I72: PYF | J72: 258 | K72: OAS | N72: EE00 | O72: Eesti | P72: Eesti | Q72: Eesti
A73: BG32 | G73: Gabon | H73: GA | I73: GAB | J73: 266 | K73: SSA | N73: IE04 | O73: Éire/Ireland | P73: Ireland | Q73: Northern and Western
A74: BG33 | G74: Gambia | H74: GM | I74: GMB | J74: 270 | K74: SSA | N74: IE05 | O74: Éire/Ireland | P74: Ireland | Q74: Southern
A75: BG34 | G75: Georgia | H75: GE | I75: GEO | J75: 268 | K75: FSU | N75: IE06 | O75: Éire/Ireland | P75: Ireland | Q75: Eastern and Midland
A76: BG41 | G76: Germany | H76: DE | I76: DEU | J76: 276 | K76: EUR | N76: EL30 | O76: Elláda | P76: Attiki | Q76: Attiki
A77: BG42 | G77: Ghana | H77: GH | I77: GHA | J77: 288 | K77: SSA | N77: EL41 | O77: Elláda | P77: Nisia Aigaiou, Kriti | Q77: Voreio Aigaio
... A121: DEB3 | G121: Mali | H121: ML | I121: MLI | J121: 466 | K121: SSA | N121: FRI1 | O121: France | P121: Nouvelle-Aquitaine | Q121: Aquitaine
A122: 36861 | G122: Malta | H122: MT | I122: MLT | J122: 470 | K122: EUR | N122: FRI2 | O122: France | P122: Nouvelle-Aquitaine | Q122: Limousin
A123: DED2 | G123: Marshall Islands | H123: MH | I123: MHL | J123: 584 | K123: OAS | N123: FRI3 | O123: France | P123: Nouvelle-Aquitaine | Q123: Poitou-Charentes
A124: DED4 | G124: Mauritania | H124: MR | I124: MRT | J124: 478 | K124: SSA | N124: FRJ1 | O124: France | P124: Occitanie | Q124: Languedoc-Roussillon
A125: DED5 | G125: Mauritius | H125: MU | I125: MUS | J125: 480 | K125: SSA | N125: FRJ2 | O125: France | P125: Occitanie | Q125: Midi-Pyrénées
A126: DEE0 | G126: Mexico | H126: MX | I126: MEX | J126: 484 | K126: OSA | N126: FRK1 | O126: France | P126: Auvergne-Rhône-Alpes | Q126: Auvergne
A127: DEF0 | G127: Micronesia (Federated States of) | H127: FM | I127: FSM | J127: 583 | K127: OAS | N127: FRK2 | O127: France | P127: Auvergne-Rhône-Alpes | Q127: Rhône-Alpes
A128: DEG0 | G128: Monaco | H128: MC | I128: MCO | J128: 492 | K128: EUR | N128: FRL0 | O128: France | P128: Provence-Alpes-Côte d’Azur | Q128: Provence-Alpes-Côte d’Azur
A129: EE00 | G129: Mongolia | H129: MN | I129: MNG | J129: 496 | K129: OAS | N129: FRM0 | O129: France | P129: Corse | Q129: Corse
A130: IE04 | G130: Montenegro | H130: ME | I130: MNE | J130: 499 | K130: EUR | N130: FRY1 | O130: France | P130: RUP FR — Régions Ultrapériphériques Françaises | Q130: Guadeloupe
A131: IE05 | G131: Montserrat | H131: MS | I131: MSR | J131: 500 | K131: OSA | N131: FRY2 | O131: France | P131: RUP FR — Régions Ultrapériphériques Françaises | Q131: Martinique
A132: IE06 | G132: Morocco | H132: MA | I132: MAR | J132: 504 | K132: MEN | N132: FRY3 | O132: France | P132: RUP FR — Régions Ultrapériphériques Françaises | Q132: Guyane
A133: EL30 | G133: Mozambique | H133: MZ | I133: MOZ | J133: 508 | K133: SSA | N133: FRY4 | O133: France | P133: RUP FR — Régions Ultrapériphériques Françaises | Q133: La Réunion
A134: EL41 | G134: Myanmar (Burma) | H134: MM | I134: MMR | J134: 104 | K134: SEA | N134: FRY5 | O134: France | P134: RUP FR — Régions Ultrapériphériques Françaises | Q134: Mayotte
... A138: EL52 | G138: Netherlands | H138: NL | I138: NLD | J138: 528 | K138: EUR | N138: HR06 | O138: Hrvatska | P138: Hrvatska | Q138: Sjeverna Hrvatska
A139: EL53 | G139: Netherlands Antilles | H139: #N/A | I139: ANT | J139: #N/A | K139: OSA | N139: ITC1 | O139: Italia | P139: Nord-Ovest | Q139: Piemonte
A140: EL54 | G140: New Caledonia | H140: NC | I140: NCL | J140: 540 | K140: OAS | N140: ITC2 | O140: Italia | P140: Nord-Ovest | Q140: Valle d’Aosta/Vallée d’Aoste
A141: EL61 | G141: New Zealand | H141: NZ | I141: NZL | J141: 554 | K141: ANZ | N141: ITC3 | O141: Italia | P141: Nord-Ovest | Q141: Liguria
A142: EL62 | G142: Nicaragua | H142: NI | I142: NIC | J142: 558 | K142: OSA | N142: ITC4 | O142: Italia | P142: Nord-Ovest | Q142: Lombardia
A143: EL63 | G143: Niger | H143: NE | I143: NER | J143: 562 | K143: SSA | N143: ITF1 | O143: Italia | P143: Sud | Q143: Abruzzo
A144: EL64 | G144: Nigeria | H144: NG | I144: NGA | J144: 566 | K144: SSA | N144: ITF2 | O144: Italia | P144: Sud | Q144: Molise
A145: EL65 | G145: Niue | H145: NU | I145: NIU | J145: 570 | K145: OAS | N145: ITF3 | O145: Italia | P145: Sud | Q145: Campania
A146: ES11 | G146: Norway | H146: NO | I146: NOR | J146: 578 | K146: EUR | N146: ITF4 | O146: Italia | P146: Sud | Q146: Puglia
A147: ES12 | G147: Oman | H147: OM | I147: OMN | J147: 512 | K147: MEN | N147: ITF5 | O147: Italia | P147: Sud | Q147: Basilicata
A148: ES13 | G148: Pakistan | H148: PK | I148: PAK | J148: 586 | K148: OAS | N148: ITF6 | O148: Italia | P148: Sud | Q148: Calabria
A149: ES21 | G149: Palau | H149: PW | I149: PLW | J149: 585 | K149: OAS | N149: ITG1 | O149: Italia | P149: Isole | Q149: Sicilia
A150: ES22 | G150: Palestinian Territories | H150: PS | I150: PSE | J150: 275 | K150: MEN | N150: ITG2 | O150: Italia | P150: Isole | Q150: Sardegna
A151: ES23 | G151: Panama | H151: PA | I151: PAN | J151: 591 | K151: OSA | N151: ITH1 | O151: Italia | P151: Nord-Est | Q151: Provincia Autonoma di Bolzano/Bozen
... A227: HU31 | G227: US Virgin Islands | H227: VI | I227: VIR | J227: 850 | K227: OSA | N227: SI03 | O227: Slovenija | P227: Slovenija | Q227: Vzhodna Slovenija
A228: HU32 | N228: SI04 | O228: Slovenija | P228: Slovenija | Q228: Zahodna Slovenija
A229: HU33 | N229: SK01 | O229: Slovensko | P229: Slovensko | Q229: Bratislavský kraj
A230: MT00 | N230: SK02 | O230: Slovensko | P230: Slovensko | Q230: Západné Slovensko
A231: NL11 | N231: SK03 | O231: Slovensko | P231: Slovensko | Q231: Stredné Slovensko
A232: NL12 | N232: SK04 | O232: Slovensko | P232: Slovensko | Q232: Východné Slovensko
A233: NL13 | N233: FI19 | O233: Suomi/Finland | P233: Manner-Suomi | Q233: Länsi-Suomi
A234: NL21 | N234: FI1B | O234: Suomi/Finland | P234: Manner-Suomi | Q234: Helsinki-Uusimaa
A235: NL22 | N235: FI1C | O235: Suomi/Finland | P235: Manner-Suomi | Q235: Etelä-Suomi
A236: NL23 | N236: FI1D | O236: Suomi/Finland | P236: Manner-Suomi | Q236: Pohjois- ja Itä-Suomi
A237: NL31 | N237: FI20 | O237: Suomi/Finland | P237: Åland | Q237: Åland
A238: NL32 | N238: SE11 | O238: Sverige | P238: Östra Sverige | Q238: Stockholm
A239: NL33 | N239: SE12 | O239: Sverige | P239: Östra Sverige | Q239: Östra Mellansverige
... A337: UKL2 | N337: TRC3 | O337: Türkiye | P337: Güneydoğu Anadolu | Q337: Mardin, Batman, Şırnak, Siirt
...

Sheet Units
A1: Units | B1: Description
A2: million
A3: bn USD 2005 MER
A4: USD/t
A5: 1000 ha
A6: t/ha
A7: multiplier (unitless)
A8: kg prt/ha
A9: kg prt/kg prt
A10: 1000 t
A11: km3
A12: kcal/cap/d
A13: LSU | B13: livestock units, see https://ec.europa.eu/eurostat/statistics-explained/index.php?title=Glossary:Livestock_unit_(LSU)
A14: MtCO2e
A15: tCH4
A16: tN2O
A17: USD/tCO2e
A18: BII
A19: tC/ha
A20: 1000 t
A21: tN
A22: tP
A23: Mt NH3
A24: t | B24: tons
A25: 1000 head | B25: livestock numbers
A26: gprt/cap/day | B26: gram proteins per capita per day

Sheet Items
A2: Reporting sectors | E2: Commnets
B3: Code | C3: Description | D3: Link to GTAP sectors | E3: CAPRI | F3: AGMEMOD | G3: GLOBIOM | H3: IMAGE | I3: MAGNET
B4: RIC | C4: Rice (paddy equivalent) | D4: pdr (+ pcr in raw eq.) | F4: RE | I4: Only primary production
B5: WHT | C5: Wheat | D5: wht | F5: GR
B6: CGR | C6: Other cereal grains | D6: gro
B7: OSD | C7: Oilseeds and oil crops (raw equivalent) | D7: osd (+ vol in raw eq.) | I7: Only primary production
B8: SGC | C8: Sugar crops (raw equivalent) | D8: c_b (+ sgr in raw eq.) | I8: Only primary production
B9: VFN | C9: Vegetables, fruits, nuts (incl. roots and tubers) | D9: v_f
B10: PFB | C10: Plant based fibres | D10: pfb | I10: Refers to seed cotton, unginned for production and area
B11: ECP | C11: Energy crops | I11: Not explicitely present
B12: OCR | C12: Other crops | D12: ocr
B13: RUM | C13: Ruminant meats | D13: ctl (+ cmt in raw eq.) | I13: Only primary production
B14: NRM | C14: Non ruminant meats | D14: oap (+ omt in raw eq.) | I14: Only primary production
B15: DRY | C15: Dairy (raw milk equivalent) | D15: rmk (+ mil in raw eq.) | I15: Only primary production
B16: OAP | C16: Other animal products (wool, honey) | D16: wol
B17: GRS | C17: Grass
B18: OFD | C18: Other feed products
B19: FSH | C19: Fish | D19: fsh
B20: FOR | C20: Forestry products | D20: frs
A21: Sectors subcategories (same variables as parents)
B22: VFN|VEG | C22: Vegetables | D22: definition to be clarified in sheet "overview crop definitions" | I22: Available
B23: VFN|FRU | C23: Fruits | D23: definition to be clarified in sheet "overview crop definitions" | I23: Available
B24: VFN|NUT | C24: Nuts | D24: definition to be clarified in sheet "overview crop definitions" | I24: Available
B25: VFN|ROOT | C25: Roots & tubers | D25: definition to be clarified in sheet "overview crop definitions" | I25: Available
B26: VFN|PULS | C26: Pulses | D26: definition to be clarified in sheet "overview crop definitions" | I26: Available
B27: PFB|COT | C27: Cotton | I27: NA
B28: PFB|OPF | C28: other plant based fibres | I28: NA
B29: CGR|MAI | C29: Maize | I29: NA
B30: CGR|OCG | C30: other coarse grains | I30: NA
B31: OSD|SRS | C31: soya, rapeseed, sunflower | I31: NA
B32: OSD|OOC | C32: other oilseeds and oil crops | I32: NA
B33: NRM|PRK | C33: Pork meat | F33: NRM|PK | I33: NA
B34: NRM|PTM | C34: Poultry meat | F34: NRM|PTM | I34: NA
B35: NRM|EGG | C35: Poultry eggs | F35: NRM|PO | I35: NA
B36: NRM|ONR | C36: Other non-ruminant | F36: NRM|EG | I36: NA
B37: RUM|BEF | C37: beef | I37: Available
B38: RUM|ORU | C38: Other ruminant | I38: Available
B39: CRP|ARA | C39: Arable crops | I39: NA
B40: CRP|PRM | C40: Permanent crops | I40: NA
A41: Sectors aggregates
B42: CRP | C42: All crops | D42: = RIC + WHT + CGR + OSD + SGC + VFN + PFB + OCR
B43: LSP | C43: Livestock products | D43: = RUM + NRM + DRY + OAP
B44: AGR | C44: All agricultural products | D44: = CRP + LSP + OFD + GRS
B45: TOT | C45: Total (full economy, population, GDP, calories)
A47: LAND variable items
B48: CRP | C48: Cropland (including energy crops)
B49: GRS | C49: Grassland
B50: ONV | C50: Other natural land (mostly shrubland)
B51: FOR | C51: Managed and primary forest
B52: FOR|MAN | C52: Managed Forest
B53: FOR|PRIM | C53: Primary Forest
B54: NLD | C54: Non arable land (OLD+BUI = desert etc + built-up areas…)
B55: BUI | C55: Built up areas
B56: OLD | C56: Other land except CRP,GRS,ONV,FOR,BUI (desert, glaciers, etc)
A57: LAND aggregates/subitems
B58: AGR | C58: Cropland + grassland
B59: ECP | C59: Energy crops (included in cropland)
A60: Production factors and intermediates
B61: LAB | C61: Labor
B62: CAP | C62: Capital
B63: FRT | C63: Fertiliser
B64: FF | C64: Fossil fuel
B65: ELEC | C65: Electricity
A66: Processed food, food services, and nonfood
B67: PRAG | C67: Primary agriculture & fish | D67: These four add up tot total economy for magnet
B68: PRFD | C68: Processed food sectors
B69: PDSV | C69: Food services
B70: NONF | C70: Non food sectors
A72: Biochemicals
B73: BC20 | C73: Total biobased chemicals (C20)
A75: Emission categories
B76: LUC | C76: Land-use change
B77: AFOLU | C77: Agriculture, Forestry, Land use-change
B78: WEM | C78: Wetland emissions
B79: ENT | C79: Enteric Fermentation
B80: MAS | C80: Manure applied to soils
B81: MGR | C81: Manure dropped on pasture
B82: MMG | C82: Manure mangement
B83: RCC | C83: Rice cultivation
B84: SFR | C84: Synthetic fertilizer application

Sheet Overview crop definitions
B1: Crop definitions based on gtap categories, and inspired on Table 2.1. of 'Economic Analysis of Land Use in Global Climate Change Policy', W. Hertel, 2009.
D2: % filters for most important crops based on world harvest area FAO
F4: Definitions in models (please add the best matching AgMIP category for each crop):
B5: Crop FAO | C5: AgMIP cat | D5: % area in AgMIP cat | E5: % Area all cat | F5: AIM/CGE | G5: GCAM | H5: MAgPIE | I5: MAGNET | J5: IMAGE | K5: GLOBIOM | L5: Impact | M5: CAPRI | N5: CLUMONDO | O5: AGMEMOD | P5: CGR | Q5: CGR2 | R5: CGR3 | S5: Column1
B6: Rice, paddy | C6: RIC | D6: 1 | E6: 0.12463543 | I6: RIC | J6: RIC | K6: RIC | L6: RIC | M6: RIC | N6: ARA | O6: RIC | P6: CGR | Q6: CGR
B7: Wheat | C7: WHT | D7: 1 | E7: 0.16659063 | I7: WHT | J7: WHT | K7: WHT | L7: WHT | M7: WHT | N7: ARA | O7: WHT | P7: CGR | Q7: CGR
B8: Maize | C8: CGR | D8: 0.51810527 | E8: 0.12646508 | I8: CGR | J8: CGR | K8: CGR | L8: CGR | M8: CGR|MAI | N8: ARA | O8: CGR|MAI | P8: CGR | Q8: CGR
B9: Barley | C9: CGR | D9: 0.14953728 | E9: 0.036500775 | I9: CGR | J9: CGR | K9: CGR | L9: CGR | M9: CGR|OCG | N9: ARA | O9: CGR|OCG
B10: Sorghum | C10: CGR | D10: 0.13330185 | E10: 0.032537847 | I10: CGR | J10: CGR | K10: CGR | L10: CGR | M10: CGR|OCG | N10: ARA | O10: CGR|OCG
B11: Millet | C11: CGR | D11: 0.11442755 | E11: 0.027930791 | I11: CGR | J11: CGR | K11: CGR | L11: CGR | M11: CGR|OCG | N11: ARA | O11: CGR|OCG
B12: Oats | C12: CGR | D12: 0.028732143 | E12: 0.0070132713 | I12: CGR | J12: CGR | L12: CGR | M12: CGR|OCG | N12: ARA | O12: CGR|OCG
B13: Rye | C13: CGR | D13: 0.015875845 | E13: 0.0038751586 | I13: CGR | J13: CGR | L13: CGR | M13: CGR|OCG | N13: ARA | O13: CGR|OCG
B14: Cereals, nes | C14: CGR | D14: 0.01434593 | E14: 0.0035017194 | I14: CGR | J14: CGR | L14: CGR | M14: CGR|OCG | N14: ARA | O14: CGR|OCG
B15: Triticale | C15: CGR | D15: 0.012640217 | E15: 0.0030853694 | I15: CGR | J15: CGR | L15: CGR | M15: CGR|OCG | N15: ARA | O15: CGR|OCG
B16: Buckwheat | C16: CGR | D16: 0.0060383838 | E16: 0.001473918 | I16: CGR | J16: CGR | L16: CGR | M16: CGR|OCG | N16: ARA
B17: Grain, mixed | C17: CGR | D17: 0.0039917897 | E17: 0.00097436186 | I17: CGR | J17: CGR | L17: CGR | M17: CGR|OCG | N17: ARA
B18: Fonio | C18: CGR | D18: 0.0018402322 | E18: 0.000449185 | I18: CGR | J18: CGR | L18: CGR | M18: CGR|OCG | N18: ARA
B19: Canary seed | C19: CGR | D19: 0.0008606072 | E19: 0.00021006689 | I19: CGR | J19: CGR | L19: CGR | M19: CGR|OCG | N19: ARA
B20: Quinoa | C20: CGR | D20: 0.00030290286 | E20: 7.393601e-05 | I20: CGR | J20: CGR | L20: CGR | M20: CGR|OCG | N20: ARA
B21: Coffee, green | C21: OCR | D21: 0.29541608 | E21: 0.0081150068 | I21: OCR | J21: OCR | L21: OCR | M21: OCR | N21: PRM
B22: Cocoa, beans | C22: OCR | D22: 0.27016925 | E22: 0.0074214827 | I22: OCR | J22: OCR | L22: OCR | M22: OCR | N22: PRM
B23: Tobacco, unmanufactured | C23: OCR | D23: 0.11090779 | E23: 0.0030466098 | I23: OCR | J23: OCR | L23: OCR | M23: OCR | N23: ARA
B24: Tea | C24: OCR | D24: 0.088325494 | E24: 0.0024262795 | I24: OCR | J24: OCR | L24: OCR | M24: OCR | N24: PRM
B25: Chillies and peppers, dry | C25: OCR | D25: 0.052848878 | E25: 0.0014517457 | I25: OCR | J25: OCR | L25: VFN | M25: OCR | N25: ARA
B26: Roots and tubers, nes | C26: OCR | D26: 0.03396986 | E26: 0.00093314367 | I26: OCR | J26: VFN | L26: OCR | M26: VFN|ROOT | N26: ARA | O26: VFN|ROOT
B27: Spices, nes | C27: OCR | D27: 0.027131129 | E27: 0.00074528544 | I27: OCR | J27: OCR | L27: OCR | M27: OCR | N27: PRM
B28: Lupins | C28: OCR | D28: 0.026696772 | E28: 0.00073335375 | I28: OCR | J28: VFN | L28: OCR | M28: VFN|PULS | N28: ARA | O28: VFN|PULS
B29: Anise, badian, fennel, coriander | C29: OCR | D29: 0.026208103 | E29: 0.00071993013 | I29: OCR | J29: OCR | L29: OCR | M29: OCR | N29: PRM
B30: Pepper (piper spp.) | C30: OCR | D30: 0.015869101 | E30: 0.00043592029 | I30: OCR | J30: OCR | L30: OCR | M30: OCR | N30: PRM
B31: Vetches | C31: OCR | D31: 0.014085813 | E31: 0.00038693381 | I31: OCR | J31: VFN | L31: OCR | M31: OCR | N31: ARA
B32: Cloves | C32: OCR | D32: 0.010927225 | E32: 0.00030016818 | I32: OCR | J32: OCR | L32: OCR | M32: OCR | N32: ARA
B33: Nutmeg, mace and cardamoms | C33: OCR | D33: 0.0083065355 | E33: 0.00022817848 | I33: OCR | J33: OCR | L33: OCR | M33: OCR | N33: PRM
B34: Ginger | C34: OCR | D34: 0.0075465019 | E34: 0.00020730055 | I34: OCR | J34: OCR | L34: OCR | M34: OCR | N34: PRM
B35: Cinnamon (canella) | C35: OCR | D35: 0.0064575059 | E35: 0.0001773861 | I35: OCR | J35: OCR | L35: OCR | M35: OCR | N35: PRM
B36: Vanilla | C36: OCR | D36: 0.0024225652 | E36: 6.6547269e-05 | I36: OCR | J36: OCR | L36: OCR | M36: OCR | N36: PRM
B37: Hops | C37: OCR | D37: 0.0021767562 | E37: 5.9794956e-05 | I37: OCR | J37: OCR | L37: OCR | M37: OCR | N37: PRM | R37: OSD
B38: Pyrethrum, dried | C38: OCR | D38: 0.00045673912 | E38: 1.2546511e-05 | I38: OCR | J38: OCR | L38: OCR | M38: OCR | N38: ARA
B39: Peppermint | C39: OCR | D39: 7.7901766e-05 | E39: 2.1399423e-06 | I39: OCR | J39: OCR | L39: OCR | M39: OCR | N39: ARA
B40: Soybeans | C40: OSD | D40: 0.43341346 | E40: 0.079338255 | I40: OSD | J40: OSD | K40: OSD | L40: OSD | M40: OSD|SRS | N40: ARA | O40: OSD|SRS
B41: Rapeseed | C41: OSD | D41: 0.13583429 | E41: 0.024865068 | I41: OSD | J41: OSD | K41: OSD | L41: OSD | M41: OSD|SRS | N41: ARA | O41: OSD|SRS
B42: Groundnuts, with shell | C42: OSD | D42: 0.1101688 | E42: 0.020166886 | I42: OSD | J42: OSD | K42: OSD | L42: OSD | M42: OSD|OOC | N42: ARA
B43: Sunflower seed | C43: OSD | D43: 0.09738587 | E43: 0.017826915 | I43: OSD | J43: OSD | K43: OSD | L43: OSD | M43: OSD|SRS | N43: ARA | O43: OSD|SRS
B44: Oil, palm fruit | C44: OSD | D44: 0.068054223 | E44: 0.012457627 | I44: OSD | J44: OSD | K44: OSD | L44: OSD | M44: OSD|OOC | N44: PRM | O44: OSD|OOC
B45: Coconuts | C45: OSD | D45: 0.049483271 | E45: 0.009058132 | I45: OSD | J45: OSD | L45: OSD | M45: OSD|OOC | N45: PRM
B46: Olives | C46: OSD | D46: 0.041573816 | E46: 0.0076102713 | I46: OSD | J46: OSD | L46: OSD | M46: OSD|OOC | N46: PRM | O46: OSD|OOC
B47: Sesame seed | C47: OSD | D47: 0.035355124 | E47: 0.0064719122 | I47: OSD | J47: OSD | L47: OSD | M47: OSD|OOC | N47: ARA
B48: Oilseeds nes | C48: OSD | D48: 0.0068112337 | E48: 0.0012468265 | I48: OSD | J48: OSD | L48: OSD | M48: OSD|OOC | N48: ARA
B49: Castor oil seed | C49: OSD | D49: 0.0064582352 | E49: 0.0011822086 | I49: OSD | J49: OSD | L49: OSD | M49: OSD|OOC | N49: ARA
B50: Melonseed | C50: OSD | D50: 0.0035217371 | E50: 0.00064466958 | I50: OSD | J50: OSD | L50: OSD | M50: OSD|OOC | N50: ARA
B51: Safflower seed | C51: OSD | D51: 0.00342736 | E51: 0.00062739344 | I51: OSD | J51: OSD | L51: OSD | M51: OSD|OOC | N51: ARA
B52: Mustard seed | C52: OSD | D52: 0.0033397088 | E52: 0.0006113485 | I52: OSD | J52: OCR | L52: OSD | M52: OSD|OOC | N52: ARA
B53: Karite nuts (sheanuts) | C53: OSD | D53: 0.0021370598 | E53: 0.00039119827 | I53: OSD | J53: OSD | L53: OSD | M53: OSD|OOC | N53: PRM
B54: Tallowtree seed | C54: OSD | D54: 0.0016769532 | E54: 0.00030697372 | I54: OSD | L54: OSD | M54: OSD|OOC | N54: ARA
B55: Tung nuts | C55: OSD | D55: 0.00072953317 | E55: 0.00013354428 | I55: OSD | J55: OSD | L55: OSD | M55: OSD|OOC | N55: PRM
B56: Poppy seed | C56: OSD | D56: 0.00062802147 | E56: 0.00011496211 | I56: OSD | J56: OSD | L56: OSD | M56: OSD|OOC | N56: ARA
B57: Jojoba seed | C57: OSD | D57: 1.3106169e-06 | E57: 2.3991422e-07 | I57: OSD | L57: OSD | M57: OSD|OOC | N57: ARA
B58: Seed cotton | C58: PFB | D58: 0.86274563 | E58: 0.024596417 | I58: PFB | J58: PFB | K58: PFB | L58: PFB | M58: PFB | N58: ARA
B59: Linseed | C59: OSD | D59: 0.056528008 | E59: 0.0016115833 | I59: OSD | J59: OSD | L59: OSD | M59: OSD|OOC | N59: ARA
B60: Jute | C60: PFB | D60: 0.033151937 | E60: 0.00094514401 | I60: PFB | J60: PFB | L60: OCR | M60: PFB | N60: ARA
B61: Sisal | C61: PFB | D61: 0.011362046 | E61: 0.00032392586 | I61: PFB | J61: PFB | L61: OCR | M61: PFB | N61: PRM
B62: Fibre crops nes | C62: PFB | D62: 0.010150304 | E62: 0.00028937975 | I62: PFB | J62: PFB | L62: OCR | M62: PFB | N62: ARA
B63: Flax fibre and tow | C63: PFB | D63: 0.0056459009 | E63: 0.00016096162 | I63: PFB | J63: PFB | L63: OCR | M63: PFB | N63: ARA
B64: Kapok fruit | C64: PFB | D64: 0.0053387849 | E64: 0.0001522059 | I64: PFB | J64: OSD | L64: OCR | M64: OSD|OOC | N64: ARA
B65: Bastfibres, other | C65: PFB | D65: 0.0047944455 | E65: 0.00013668708 | I65: PFB | J65: PFB | L65: OCR | M65: PFB | N65: ARA
B66: Manila fibre (abaca) | C66: PFB | D66: 0.0044353498 | E66: 0.00012644945 | I66: PFB | J66: PFB | L66: OCR | M66: PFB | N66: PRM
B67: Ramie | C67: PFB | D67: 0.0027316003 | E67: 7.7876466e-05 | I67: PFB | J67: PFB | L67: OCR | M67: PFB | N67: ARA
B68: Agave fibres nes | C68: PFB | D68: 0.0015288963 | E68: 4.3588017e-05 | I68: PFB | J68: PFB | L68: OCR | M68: PFB | N68: ARA | P68: RIC | Q68: RIC | R68: RIC
B69: Hemp tow waste | C69: PFB | D69: 0.0011391161 | E69: 3.2475592e-05 | I69: PFB | J69: PFB | L69: OCR | M69: PFB | N69: ARA
B70: Hempseed | C70: PFB | D70: 0.00044798343 | E70: 1.2771768e-05 | I70: PFB | J70: OSD | L70: OSD | M70: PFB | N70: ARA
B71: Sugar cane | C71: SGC | D71: 0.83149058 | E71: 0.018320845 | I71: SGC | J71: SGC | K71: SGC | L71: SGC | M71: SGC | N71: ARA
B72: Sugar beet | C72: SGC | D72: 0.16475209 | E72: 0.0036301043 | I72: SGC | J72: SGC | L72: SGC | M72: SGC | N72: ARA | O72: SGC
B73: Sugar crops, nes | C73: SGC | D73: 0.0037573357 | E73: 8.278815e-05 | I73: SGC | J73: SGC | L73: OCR | M73: OCR | N73: ARA
B74: Beans, dry | C74: VFN | D74: 0.12227713 | E74: 0.023981975 | I74: VFN|PULS | J74: VFN | K74: VFN | L74: VFN | M74: VFN|PULS | N74: ARA | O74: VFN|PULS
B75: Cassava | C75: VFN | D75: 0.07742518 | E75: 0.015185249 | I75: VFN|ROOT | J75: VFN | K75: VFN | L75: OCR | M75: VFN|ROOT | N75: ARA
B76: Potatoes | C76: VFN | D76: 0.073309508 | E76: 0.01437805 | I76: VFN|ROOT | J76: VFN | K76: VFN | L76: VFN | M76: VFN|ROOT | N76: ARA | O76: VFN|ROOT
B77: Vegetables, fresh nes | C77: VFN | D77: 0.072713379 | E77: 0.014261133 | I77: VFN|VEG | J77: VFN | L77: VFN | M77: VFN|VEG | N77: ARA | O77: VFN|VEG
B78: Chick peas | C78: VFN | D78: 0.047099152 | E78: 0.0092374644 | I78: VFN|PULS | J78: VFN | K78: VFN | L78: VFN | M78: VFN|PULS | N78: ARA
B79: Cow peas, dry | C79: VFN | D79: 0.045798755 | E79: 0.0089824202 | I79: VFN|PULS | J79: VFN | L79: VFN | M79: VFN|PULS | N79: ARA | O79: VFN|PULS
B80: Sweet potatoes | C80: VFN | D80: 0.033540021 | E80: 0.0065781387 | I80: VFN|ROOT | J80: VFN | K80: VFN | L80: OCR | M80: VFN|ROOT | N80: ARA
B81: Grapes | C81: VFN | D81: 0.027721054 | E81: 0.005436876 | I81: VFN|FRU | J81: VFN | L81: VFN | M81: VFN|FRU | N81: PRM
B82: Peas, dry | C82: VFN | D82: 0.025741362 | E82: 0.005048603 | I82: VFN|PULS | J82: VFN | L82: VFN | M82: VFN|PULS | N82: ARA
B83: Bananas | C83: VFN | D83: 0.021290833 | E83: 0.0041757294 | I83: VFN|FRU | J83: VFN | L83: VFN | M83: VFN|FRU | N83: PRM
B84: Cashew nuts, with shell | C84: VFN | D84: 0.020228157 | E84: 0.0039673088 | I84: VFN|NUT | J84: VFN | L84: VFN | M84: VFN|NUT | N84: PRM
B85: Mangoes, mangosteens, guavas | C85: VFN | D85: 0.019670428 | E85: 0.0038579225 | I85: VFN|FRU | J85: VFN | L85: VFN | M85: VFN|FRU | N85: PRM
B86: Yams | C86: VFN | D86: 0.019389576 | E86: 0.0038028395 | I86: VFN|ROOT | J86: VFN | L86: OCR | M86: VFN|ROOT | N86: ARA
B87: Pigeon peas | C87: VFN | D87: 0.019203039 | E87: 0.0037662545 | I87: VFN|PULS | J87: VFN | L87: VFN | M87: VFN|PULS | N87: ARA
B88: Plantains | C88: VFN | D88: 0.019082504 | E88: 0.0037426141 | I88: VFN|FRU | J88: VFN | L88: VFN | M88: VFN|FRU | N88: PRM
B89: Apples | C89: VFN | D89: 0.018991169 | E89: 0.0037247007 | I89: VFN|FRU | J89: VFN | L89: VFN | M89: VFN|FRU | N89: PRM | O89: VFN|FRU
B90: Pulses, nes | C90: VFN | D90: 0.018659034 | E90: 0.0036595598 | I90: VFN|PULS | J90: VFN | L90: VFN | M90: VFN|PULS | N90: ARA
B91: Tomatoes | C91: VFN | D91: 0.01768243 | E91: 0.0034680203 | I91: VFN|VEG | J91: VFN | L91: VFN | M91: VFN|VEG | N91: ARA | O91: VFN|VEG
B92: Fruit, fresh nes | C92: VFN | D92: 0.017628654 | E92: 0.0034574733 | I92: VFN|FRU | J92: VFN | L92: VFN | M92: VFN|FRU | N92: ARA
B93: Lentils | C93: VFN | D93: 0.017020209 | E93: 0.0033381403 | I93: VFN|PULS | J93: VFN | L93: VFN | M93: VFN|PULS | N93: ARA | O93: VFN|PULS
B94: Onions, dry | C94: VFN | D94: 0.016419356 | E94: 0.0032202961 | I94: VFN|VEG | J94: VFN | L94: VFN | M94: VFN|VEG | N94: ARA
B95: Oranges | C95: VFN | D95: 0.016232981 | E95: 0.0031837428 | I95: VFN|FRU | J95: VFN | L95: VFN | M95: VFN|FRU | N95: PRM | O95: VFN|FRU
B96: Watermelons | C96: VFN | D96: 0.013508446 | E96: 0.0026493851 | I96: VFN|VEG | J96: VFN | L96: VFN | M96: VFN|VEG | N96: ARA
B97: Fruit, tropical fresh nes | C97: VFN | D97: 0.011234372 | E97: 0.0022033753 | I97: VFN|FRU | J97: VFN | L97: VFN | M97: VFN|FRU | N97: PRM
B98: Broad beans, horse beans, dry | C98: VFN | D98: 0.0098899144 | E98: 0.0019396895 | I98: VFN|PULS | J98: VFN | L98: VFN | M98: VFN|PULS | N98: ARA
B99: Plums and sloes | C99: VFN | D99: 0.0093965304 | E99: 0.0018429231 | I99: VFN|FRU | J99: VFN | L99: VFN | M99: VFN|FRU | N99: PRM
B100: Cabbages and other brassicas | C100: VFN | D100: 0.0091393169 | E100: 0.0017924763 | I100: VFN|VEG | J100: VFN | L100: VFN | M100: VFN|VEG | N100: ARA
B101: Peas, green | C101: VFN | D101: 0.0086151392 | E101: 0.0016896704 | I101: VFN|PULS | J101: VFN | L101: VFN | M101: VFN|VEG | N101: ARA
...

Sheet Overview regional mapping
A1: AgMIP | C1: MAPPING | H1: Only deviations listed! | S1: CAPRI | W1: GLOBIOM | AA1: IMAGE | AE1: MAGNET | AJ1: IMPACT | AQ1: FAO
A2: AgMIP | B2: Descr | C2: Country | D2: ISO2 | E2: ISO3 | F2: ISO# | G2: % of world population | H2: GLOBIOM | I2: IMAGE | J2: CAPRI | K2: MAGNET | L2: IMPACT | S2: CAPRI | T2: ISO | U2: AGMIP | W2: ISO3 | X2: ALLCOUNTRY | Y2: AgMIP region | AA2: iso3 | AB2: IMAGE_reg_name | AC2: AGMIP_reg_name | AE2: ISO | AF2: GTAP | AG2: MAGNET | AH2: AgMIP | AJ2: ISO3 | AK2: IMPACT_CTY | AL2: AgMIP_Level_1 | AM2: AgMIP_Level_2 | AN2: AgMIP_Level_3 | AO2: Notes and exceptions (**) to AgMIP | AQ2: Area Code (ISO3) | AR2: Area | AS2: Element | AT2: Item | AU2: Year | AV2: Unit | AW2: Value
A3: ANZ | B3: =INDEX(Regions!B:B,MATCH(A3,Regions!A:A,0)) -> Australia/New Zealand | C3: Australia | D3: AU | E3: AUS | F3: 36 | G3: =INDEX(AW:AW,MATCH(E3,AQ:AQ,0))/INDEX(AW:AW,MATCH("World",AR:AR,0)) -> 0.0032344734 | H3: =IF(INDEX(Y:Y,MATCH(E3,W:W,0))=A3,"",INDEX(Y:Y,MATCH(E3,W:W,0))) | I3: =IF(INDEX(AC:AC,MATCH(E3,AA:AA,0))=A3,"",INDEX(AC:AC,MATCH(E3,AA:AA,0))) | J3: =IF(INDEX(U:U,MATCH(E3,T:T,0))=A3,"",INDEX(U:U,MATCH(E3,T:T,0))) | K3: =IF(INDEX(AH:AH,MATCH(E3,AE:AE,0))=A3,"",INDEX(AH:AH,MATCH(E3,AE:AE,0))) | S3: #N/A | T3: ABW | U3: #N/A | W3: ARG | X3: Argentina | Y3: OSA | AA3: CAN | AB3: Canada | AC3: CAN | AE3: AUS | AF3: aus | AG3: OCE | AH3: ANZ | AJ3: ABW | AK3: CRB | AL3: OSA | AN3: WLD | AQ3: AFG | AR3: Afghanistan | AS3: Total Population - Both sexes | AT3: Population - Est. & Proj. | AU3: 2014 | AV3: 1000 persons | AW3: 33370.794
A4: ANZ | B4: =INDEX(Regions!B:B,MATCH(A4,Regions!A:A,0)) -> Australia/New Zealand | C4: New Zealand | D4: NZ | E4: NZL | F4: 554 | G4: =INDEX(AW:AW,MATCH(E4,AQ:AQ,0))/INDEX(AW:AW,MATCH("World",AR:AR,0)) -> 0.00062609252 | H4: =IF(INDEX(Y:Y,MATCH(E4,W:W,0))=A4,"",INDEX(Y:Y,MATCH(E4,W:W,0))) | I4: =IF(INDEX(AC:AC,MATCH(E4,AA:AA,0))=A4,"",INDEX(AC:AC,MATCH(E4,AA:AA,0))) | J4: =IF(INDEX(U:U,MATCH(E4,T:T,0))=A4,"",INDEX(U:U,MATCH(E4,T:T,0))) | K4: =IF(INDEX(AH:AH,MATCH(E4,AE:AE,0))=A4,"",INDEX(AH:AH,MATCH(E4,AE:AE,0))) | S4: ASOCE_LDC | T4: AFG | U4: OAS | W4: AUS | X4: Australia | Y4: ANZ | AA4: SPM | AB4: USA | AC4: USA | AE4: CXR | AF4: aus | AG4: OCE | AH4: ANZ | AJ4: AFG | AK4: AFG | AL4: OAS | AM4: SAS | AN4: WLD | AQ4: ALB | AR4: Albania | AS4: Total Population - Both sexes | AT4: Population - Est. & Proj. | AU4: 2014 | AV4: 1000 persons | AW4: 2896.305
A5: BRA | B5: =INDEX(Regions!B:B,MATCH(A5,Regions!A:A,0)) -> Brazil | C5: Brazil | D5: BR | E5: BRA | F5: 76 | G5: =INDEX(AW:AW,MATCH(E5,AQ:AQ,0))/INDEX(AW:AW,MATCH("World",AR:AR,0)) -> 0.027793784 | H5: =IF(INDEX(Y:Y,MATCH(E5,W:W,0))=A5,"",INDEX(Y:Y,MATCH(E5,W:W,0))) | I5: =IF(INDEX(AC:AC,MATCH(E5,AA:AA,0))=A5,"",INDEX(AC:AC,MATCH(E5,AA:AA,0))) | J5: =IF(INDEX(U:U,MATCH(E5,T:T,0))=A5,"",INDEX(U:U,MATCH(E5,T:T,0))) | K5: =IF(INDEX(AH:AH,MATCH(E5,AE:AE,0))=A5,"",INDEX(AH:AH,MATCH(E5,AE:AE,0))) | S5: AFR_LDC | T5: AGO | U5: SSA | W5: BRA | X5: Brazil | Y5: BRA | AA5: USA | AB5: USA | AC5: USA | AE5: CCK | AF5: aus | AG5: OCE | AH5: ANZ | AJ5: AGO | AK5: AGO | AL5: SSA | AM5: AME | AN5: WLD | AQ5: DZA | AR5: Algeria | AS5: Total Population - Both sexes | AT5: Population - Est. & Proj. | AU5: 2014 | AV5: 1000 persons | AW5: 38923.692
A6: CAN | B6: =INDEX(Regions!B:B,MATCH(A6,Regions!A:A,0)) -> Canada | C6: Canada | D6: CA | E6: CAN | F6: 124 | G6: =INDEX(AW:AW,MATCH(E6,AQ:AQ,0))/INDEX(AW:AW,MATCH("World",AR:AR,0)) -> 0.0048886793 | H6: =IF(INDEX(Y:Y,MATCH(E6,W:W,0))=A6,"",INDEX(Y:Y,MATCH(E6,W:W,0))) | I6: =IF(INDEX(AC:AC,MATCH(E6,AA:AA,0))=A6,"",INDEX(AC:AC,MATCH(E6,AA:AA,0))) | J6: =IF(INDEX(U:U,MATCH(E6,T:T,0))=A6,"",INDEX(U:U,MATCH(E6,T:T,0))) | K6: =IF(INDEX(AH:AH,MATCH(E6,AE:AE,0))=A6,"",INDEX(AH:AH,MATCH(E6,AE:AE,0))) | S6: AL000000 | T6: ALB | U6: EUR | W6: CAN | X6: Canada | Y6: CAN | AA6: UMI | AB6: USA | AC6: USA | AE6: HMD | AF6: aus | AG6: OCE | AH6: ANZ | AJ6: AIA | AK6: CRB | AL6: OSA | AN6: WLD | AQ6: ASM | AR6: American Samoa | AS6: Total Population - Both sexes | AT6: Population - Est. & Proj. | AU6: 2014 | AV6: 1000 persons | AW6: 55.791
A7: CHN | B7: =INDEX(Regions!B:B,MATCH(A7,Regions!A:A,0)) -> China | C7: China | D7: CN | E7: CHN | F7: 156 | G7: =INDEX(AW:AW,MATCH(E7,AQ:AQ,0))/INDEX(AW:AW,MATCH("World",AR:AR,0)) -> 0.19610881 | H7: =IF(INDEX(Y:Y,MATCH(E7,W:W,0))=A7,"",INDEX(Y:Y,MATCH(E7,W:W,0))) | I7: =IF(INDEX(AC:AC,MATCH(E7,AA:AA,0))=A7,"",INDEX(AC:AC,MATCH(E7,AA:AA,0))) | J7: =IF(INDEX(U:U,MATCH(E7,T:T,0))=A7,"",INDEX(U:U,MATCH(E7,T:T,0))) | K7: =IF(INDEX(AH:AH,MATCH(E7,AE:AE,0))=A7,"",INDEX(AH:AH,MATCH(E7,AE:AE,0))) | S7: MIDEAST | T7: ARE | U7: MEN | W7: CHN | X7: China | Y7: CHN | AA7: MEX | AB7: Mexico | AC7: OSA | AE7: NFK | AF7: aus | AG7: OCE | AH7: ANZ | AJ7: ALA | AK7: FNP | AL7: EUR | AN7: WLD | AO7: Åland Islands | AQ7: AND | AR7: Andorra | AS7: Total Population - Both sexes | AT7: Population - Est. & Proj. | AU7: 2014 | AV7: 1000 persons | AW7: 79.213
A8: CHN | B8: =INDEX(Regions!B:B,MATCH(A8,Regions!A:A,0)) -> China | C8: Hong Kong | D8: HK | E8: HKG | F8: 344 | G8: =INDEX(AW:AW,MATCH(E8,AQ:AQ,0))/INDEX(AW:AW,MATCH("World",AR:AR,0)) -> 0.00097798295 | H8: =IF(INDEX(Y:Y,MATCH(E8,W:W,0))=A8,"",INDEX(Y:Y,MATCH(E8,W:W,0))) -> NotAccounted | I8: =IF(INDEX(AC:AC,MATCH(E8,AA:AA,0))=A8,"",INDEX(AC:AC,MATCH(E8,AA:AA,0))) | J8: =IF(INDEX(U:U,MATCH(E8,T:T,0))=A8,"",INDEX(U:U,MATCH(E8,T:T,0))) -> #N/A | K8: =IF(INDEX(AH:AH,MATCH(E8,AE:AE,0))=A8,"",INDEX(AH:AH,MATCH(E8,AE:AE,0))) | S8: ARG | T8: ARG | U8: OSA | W8: CMR | X8: Cameroon | Y8: SSA | AA8: AIA | AB8: Rest Central America | AC8: OSA | AE8: NZL | AF8: nzl | AG8: OCE | AH8: ANZ | AJ8: ALB | AK8: ALB | AL8: EUR | AN8: WLD | AQ8: AGO | AR8: Angola | AS8: Total Population - Both sexes | AT8: Population - Est. & Proj. | AU8: 2014 | AV8: 1000 persons | AW8: 26941.779
A9: CHN | B9: =INDEX(Regions!B:B,MATCH(A9,Regions!A:A,0)) -> China | C9: Macao, China | D9: MO | E9: MAC | F9: 446 | G9: =INDEX(AW:AW,MATCH(E9,AQ:AQ,0))/INDEX(AW:AW,MATCH("World",AR:AR,0)) -> 8.0902601e-05 | H9: =IF(INDEX(Y:Y,MATCH(E9,W:W,0))=A9,"",INDEX(Y:Y,MATCH(E9,W:W,0))) -> NotAccounted | I9: =IF(INDEX(AC:AC,MATCH(E9,AA:AA,0))=A9,"",INDEX(AC:AC,MATCH(E9,AA:AA,0))) | J9: =IF(INDEX(U:U,MATCH(E9,T:T,0))=A9,"",INDEX(U:U,MATCH(E9,T:T,0))) -> #N/A | K9: =IF(INDEX(AH:AH,MATCH(E9,AE:AE,0))=A9,"",INDEX(AH:AH,MATCH(E9,AE:AE,0))) | S9: FSU | T9: ARM | U9: FSU | W9: CAF | X9: CentAfrRep | Y9: SSA | AA9: ATG | AB9: Rest Central America | AC9: OSA | AE9: ASM | AF9: xoc | AG9: IDN | AH9: SEA | AJ9: AND | AK9: SPP | AL9: EUR | AN9: WLD | AQ9: AIA | AR9: Anguilla | AS9: Total Population - Both sexes | AT9: Population - Est. & Proj. | AU9: 2014 | AV9: 1000 persons | AW9: 14.112
A10: EUR | B10: =INDEX(Regions!B:B,MATCH(A10,Regions!A:A,0)) -> Europe | C10: Albania | D10: AL | E10: ALB | F10: 8 | G10: =INDEX(AW:AW,MATCH(E10,AQ:AQ,0))/INDEX(AW:AW,MATCH("World",AR:AR,0)) -> 0.00039701022 | H10: =IF(INDEX(Y:Y,MATCH(E10,W:W,0))=A10,"",INDEX(Y:Y,MATCH(E10,W:W,0))) | I10: =IF(INDEX(AC:AC,MATCH(E10,AA:AA,0))=A10,"",INDEX(AC:AC,MATCH(E10,AA:AA,0))) | J10: =IF(INDEX(U:U,MATCH(E10,T:T,0))=A10,"",INDEX(U:U,MATCH(E10,T:T,0))) | K10: =IF(INDEX(AH:AH,MATCH(E10,AE:AE,0))=A10,"",INDEX(AH:AH,MATCH(E10,AE:AE,0))) | S10: #N/A | T10: ASM | U10: #N/A | W10: COG | X10: CongoRep | Y10: SSA | AA10: ABW | AB10: Rest Central America | AC10: OSA | AE10: COK | AF10: xoc | AG10: IDN | AH10: SEA | AJ10: ANT | AK10: CRB | AL10: OSA | AN10: WLD | AQ10: ATG | AR10: Antigua and Barbuda | AS10: Total Population - Both sexes | AT10: Population - Est. & Proj. | AU10: 2014 | AV10: 1000 persons | AW10: 92.562
A11: EUR | B11: =INDEX(Regions!B:B,MATCH(A11,Regions!A:A,0)) -> Europe | C11: Andorra | D11: AD | E11: AND | F11: 20 | G11: =INDEX(AW:AW,MATCH(E11,AQ:AQ,0))/INDEX(AW:AW,MATCH("World",AR:AR,0)) -> 1.08581e-05 | H11: =IF(INDEX(Y:Y,MATCH(E11,W:W,0))=A11,"",INDEX(Y:Y,MATCH(E11,W:W,0))) -> NotAccounted | I11: =IF(INDEX(AC:AC,MATCH(E11,AA:AA,0))=A11,"",INDEX(AC:AC,MATCH(E11,AA:AA,0))) | J11: =IF(INDEX(U:U,MATCH(E11,T:T,0))=A11,"",INDEX(U:U,MATCH(E11,T:T,0))) -> #N/A | K11: =IF(INDEX(AH:AH,MATCH(E11,AE:AE,0))=A11,"",INDEX(AH:AH,MATCH(E11,AE:AE,0))) | S11: MSA_ACP | T11: ATG | U11: OSA | W11: COD | X11: CongoDemR | Y11: SSA | AA11: BHS | AB11: Rest Central America | AC11: OSA | AE11: FJI | AF11: xoc | AG11: IDN | AH11: SEA | AJ11: ARE | AK11: RAP | AL11: MEN | AM11: AME | AN11: WLD | AQ11: ARG | AR11: Argentina | AS11: Total Population - Both sexes | AT11: Population - Est. & Proj. | AU11: 2014 | AV11: 1000 persons | AW11: 42637.511
A12: EUR | B12: =INDEX(Regions!B:B,MATCH(A12,Regions!A:A,0)) -> Europe | C12: Austria | D12: AT | E12: AUT | F12: 40 | G12: =INDEX(AW:AW,MATCH(E12,AQ:AQ,0))/INDEX(AW:AW,MATCH("World",AR:AR,0)) -> 0.0011809281 | H12: =IF(INDEX(Y:Y,MATCH(E12,W:W,0))=A12,"",INDEX(Y:Y,MATCH(E12,W:W,0))) | I12: =IF(INDEX(AC:AC,MATCH(E12,AA:AA,0))=A12,"",INDEX(AC:AC,MATCH(E12,AA:AA,0))) | J12: =IF(INDEX(U:U,MATCH(E12,T:T,0))=A12,"",INDEX(U:U,MATCH(E12,T:T,0))) | K12: =IF(INDEX(AH:AH,MATCH(E12,AE:AE,0))=A12,"",INDEX(AH:AH,MATCH(E12,AE:AE,0))) | S12: AUS | T12: AUS | U12: ANZ | W12: GNQ | X12: EqGuinea | Y12: SSA | AA12: BRB | AB12: Rest Central America | AC12: OSA | AE12: PYF | AF12: xoc | AG12: IDN | AH12: SEA | AJ12: ARG | AK12: ARG | AL12: OSA | AM12: OAM | AN12: WLD | AQ12: ARM | AR12: Armenia | AS12: Total Population - Both sexes | AT12: Population - Est. & Proj. | AU12: 2014 | AV12: 1000 persons | AW12: 2912.409
A13: EUR | B13: =INDEX(Regions!B:B,MATCH(A13,Regions!A:A,0)) -> Europe | C13: Belgium | D13: BE | E13: BEL | F13: 56 | G13: =INDEX(AW:AW,MATCH(E13,AQ:AQ,0))/INDEX(AW:AW,MATCH("World",AR:AR,0)) -> 0.0015381472 | H13: =IF(INDEX(Y:Y,MATCH(E13,W:W,0))=A13,"",INDEX(Y:Y,MATCH(E13,W:W,0))) | I13: =IF(INDEX(AC:AC,MATCH(E13,AA:AA,0))=A13,"",INDEX(AC:AC,MATCH(E13,AA:AA,0))) | J13: =IF(INDEX(U:U,MATCH(E13,T:T,0))=A13,"",INDEX(U:U,MATCH(E13,T:T,0))) | K13: =IF(INDEX(AH:AH,MATCH(E13,AE:AE,0))=A13,"",INDEX(AH:AH,MATCH(E13,AE:AE,0))) | S13: AT000000 | T13: AUT | U13: EUR | W13: GAB | X13: Gabon | Y13: SSA | AA13: BLZ | AB13: Rest Central America | AC13: OSA | AE13: GUM | AF13: xoc | AG13: IDN | AH13: SEA | AJ13: ARM | AK13: ARM | AL13: FSU | AN13: WLD | AQ13: ABW | AR13: Aruba | AS13: Total Population - Both sexes | AT13: Population - Est. & Proj. | AU13: 2014 | AV13: 1000 persons | AW13: 103.774
A14: EUR | B14: =INDEX(Regions!B:B,MATCH(A14,Regions!A:A,0)) -> Europe | C14: Bosnia and Herzegovina | D14: BA | E14: BIH | F14: 70 | G14: =INDEX(AW:AW,MATCH(E14,AQ:AQ,0))/INDEX(AW:AW,MATCH("World",AR:AR,0)) -> 0.0004773086 | H14: =IF(INDEX(Y:Y,MATCH(E14,W:W,0))=A14,"",INDEX(Y:Y,MATCH(E14,W:W,0))) | I14: =IF(INDEX(AC:AC,MATCH(E14,AA:AA,0))=A14,"",INDEX(AC:AC,MATCH(E14,AA:AA,0))) | J14: =IF(INDEX(U:U,MATCH(E14,T:T,0))=A14,"",INDEX(U:U,MATCH(E14,T:T,0))) | K14: =IF(INDEX(AH:AH,MATCH(E14,AE:AE,0))=A14,"",INDEX(AH:AH,MATCH(E14,AE:AE,0))) | S14: FSU | T14: AZE | U14: FSU | W14: BDI | X14: Burundi | Y14: SSA | AA14: BMU | AB14: Rest Central America | AC14: OSA | AE14: KIR | AF14: xoc | AG14: IDN | AH14: SEA | AJ14: ASM | AK14: OPO | AL14: OAS | AN14: WLD | AO14: American Samoa | AQ14: AUS | AR14: Australia | AS14: Total Population - Both sexes | AT14: Population - Est. & Proj. | AU14: 2014 | AV14: 1000 persons | AW14: 23596.424
A15: EUR | B15: =INDEX(Regions!B:B,MATCH(A15,Regions!A:A,0)) -> Europe | C15: Bulgaria | D15: BG | E15: BGR | F15: 100 | G15: =INDEX(AW:AW,MATCH(E15,AQ:AQ,0))/INDEX(AW:AW,MATCH("World",AR:AR,0)) -> 0.00099319496 | H15: =IF(INDEX(Y:Y,MATCH(E15,W:W,0))=A15,"",INDEX(Y:Y,MATCH(E15,W:W,0))) | I15: =IF(INDEX(AC:AC,MATCH(E15,AA:AA,0))=A15,"",INDEX(AC:AC,MATCH(E15,AA:AA,0))) | J15: =IF(INDEX(U:U,MATCH(E15,T:T,0))=A15,"",INDEX(U:U,MATCH(E15,T:T,0))) | K15: =IF(INDEX(AH:AH,MATCH(E15,AE:AE,0))=A15,"",INDEX(AH:AH,MATCH(E15,AE:AE,0))) | S15: #N/A | T15: BDI | U15: #N/A | W15: ETH | X15: Ethiopia | Y15: SSA | AA15: CYM | AB15: Rest Central America | AC15: OSA | AE15: MHL | AF15: xoc | AG15: IDN | AH15: SEA | AJ15: ATA | AK15: n/a | AL15: #N/A | AM15: #N/A | AN15: #N/A | AO15: Antartica | AQ15: AUT | AR15: Austria | AS15: Total Population - Both sexes | AT15: Population - Est. & Proj. | AU15: 2014 | AV15: 1000 persons | AW15: 8615.214
A16: EUR | B16: =INDEX(Regions!B:B,MATCH(A16,Regions!A:A,0)) -> Europe | C16: Croatia | D16: HR | E16: HRV | F16: 191 | G16: =INDEX(AW:AW,MATCH(E16,AQ:AQ,0))/INDEX(AW:AW,MATCH("World",AR:AR,0)) -> 0.00058332315 | H16: =IF(INDEX(Y:Y,MATCH(E16,W:W,0))=A16,"",INDEX(Y:Y,MATCH(E16,W:W,0))) | I16: =IF(INDEX(AC:AC,MATCH(E16,AA:AA,0))=A16,"",INDEX(AC:AC,MATCH(E16,AA:AA,0))) | J16: =IF(INDEX(U:U,MATCH(E16,T:T,0))=A16,"",INDEX(U:U,MATCH(E16,T:T,0))) | K16: =IF(INDEX(AH:AH,MATCH(E16,AE:AE,0))=A16,"",INDEX(AH:AH,MATCH(E16,AE:AE,0))) | S16: BL000000 | T16: BEL | U16: EUR | W16: KEN | X16: Kenya | Y16: SSA | AA16: CRI | AB16: Rest Central America | AC16: OSA | AE16: FSM | AF16: xoc | AG16: IDN | AH16: SEA | AJ16: ATF | AK16: OIO | AL16: SSA | AN16: WLD | AO16: French Southern Territories | AQ16: AZE | AR16: Azerbaijan | AS16: Total Population - Both sexes | AT16: Population - Est. & Proj. | AU16: 2014 | AV16: 1000 persons | AW16: 9505.622
A17: EUR | B17: =INDEX(Regions!B:B,MATCH(A17,Regions!A:A,0)) -> Europe | C17: Cyprus | D17: CY | E17: CYP | F17: 196 | G17: =INDEX(AW:AW,MATCH(E17,AQ:AQ,0))/INDEX(AW:AW,MATCH("World",AR:AR,0)) -> 0.00015794915 | H17: =IF(INDEX(Y:Y,MATCH(E17,W:W,0))=A17,"",INDEX(Y:Y,MATCH(E17,W:W,0))) | I17: =IF(INDEX(AC:AC,MATCH(E17,AA:AA,0))=A17,"",INDEX(AC:AC,MATCH(E17,AA:AA,0))) | J17: =IF(INDEX(U:U,MATCH(E17,T:T,0))=A17,"",INDEX(U:U,MATCH(E17,T:T,0))) | K17: =IF(INDEX(AH:AH,MATCH(E17,AE:AE,0))=A17,"",INDEX(AH:AH,MATCH(E17,AE:AE,0))) | S17: AFR_LDC | T17: BEN | U17: SSA | W17: RWA | X17: Rwanda | Y17: SSA | AA17: CUB | AB17: Rest Central America | AC17: OSA | AE17: NRU | AF17: xoc | AG17: IDN | AH17: SEA | AJ17: ATG | AK17: CRB | AL17: OSA | AN17: WLD | AQ17: BHS | AR17: Bahamas | AS17: Total Population - Both sexes | AT17: Population - Est. & Proj. | AU17: 2014 | AV17: 1000 persons | AW17: 370.633
A18: EUR | B18: =INDEX(Regions!B:B,MATCH(A18,Regions!A:A,0)) -> Europe | C18: Czech Republic | D18: CZ | E18: CZE | F18: 203 | G18: =INDEX(AW:AW,MATCH(E18,AQ:AQ,0))/INDEX(AW:AW,MATCH("World",AR:AR,0)) -> 0.0014517733 | H18: =IF(INDEX(Y:Y,MATCH(E18,W:W,0))=A18,"",INDEX(Y:Y,MATCH(E18,W:W,0))) | I18: =IF(INDEX(AC:AC,MATCH(E18,AA:AA,0))=A18,"",INDEX(AC:AC,MATCH(E18,AA:AA,0))) | J18: =IF(INDEX(U:U,MATCH(E18,T:T,0))=A18,"",INDEX(U:U,MATCH(E18,T:T,0))) | K18: =IF(INDEX(AH:AH,MATCH(E18,AE:AE,0))=A18,"",INDEX(AH:AH,MATCH(E18,AE:AE,0))) | S18: AFR_LDC | T18: BFA | U18: SSA | W18: TZA | X18: Tanzania | Y18: SSA | AA18: DMA | AB18: Rest Central America | AC18: OSA | AE18: NCL | AF18: xoc | AG18: IDN | AH18: SEA | AJ18: AUS | AK18: AUS | AL18: ANZ | AN18: WLD | AQ18: BHR | AR18: Bahrain | AS18: Total Population - Both sexes | AT18: Population - Est. & Proj. | AU18: 2014 | AV18: 1000 persons | AW18: 1336.075
A19: EUR | B19: =INDEX(Regions!B:B,MATCH(A19,Regions!A:A,0)) -> Europe | C19: Denmark | D19: DK | E19: DNK | F19: 208 | G19: =INDEX(AW:AW,MATCH(E19,AQ:AQ,0))/INDEX(AW:AW,MATCH("World",AR:AR,0)) -> 0.00077641813 | H19: =IF(INDEX(Y:Y,MATCH(E19,W:W,0))=A19,"",INDEX(Y:Y,MATCH(E19,W:W,0))) | I19: =IF(INDEX(AC:AC,MATCH(E19,AA:AA,0))=A19,"",INDEX(AC:AC,MATCH(E19,AA:AA,0))) | J19: =IF(INDEX(U:U,MATCH(E19,T:T,0))=A19,"",INDEX(U:U,MATCH(E19,T:T,0))) | K19: =IF(INDEX(AH:AH,MATCH(E19,AE:AE,0))=A19,"",INDEX(AH:AH,MATCH(E19,AE:AE,0))) | S19: BGD | T19: BGD | U19: OAS | W19: UGA | X19: Uganda | Y19: SSA | AA19: DOM | AB19: Rest Central America | AC19: OSA | AE19: NIU | AF19: xoc | AG19: IDN | AH19: SEA | AJ19: AUT | AK19: AUT | AL19: EUR | AN19: WLD | AQ19: BGD | AR19: Bangladesh | AS19: Total Population - Both sexes | AT19: Population - Est. & Proj. | AU19: 2014 | AV19: 1000 persons | AW19: 154517.38
A20: EUR | B20: =INDEX(Regions!B:B,MATCH(A20,Regions!A:A,0)) -> Europe | C20: Estonia | D20: EE | E20: EST | F20: 233 | G20: =INDEX(AW:AW,MATCH(E20,AQ:AQ,0))/INDEX(AW:AW,MATCH("World",AR:AR,0)) -> 0.00018042831 | H20: =IF(INDEX(Y:Y,MATCH(E20,W:W,0))=A20,"",INDEX(Y:Y,MATCH(E20,W:W,0))) | I20: =IF(INDEX(AC:AC,MATCH(E20,AA:AA,0))=A20,"",INDEX(AC:AC,MATCH(E20,AA:AA,0))) | J20: =IF(INDEX(U:U,MATCH(E20,T:T,0))=A20,"",INDEX(U:U,MATCH(E20,T:T,0))) | K20: =IF(INDEX(AH:AH,MATCH(E20,AE:AE,0))=A20,"",INDEX(AH:AH,MATCH(E20,AE:AE,0))) | S20: BG000000 | T20: BGR | U20: EUR | W20: EST | X20: Estonia | Y20: EUR | AA20: SLV | AB20: Rest Central America | AC20: OSA | AE20: MNP | AF20: xoc | AG20: IDN | AH20: SEA | AJ20: AZE | AK20: AZE | AL20: FSU | AN20: WLD | AQ20: BRB | AR20: Barbados | AS20: Total Population - Both sexes | AT20: Population - Est. & Proj. | AU20: 2014 | AV20: 1000 persons | AW20: 284.826
A21: EUR | B21: =INDEX(Regions!B:B,MATCH(A21,Regions!A:A,0)) -> Europe | C21: Finland | D21: FI | E21: FIN | F21: 246 | G21: =INDEX(AW:AW,MATCH(E21,AQ:AQ,0))/INDEX(AW:AW,MATCH("World",AR:AR,0)) -> 0.00074862143 | H21: =IF(INDEX(Y:Y,MATCH(E21,W:W,0))=A21,"",INDEX(Y:Y,MATCH(E21,W:W,0))) | I21: =IF(INDEX(AC:AC,MATCH(E21,AA:AA,0))=A21,"",INDEX(AC:AC,MATCH(E21,AA:AA,0))) | J21: =IF(INDEX(U:U,MATCH(E21,T:T,0))=A21,"",INDEX(U:U,MATCH(E21,T:T,0))) | K21: =IF(INDEX(AH:AH,MATCH(E21,AE:AE,0))=A21,"",INDEX(AH:AH,MATCH(E21,AE:AE,0))) | S21: #N/A | T21: BHR | U21: #N/A | W21: LVA | X21: Latvia | Y21: EUR | AA21: GRD | AB21: Rest Central America | AC21: OSA | AE21: PLW | AF21: xoc | AG21: IDN | AH21: SEA | AJ21: BDI | AK21: BDI | AL21: SSA | AM21: AME | AN21: WLD | AQ21: BLR | AR21: Belarus | AS21: Total Population - Both sexes | AT21: Population - Est. & Proj. | AU21: 2014 | AV21: 1000 persons | AW21: 9431.735
A22: EUR | B22: =INDEX(Regions!B:B,MATCH(A22,Regions!A:A,0)) -> Europe | C22: France | D22: FR | E22: FRA | F22: 250 | G22: =INDEX(AW:AW,MATCH(E22,AQ:AQ,0))/INDEX(AW:AW,MATCH("World",AR:AR,0)) -> 0.0087993134 | H22: =IF(INDEX(Y:Y,MATCH(E22,W:W,0))=A22,"",INDEX(Y:Y,MATCH(E22,W:W,0))) | I22: =IF(INDEX(AC:AC,MATCH(E22,AA:AA,0))=A22,"",INDEX(AC:AC,MATCH(E22,AA:AA,0))) | J22: =IF(INDEX(U:U,MATCH(E22,T:T,0))=A22,"",INDEX(U:U,MATCH(E22,T:T,0))) | K22: =IF(INDEX(AH:AH,MATCH(E22,AE:AE,0))=A22,"",INDEX(AH:AH,MATCH(E22,AE:AE,0))) | S22: MSA_ACP | T22: BHS | U22: OSA | W22: LTU | X22: Lithuania | Y22: EUR | AA22: GLP | AB22: Rest Central America | AC22: OSA | AE22: PNG | AF22: xoc | AG22: IDN | AH22: SEA | AJ22: BEL | AK22: BLX | AL22: EUR | AN22: WLD | AQ22: BEL | AR22: Belgium | AS22: Total Population - Both sexes | AT22: Population - Est. & Proj. | AU22: 2014 | AV22: 1000 persons | AW22: 11221.231
A23: EUR | B23: =INDEX(Regions!B:B,MATCH(A23,Regions!A:A,0)) -> Europe | C23: Germany | D23: DE | E23: DEU | F23: 276 | G23: =INDEX(AW:AW,MATCH(E23,AQ:AQ,0))/INDEX(AW:AW,MATCH("World",AR:AR,0)) -> 0.011164788 | H23: =IF(INDEX(Y:Y,MATCH(E23,W:W,0))=A23,"",INDEX(Y:Y,MATCH(E23,W:W,0))) | I23: =IF(INDEX(AC:AC,MATCH(E23,AA:AA,0))=A23,"",INDEX(AC:AC,MATCH(E23,AA:AA,0))) | J23: =IF(INDEX(U:U,MATCH(E23,T:T,0))=A23,"",INDEX(U:U,MATCH(E23,T:T,0))) | K23: =IF(INDEX(AH:AH,MATCH(E23,AE:AE,0))=A23,"",INDEX(AH:AH,MATCH(E23,AE:AE,0))) | S23: BA000000 | T23: BIH | U23: EUR | W23: BGR | X23: Bulgaria | Y23: EUR | AA23: GTM | AB23: Rest Central America | AC23: OSA | AE23: PCN | AF23: xoc | AG23: IDN | AH23: SEA | AJ23: BEN | AK23: BEN | AL23: SSA | AM23: AME | AN23: WLD | AQ23: BLZ | AR23: Belize | AS23: Total Population - Both sexes | AT23: Population - Est. & Proj. | AU23: 2014 | AV23: 1000 persons | AW23: 353.366
A24: EUR | B24: =INDEX(Regions!B:B,MATCH(A24,Regions!A:A,0)) -> Europe | C24: Gibraltar | D24: GI | E24: GIB | F24: 292 | G24: =INDEX(AW:AW,MATCH(E24,AQ:AQ,0))/INDEX(AW:AW,MATCH("World",AR:AR,0)) -> 4.6228452e-06 | H24: =IF(INDEX(Y:Y,MATCH(E24,W:W,0))=A24,"",INDEX(Y:Y,MATCH(E24,W:W,0))) -> NotAccounted | I24: =IF(INDEX(AC:AC,MATCH(E24,AA:AA,0))=A24,"",INDEX(AC:AC,MATCH(E24,AA:AA,0))) | J24: =IF(INDEX(U:U,MATCH(E24,T:T,0))=A24,"",INDEX(U:U,MATCH(E24,T:T,0))) -> #N/A | K24: =IF(INDEX(AH:AH,MATCH(E24,AE:AE,0))=A24,"",INDEX(AH:AH,MATCH(E24,AE:AE,0))) | S24: BEL | T24: BLR | U24: FSU | W24: HRV | X24: Croatia | Y24: EUR | AA24: HTI | AB24: Rest Central America | AC24: OSA | AE24: WSM | AF24: xoc | AG24: IDN | AH24: SEA | AJ24: BES | AK24: CRB | AL24: OSA | AN24: WLD | AO24: Bonaire, Sint Eustatius and Saba | AQ24: BEN | AR24: Benin | AS24: Total Population - Both sexes | AT24: Population - Est. & Proj. | AU24: 2014 | AV24: 1000 persons | AW24: 10286.844
A25: EUR | B25: =INDEX(Regions!B:B,MATCH(A25,Regions!A:A,0)) -> Europe | C25: Greece | D25: GR | E25: GRC | F25: 300 | G25: =INDEX(AW:AW,MATCH(E25,AQ:AQ,0))/INDEX(AW:AW,MATCH("World",AR:AR,0)) -> 0.0014668992 | H25: =IF(INDEX(Y:Y,MATCH(E25,W:W,0))=A25,"",INDEX(Y:Y,MATCH(E25,W:W,0))) | I25: =IF(INDEX(AC:AC,MATCH(E25,AA:AA,0))=A25,"",INDEX(AC:AC,MATCH(E25,AA:AA,0))) | J25: =IF(INDEX(U:U,MATCH(E25,T:T,0))=A25,"",INDEX(U:U,MATCH(E25,T:T,0))) | K25: =IF(INDEX(AH:AH,MATCH(E25,AE:AE,0))=A25,"",INDEX(AH:AH,MATCH(E25,AE:AE,0))) | S25: MSA_ACP | T25: BLZ | U25: OSA | W25: CZE | X25: CzechRep | Y25: EUR | AA25: HND | AB25: Rest Central America | AC25: OSA | AE25: SLB | AF25: xoc | AG25: IDN | AH25: SEA | AJ25: BFA | AK25: BFA | AL25: SSA | AM25: AME | AN25: WLD | AQ25: BMU | AR25: Bermuda | AS25: Total Population - Both sexes | AT25: Population - Est. & Proj. | AU25: 2014 | AV25: 1000 persons | AW25: 64.033
A26: EUR | B26: =INDEX(Regions!B:B,MATCH(A26,Regions!A:A,0)) -> Europe | C26: Holy See | D26: VA | E26: VAT | F26: 336 | G26: =INDEX(AW:AW,MATCH(E26,AQ:AQ,0))/INDEX(AW:AW,MATCH("World",AR:AR,0)) -> 1.0965978e-07 | H26: =IF(INDEX(Y:Y,MATCH(E26,W:W,0))=A26,"",INDEX(Y:Y,MATCH(E26,W:W,0))) -> NotAccounted | I26: =IF(INDEX(AC:AC,MATCH(E26,AA:AA,0))=A26,"",INDEX(AC:AC,MATCH(E26,AA:AA,0))) | J26: =IF(INDEX(U:U,MATCH(E26,T:T,0))=A26,"",INDEX(U:U,MATCH(E26,T:T,0))) -> #N/A | K26: =IF(INDEX(AH:AH,MATCH(E26,AE:AE,0))=A26,"",INDEX(AH:AH,MATCH(E26,AE:AE,0))) | S26: RSA | T26: BMU | U26: OSA | W26: HUN | X26: Hungary | Y26: EUR | AA26: JAM | AB26: Rest Central America | AC26: OSA | AE26: TKL | AF26: xoc | AG26: IDN | AH26: SEA | AJ26: BGD | AK26: BGD | AL26: OAS | AM26: SAS | AN26: WLD | AQ26: BTN | AR26: Bhutan | AS26: Total Population - Both sexes | AT26: Population - Est. & Proj. | AU26: 2014 | AV26: 1000 persons | AW26: 719.055
A27: EUR | B27: =INDEX(Regions!B:B,MATCH(A27,Regions!A:A,0)) -> Europe | C27: Hungary | D27: HU | E27: HUN | F27: 348 | G27: =INDEX(AW:AW,MATCH(E27,AQ:AQ,0))/INDEX(AW:AW,MATCH("World",AR:AR,0)) -> 0.0013440165 | H27: =IF(INDEX(Y:Y,MATCH(E27,W:W,0))=A27,"",INDEX(Y:Y,MATCH(E27,W:W,0))) | I27: =IF(INDEX(AC:AC,MATCH(E27,AA:AA,0))=A27,"",INDEX(AC:AC,MATCH(E27,AA:AA,0))) | J27: =IF(INDEX(U:U,MATCH(E27,T:T,0))=A27,"",INDEX(U:U,MATCH(E27,T:T,0))) | K27: =IF(INDEX(AH:AH,MATCH(E27,AE:AE,0))=A27,"",INDEX(AH:AH,MATCH(E27,AE:AE,0))) | S27: BOL | T27: BOL | U27: OSA | W27: POL | X27: Poland | Y27: EUR | AA27: MTQ | AB27: Rest Central America | AC27: OSA | AE27: TON | AF27: xoc | AG27: IDN | AH27: SEA | AJ27: BGR | AK27: BGR | AL27: EUR | AN27: WLD | AQ27: BOL | AR27: Bolivia (Plurinational State of) | AS27: Total Population - Both sexes | AT27: Population - Est. & Proj. | AU27: 2014 | AV27: 1000 persons | AW27: 10706.517
A28: EUR | B28: =INDEX(Regions!B:B,MATCH(A28,Regions!A:A,0)) -> Europe | C28: Iceland | D28: IS | E28: ISL | F28: 352 | G28: =INDEX(AW:AW,MATCH(E28,AQ:AQ,0))/INDEX(AW:AW,MATCH("World",AR:AR,0)) -> 4.5041933e-05 | H28: =IF(INDEX(Y:Y,MATCH(E28,W:W,0))=A28,"",INDEX(Y:Y,MATCH(E28,W:W,0))) | I28: =IF(INDEX(AC:AC,MATCH(E28,AA:AA,0))=A28,"",INDEX(AC:AC,MATCH(E28,AA:AA,0))) | J28: =IF(INDEX(U:U,MATCH(E28,T:T,0))=A28,"",INDEX(U:U,MATCH(E28,T:T,0))) | K28: =IF(INDEX(AH:AH,MATCH(E28,AE:AE,0))=A28,"",INDEX(AH:AH,MATCH(E28,AE:AE,0))) | S28: BRA | T28: BRA | U28: BRA | W28: ROU | X28: Romania | Y28: EUR | AA28: MSR | AB28: Rest Central America | AC28: OSA | AE28: TUV | AF28: xoc | AG28: IDN | AH28: SEA | AJ28: BHR | AK28: RAP | AL28: MEN | AM28: AME | AN28: WLD | AQ28: BES | AR28: Bonaire, Sint Eustatius and Saba | AS28: Total Population - Both sexes | AT28: Population - Est. & Proj. | AU28: 2014 | AV28: 1000 persons | AW28: 24.07
A29: EUR | B29: =INDEX(Regions!B:B,MATCH(A29,Regions!A:A,0)) -> Europe | C29: Ireland | D29: IE | E29: IRL | F29: 372 | G29: =INDEX(AW:AW,MATCH(E29,AQ:AQ,0))/INDEX(AW:AW,MATCH("World",AR:AR,0)) -> 0.00063422338 | H29: =IF(INDEX(Y:Y,MATCH(E29,W:W,0))=A29,"",INDEX(Y:Y,MATCH(E29,W:W,0))) | I29: =IF(INDEX(AC:AC,MATCH(E29,AA:AA,0))=A29,"",INDEX(AC:AC,MATCH(E29,AA:AA,0))) | J29: =IF(INDEX(U:U,MATCH(E29,T:T,0))=A29,"",INDEX(U:U,MATCH(E29,T:T,0))) | K29: =IF(INDEX(AH:AH,MATCH(E29,AE:AE,0))=A29,"",INDEX(AH:AH,MATCH(E29,AE:AE,0))) | S29: MSA_ACP | T29: BRB | U29: OSA | W29: SVK | X29: Slovakia | Y29: EUR | AA29: ANT | AB29: Rest Central America | AC29: OSA | AE29: UMI | AF29: xoc | AG29: IDN | AH29: SEA | AJ29: BHS | AK29: CRB | AL29: OSA | AN29: WLD | AQ29: BIH | AR29: Bosnia and Herzegovina | AS29: Total Population - Both sexes | AT29: Population - Est. & Proj. | AU29: 2014 | AV29: 1000 persons | AW29: 3482.105
A30: EUR | B30: =INDEX(Regions!B:B,MATCH(A30,Regions!A:A,0)) -> Europe | C30: Italy | D30: IT | E30: ITA | F30: 380 | G30: =INDEX(AW:AW,MATCH(E30,AQ:AQ,0))/INDEX(AW:AW,MATCH("World",AR:AR,0)) -> 0.0082806323 | H30: =IF(INDEX(Y:Y,MATCH(E30,W:W,0))=A30,"",INDEX(Y:Y,MATCH(E30,W:W,0))) | I30: =IF(INDEX(AC:AC,MATCH(E30,AA:AA,0))=A30,"",INDEX(AC:AC,MATCH(E30,AA:AA,0))) | J30: =IF(INDEX(U:U,MATCH(E30,T:T,0))=A30,"",INDEX(U:U,MATCH(E30,T:T,0))) | K30: =IF(INDEX(AH:AH,MATCH(E30,AE:AE,0))=A30,"",INDEX(AH:AH,MATCH(E30,AE:AE,0))) | S30: ASOCE_REST | T30: BRN | U30: OAS | W30: SVN | X30: Slovenia | Y30: EUR | AA30: NIC | AB30: Rest Central America | AC30: OSA | AE30: VUT | AF30: xoc | AG30: IDN | AH30: SEA | AJ30: BIH | AK30: OBN | AL30: EUR | AN30: WLD | AQ30: BWA | AR30: Botswana | AS30: Total Population - Both sexes | AT30: Population - Est. & Proj. | AU30: 2014 | AV30: 1000 persons | AW30: 2088.618
A31: EUR | B31: =INDEX(Regions!B:B,MATCH(A31,Regions!A:A,0)) -> Europe | C31: Latvia | D31: LV | E31: LVA | F31: 428 | G31: =INDEX(AW:AW,MATCH(E31,AQ:AQ,0))/INDEX(AW:AW,MATCH("World",AR:AR,0)) -> 0.00027705805 | H31: =IF(INDEX(Y:Y,MATCH(E31,W:W,0))=A31,"",INDEX(Y:Y,MATCH(E31,W:W,0))) | I31: =IF(INDEX(AC:AC,MATCH(E31,AA:AA,0))=A31,"",INDEX(AC:AC,MATCH(E31,AA:AA,0))) | J31: =IF(INDEX(U:U,MATCH(E31,T:T,0))=A31,"",INDEX(U:U,MATCH(E31,T:T,0))) | K31: =IF(INDEX(AH:AH,MATCH(E31,AE:AE,0))=A31,"",INDEX(AH:AH,MATCH(E31,AE:AE,0))) | S31: #N/A | T31: BTN | U31: #N/A | W31: AUT | X31: Austria | Y31: EUR | AA31: PAN | AB31: Rest Central America | AC31: OSA | AE31: WLF | AF31: xoc | AG31: IDN | AH31: SEA | AJ31: BLM | AK31: CRB | AL31: OSA | AN31: WLD | AO31: Saint Barthélemy | AQ31: BRA | AR31: Brazil | AS31: Total Population - Both sexes | AT31: Population - Est. & Proj. | AU31: 2014 | AV31: 1000 persons | AW31: 202763.74
A32: EUR | B32: =INDEX(Regions!B:B,MATCH(A32,Regions!A:A,0)) -> Europe | C32: Liechtenstein | D32: LI | E32: LIE | F32: 438 | G32: =INDEX(AW:AW,MATCH(E32,AQ:AQ,0))/INDEX(AW:AW,MATCH("World",AR:AR,0)) -> 5.1023326e-06 | H32: =IF(INDEX(Y:Y,MATCH(E32,W:W,0))=A32,"",INDEX(Y:Y,MATCH(E32,W:W,0))) -> NotAccounted | I32: =IF(INDEX(AC:AC,MATCH(E32,AA:AA,0))=A32,"",INDEX(AC:AC,MATCH(E32,AA:AA,0))) | J32: =IF(INDEX(U:U,MATCH(E32,T:T,0))=A32,"",INDEX(U:U,MATCH(E32,T:T,0))) -> #N/A | K32: =IF(INDEX(AH:AH,MATCH(E32,AE:AE,0))=A32,"",INDEX(AH:AH,MATCH(E32,AE:AE,0))) | S32: AFR_REST | T32: BWA | U32: SSA | W32: BEL | X32: Belgium | Y32: EUR | AA32: PRI | AB32: Rest Central America | AC32: OSA | AE32: CHN | AF32: chn | AG32: CHR | AH32: CHN | AJ32: BLR | AK32: BLR | AL32: FSU | AN32: WLD | AQ32: VGB | AR32: British Virgin Islands | AS32: Total Population - Both sexes | AT32: Population - Est. & Proj. | AU32: 2014 | AV32: 1000 persons | AW32: 28.989
A33: EUR | B33: =INDEX(Regions!B:B,MATCH(A33,Regions!A:A,0)) -> Europe | C33: Lithuania | D33: LT | E33: LTU | F33: 440 | G33: =INDEX(AW:AW,MATCH(E33,AQ:AQ,0))/INDEX(AW:AW,MATCH("World",AR:AR,0)) -> 0.00040731714 | H33: =IF(INDEX(Y:Y,MATCH(E33,W:W,0))=A33,"",INDEX(Y:Y,MATCH(E33,W:W,0))) | I33: =IF(INDEX(AC:AC,MATCH(E33,AA:AA,0))=A33,"",INDEX(AC:AC,MATCH(E33,AA:AA,0))) | J33: =IF(INDEX(U:U,MATCH(E33,T:T,0))=A33,"",INDEX(U:U,MATCH(E33,T:T,0))) | K33: =IF(INDEX(AH:AH,MATCH(E33,AE:AE,0))=A33,"",INDEX(AH:AH,MATCH(E33,AE:AE,0))) | S33: AFR_LDC | T33: CAF | U33: SSA | W33: FRA | X33: France | Y33: EUR | AA33: KNA | AB33: Rest Central America | AC33: OSA | AE33: HKG | AF33: hkg | AG33: CHR | AH33: CHN | AJ33: BLZ | AK33: BLZ | AL33: OSA | AM33: OAM | AN33: WLD | AQ33: BRN | AR33: Brunei Darussalam | AS33: Total Population - Both sexes | AT33: Population - Est. & Proj. | AU33: 2014 | AV33: 1000 persons | AW33: 409.769
A34: EUR | B34: =INDEX(Regions!B:B,MATCH(A34,Regions!A:A,0)) -> Europe | C34: Luxembourg | D34: LU | E34: LUX | F34: 442 | G34: =INDEX(AW:AW,MATCH(E34,AQ:AQ,0))/INDEX(AW:AW,MATCH("World",AR:AR,0)) -> 7.601013e-05 | H34: =IF(INDEX(Y:Y,MATCH(E34,W:W,0))=A34,"",INDEX(Y:Y,MATCH(E34,W:W,0))) | I34: =IF(INDEX(AC:AC,MATCH(E34,AA:AA,0))=A34,"",INDEX(AC:AC,MATCH(E34,AA:AA,0))) | J34: =IF(INDEX(U:U,MATCH(E34,T:T,0))=A34,"",INDEX(U:U,MATCH(E34,T:T,0))) | K34: =IF(INDEX(AH:AH,MATCH(E34,AE:AE,0))=A34,"",INDEX(AH:AH,MATCH(E34,AE:AE,0))) | S34: CAN | T34: CAN | U34: CAN | W34: DEU | X34: Germany | Y34: EUR | AA34: LCA | AB34: Rest Central America | AC34: OSA | AE34: JPN | AF34: jpn | AG34: JAP | AH34: SEA | AJ34: BMU | AK34: OAO | AL34: SSA | AN34: WLD | AO34: **Part of Atlantic Ocean aggregation, assigned to SSA | AQ34: BGR | AR34: Bulgaria | AS34: Total Population - Both sexes | AT34: Population - Est. & Proj. | AU34: 2014 | AV34: 1000 persons | AW34: 7245.646
A35: EUR | B35: =INDEX(Regions!B:B,MATCH(A35,Regions!A:A,0)) -> Europe | C35: Malta | D35: MT | E35: MLT | F35: 470 | G35: =INDEX(AW:AW,MATCH(E35,AQ:AQ,0))/INDEX(AW:AW,MATCH("World",AR:AR,0)) -> 5.8969137e-05 | H35: =IF(INDEX(Y:Y,MATCH(E35,W:W,0))=A35,"",INDEX(Y:Y,MATCH(E35,W:W,0))) | I35: =IF(INDEX(AC:AC,MATCH(E35,AA:AA,0))=A35,"",INDEX(AC:AC,MATCH(E35,AA:AA,0))) | J35: =IF(INDEX(U:U,MATCH(E35,T:T,0))=A35,"",INDEX(U:U,MATCH(E35,T:T,0))) | K35: =IF(INDEX(AH:AH,MATCH(E35,AE:AE,0))=A35,"",INDEX(AH:AH,MATCH(E35,AE:AE,0))) | S35: CH | T35: CHE | U35: EUR | W35: LUX | X35: Luxembourg | Y35: EUR | AA35: VCT | AB35: Rest Central America | AC35: OSA | AE35: KOR | AF35: kor | AG35: KOR | AH35: CHN | AJ35: BOL | AK35: BOL | AL35: OSA | AM35: OAM | AN35: WLD | AQ35: BFA | AR35: Burkina Faso | AS35: Total Population - Both sexes | AT35: Population - Est. & Proj. | AU35: 2014 | AV35: 1000 persons | AW35: 17586.03
A36: EUR | B36: =INDEX(Regions!B:B,MATCH(A36,Regions!A:A,0)) -> Europe | C36: Monaco | D36: MC | E36: MCO | F36: 492 | G36: =INDEX(AW:AW,MATCH(E36,AQ:AQ,0))/INDEX(AW:AW,MATCH("World",AR:AR,0)) -> 5.115903e-06 | H36: =IF(INDEX(Y:Y,MATCH(E36,W:W,0))=A36,"",INDEX(Y:Y,MATCH(E36,W:W,0))) -> NotAccounted | I36: =IF(INDEX(AC:AC,MATCH(E36,AA:AA,0))=A36,"",INDEX(AC:AC,MATCH(E36,AA:AA,0))) | J36: =IF(INDEX(U:U,MATCH(E36,T:T,0))=A36,"",INDEX(U:U,MATCH(E36,T:T,0))) -> #N/A | K36: =IF(INDEX(AH:AH,MATCH(E36,AE:AE,0))=A36,"",INDEX(AH:AH,MATCH(E36,AE:AE,0))) | S36: CHL | T36: CHL | U36: OSA | W36: NLD | X36: Netherlands | Y36: EUR | AA36: TTO | AB36: Rest Central America | AC36: OSA | AE36: TWN | AF36: twn | AG36: CHR | AH36: CHN | AJ36: BRA | AK36: BRA | AL36: BRA | AM36: OAM | AN36: WLD | AQ36: BDI | AR36: Burundi | AS36: Total Population - Both sexes | AT36: Population - Est. & Proj. | AU36: 2014 | AV36: 1000 persons | AW36: 9844.299
A37: EUR | B37: =INDEX(Regions!B:B,MATCH(A37,Regions!A:A,0)) -> Europe | C37: Montenegro | D37: ME | E37: MNE | F37: 499 | G37: =INDEX(AW:AW,MATCH(E37,AQ:AQ,0))/INDEX(AW:AW,MATCH("World",AR:AR,0)) -> 8.5897193e-05 | H37: =IF(INDEX(Y:Y,MATCH(E37,W:W,0))=A37,"",INDEX(Y:Y,MATCH(E37,W:W,0))) | I37: =IF(INDEX(AC:AC,MATCH(E37,AA:AA,0))=A37,"",INDEX(AC:AC,MATCH(E37,AA:AA,0))) -> #N/A | J37: =IF(INDEX(U:U,MATCH(E37,T:T,0))=A37,"",INDEX(U:U,MATCH(E37,T:T,0))) | K37: =IF(INDEX(AH:AH,MATCH(E37,AE:AE,0))=A37,"",INDEX(AH:AH,MATCH(E37,AE:AE,0))) | S37: CHN | T37: CHN | U37: CHN | W37: DNK | X37: Denmark | Y37: EUR | AA37: TCA | AB37: Rest Central America | AC37: OSA | AE37: PRK | AF37: xea | AG37: KOR | AH37: CHN | AJ37: BRB | AK37: CRB | AL37: OSA | AN37: WLD | AQ37: CPV | AR37: Cabo Verde | AS37: Total Population - Both sexes | AT37: Population - Est. & Proj. | AU37: 2014 | AV37: 1000 persons | AW37: 518.271
A38: EUR | B38: =INDEX(Regions!B:B,MATCH(A38,Regions!A:A,0)) -> Europe | C38: Netherlands | D38: NL | E38: NLD | F38: 528 | G38: =INDEX(AW:AW,MATCH(E38,AQ:AQ,0))/INDEX(AW:AW,MATCH("World",AR:AR,0)) -> 0.002315538 | H38: =IF(INDEX(Y:Y,MATCH(E38,W:W,0))=A38,"",INDEX(Y:Y,MATCH(E38,W:W,0))) | I38: =IF(INDEX(AC:AC,MATCH(E38,AA:AA,0))=A38,"",INDEX(AC:AC,MATCH(E38,AA:AA,0))) | J38: =IF(INDEX(U:U,MATCH(E38,T:T,0))=A38,"",INDEX(U:U,MATCH(E38,T:T,0))) | K38: =IF(INDEX(AH:AH,MATCH(E38,AE:AE,0))=A38,"",INDEX(AH:AH,MATCH(E38,AE:AE,0))) | S38: AFR_REST | T38: CIV | U38: SSA | W38: FIN | X38: Finland | Y38: EUR | AA38: VGB | AB38: Rest Central America | AC38: OSA | AE38: MAC | AF38: xea | AG38: KOR | AH38: CHN | AJ38: BRN | AK38: OSA | AL38: SEA | AM38: SAS | AN38: WLD | AQ38: KHM | AR38: Cambodia | AS38: Total Population - Both sexes | AT38: Population - Est. & Proj. | AU38: 2014 | AV38: 1000 persons | AW38: 15274.503
A39: EUR | B39: =INDEX(Regions!B:B,MATCH(A39,Regions!A:A,0)) -> Europe | C39: Norway | D39: NO | E39: NOR | F39: 578 | G39: =INDEX(AW:AW,MATCH(E39,AQ:AQ,0))/INDEX(AW:AW,MATCH("World",AR:AR,0)) -> 0.00070487458 | H39: =IF(INDEX(Y:Y,MATCH(E39,W:W,0))=A39,"",INDEX(Y:Y,MATCH(E39,W:W,0))) | I39: =IF(INDEX(AC:AC,MATCH(E39,AA:AA,0))=A39,"",INDEX(AC:AC,MATCH(E39,AA:AA,0))) | J39: =IF(INDEX(U:U,MATCH(E39,T:T,0))=A39,"",INDEX(U:U,MATCH(E39,T:T,0))) | K39: =IF(INDEX(AH:AH,MATCH(E39,AE:AE,0))=A39,"",INDEX(AH:AH,MATCH(E39,AE:AE,0))) | S39: AFR_REST | T39: CMR | U39: SSA | W39: IRL | X39: Ireland | Y39: EUR | AA39: VIR | AB39: Rest Central America | AC39: OSA | AE39: MNG | AF39: mng | AG39: CHR | AH39: CHN | AJ39: BTN | AK39: BTN | AL39: OAS | AM39: SAS | AN39: WLD | AQ39: CMR | AR39: Cameroon | AS39: Total Population - Both sexes | AT39: Population - Est. & Proj. | AU39: 2014 | AV39: 1000 persons | AW39: 22681.852
A40: EUR | B40: =INDEX(Regions!B:B,MATCH(A40,Regions!A:A,0)) -> Europe | C40: Poland | D40: PL | E40: POL | F40: 616 | G40: =INDEX(AW:AW,MATCH(E40,AQ:AQ,0))/INDEX(AW:AW,MATCH("World",AR:AR,0)) -> 0.0052213257 | H40: =IF(INDEX(Y:Y,MATCH(E40,W:W,0))=A40,"",INDEX(Y:Y,MATCH(E40,W:W,0))) | I40: =IF(INDEX(AC:AC,MATCH(E40,AA:AA,0))=A40,"",INDEX(AC:AC,MATCH(E40,AA:AA,0))) | J40: =IF(INDEX(U:U,MATCH(E40,T:T,0))=A40,"",INDEX(U:U,MATCH(E40,T:T,0))) | K40: =IF(INDEX(AH:AH,MATCH(E40,AE:AE,0))=A40,"",INDEX(AH:AH,MATCH(E40,AE:AE,0))) | S40: #N/A | T40: COD | U40: #N/A | W40: SWE | X40: Sweden | Y40: EUR | AA40: BRA | AB40: Brazil | AC40: BRA | AE40: KHM | AF40: khm | AG40: SEA | AH40: SEA | AJ40: BVT | AK40: OAO | AL40: SSA | AN40: WLD | AO40: Bouvet Island | AQ40: CAN | AR40: Canada | AS40: Total Population - Both sexes | AT40: Population - Est. & Proj. | AU40: 2014 | AV40: 1000 persons | AW40: 35664.337
A41: EUR | B41: =INDEX(Regions!B:B,MATCH(A41,Regions!A:A,0)) -> Europe | C41: Portugal | D41: PT | E41: PRT | F41: 620 | G41: =INDEX(AW:AW,MATCH(E41,AQ:AQ,0))/INDEX(AW:AW,MATCH("World",AR:AR,0)) -> 0.0014280744 | H41: =IF(INDEX(Y:Y,MATCH(E41,W:W,0))=A41,"",INDEX(Y:Y,MATCH(E41,W:W,0))) | I41: =IF(INDEX(AC:AC,MATCH(E41,AA:AA,0))=A41,"",INDEX(AC:AC,MATCH(E41,AA:AA,0))) | J41: =IF(INDEX(U:U,MATCH(E41,T:T,0))=A41,"",INDEX(U:U,MATCH(E41,T:T,0))) | K41: =IF(INDEX(AH:AH,MATCH(E41,AE:AE,0))=A41,"",INDEX(AH:AH,MATCH(E41,AE:AE,0))) | S41: AFR_REST | T41: COG | U41: SSA | W41: GBR | X41: UK | Y41: EUR | AA41: ARG | AB41: Rest South America | AC41: OSA | AE41: IDN | AF41: idn | AG41: IDN | AH41: SEA | AJ41: BWA | AK41: BWA | AL41: SSA | AM41: AME | AN41: WLD | AQ41: CYM | AR41: Cayman Islands | AS41: Total Population - Both sexes | AT41: Population - Est. & Proj. | AU41: 2014 | AV41: 1000 persons | AW41: 60.848
A42: EUR | B42: =INDEX(Regions!B:B,MATCH(A42,Regions!A:A,0)) -> Europe | C42: Romania | D42: RO | E42: ROU | F42: 642 | G42: =INDEX(AW:AW,MATCH(E42,AQ:AQ,0))/INDEX(AW:AW,MATCH("World",AR:AR,0)) -> 0.0027464197 | H42: =IF(INDEX(Y:Y,MATCH(E42,W:W,0))=A42,"",INDEX(Y:Y,MATCH(E42,W:W,0))) | I42: =IF(INDEX(AC:AC,MATCH(E42,AA:AA,0))=A42,"",INDEX(AC:AC,MATCH(E42,AA:AA,0))) -> #N/A | J42: =IF(INDEX(U:U,MATCH(E42,T:T,0))=A42,"",INDEX(U:U,MATCH(E42,T:T,0))) | K42: =IF(INDEX(AH:AH,MATCH(E42,AE:AE,0))=A42,"",INDEX(AH:AH,MATCH(E42,AE:AE,0))) | S42: #N/A | T42: COK | U42: #N/A | W42: CYP | X42: Cyprus | Y42: EUR | AA42: BOL | AB42: Rest South America | AC42: OSA | AE42: LAO | AF42: lao | AG42: SEA | AH42: SEA | AJ42: CAF | AK42: CAF | AL42: SSA | AM42: AME | AN42: WLD | AQ42: CAF | AR42: Central African Republic | AS42: Total Population - Both sexes | AT42: Population - Est. & Proj. | AU42: 2014 | AV42: 1000 persons | AW42: 4464.175
A43: EUR | B43: =INDEX(Regions!B:B,MATCH(A43,Regions!A:A,0)) -> Europe | C43: San Marino | D43: SM | E43: SMR | F43: 674 | G43: =INDEX(AW:AW,MATCH(E43,AQ:AQ,0))/INDEX(AW:AW,MATCH("World",AR:AR,0)) -> 4.5163382e-06 | H43: =IF(INDEX(Y:Y,MATCH(E43,W:W,0))=A43,"",INDEX(Y:Y,MATCH(E43,W:W,0))) -> NotAccounted | I43: =IF(INDEX(AC:AC,MATCH(E43,AA:AA,0))=A43,"",INDEX(AC:AC,MATCH(E43,AA:AA,0))) | J43: =IF(INDEX(U:U,MATCH(E43,T:T,0))=A43,"",INDEX(U:U,MATCH(E43,T:T,0))) -> #N/A | K43: =IF(INDEX(AH:AH,MATCH(E43,AE:AE,0))=A43,"",INDEX(AH:AH,MATCH(E43,AE:AE,0))) | S43: RSA | T43: COL | U43: OSA | W43: GRC | X43: Greece | Y43: EUR | AA43: BVT | AB43: Rest South America | AC43: OSA | AE43: MYS | AF43: mys | AG43: SEA | AH43: SEA | AJ43: CAN | AK43: CAN | AL43: CAN | AM43: NAM | AN43: WLD | AQ43: TCD | AR43: Chad | AS43: Total Population - Both sexes | AT43: Population - Est. & Proj. | AU43: 2014 | AV43: 1000 persons | AW43: 13663.566
A44: EUR | B44: =INDEX(Regions!B:B,MATCH(A44,Regions!A:A,0)) -> Europe | C44: Serbia | D44: RS | E44: SRB | F44: 688 | G44: =INDEX(AW:AW,MATCH(E44,AQ:AQ,0))/INDEX(AW:AW,MATCH("World",AR:AR,0)) -> 0.0012197305 | H44: =IF(INDEX(Y:Y,MATCH(E44,W:W,0))=A44,"",INDEX(Y:Y,MATCH(E44,W:W,0))) | I44: =IF(INDEX(AC:AC,MATCH(E44,AA:AA,0))=A44,"",INDEX(AC:AC,MATCH(E44,AA:AA,0))) -> #N/A | J44: =IF(INDEX(U:U,MATCH(E44,T:T,0))=A44,"",INDEX(U:U,MATCH(E44,T:T,0))) | K44: =IF(INDEX(AH:AH,MATCH(E44,AE:AE,0))=A44,"",INDEX(AH:AH,MATCH(E44,AE:AE,0))) | S44: #N/A | T44: COM | U44: #N/A | W44: ITA | X44: Italy | Y44: EUR | AA44: CHL | AB44: Rest South America | AC44: OSA | AE44: PHL | AF44: phl | AG44: SEA | AH44: SEA | AJ44: CCK | AK44: OIO | AL44: SSA | AN44: WLD | AO44: Cocos (Keeling) Islands | AQ44: CHA | AR44: Channel Islands | AS44: Total Population - Both sexes | AT44: Population - Est. & Proj. | AU44: 2014 | AV44: 1000 persons | AW44: 164.1
A45: EUR | B45: =INDEX(Regions!B:B,MATCH(A45,Regions!A:A,0)) -> Europe | C45: Slovakia | D45: SK | E45: SVK | F45: 703 | G45: =INDEX(AW:AW,MATCH(E45,AQ:AQ,0))/INDEX(AW:AW,MATCH("World",AR:AR,0)) -> 0.0007441517 | H45: =IF(INDEX(Y:Y,MATCH(E45,W:W,0))=A45,"",INDEX(Y:Y,MATCH(E45,W:W,0))) | I45: =IF(INDEX(AC:AC,MATCH(E45,AA:AA,0))=A45,"",INDEX(AC:AC,MATCH(E45,AA:AA,0))) | J45: =IF(INDEX(U:U,MATCH(E45,T:T,0))=A45,"",INDEX(U:U,MATCH(E45,T:T,0))) | K45: =IF(INDEX(AH:AH,MATCH(E45,AE:AE,0))=A45,"",INDEX(AH:AH,MATCH(E45,AE:AE,0))) | S45: AFR_REST | T45: CPV | U45: SSA | W45: MLT | X45: Malta | Y45: EUR | AA45: COL | AB45: Rest South America | AC45: OSA | AE45: SGP | AF45: sgp | AG45: SEA | AH45: SEA | AJ45: CHE | AK45: CHP | AL45: EUR | AN45: WLD | AQ45: CHL | AR45: Chile | AS45: Total Population - Both sexes | AT45: Population - Est. & Proj. | AU45: 2014 | AV45: 1000 persons | AW45: 17758.959
A46: EUR | B46: =INDEX(Regions!B:B,MATCH(A46,Regions!A:A,0)) -> Europe | C46: Slovenia | D46: SI | E46: SVN | F46: 705 | G46: =INDEX(AW:AW,MATCH(E46,AQ:AQ,0))/INDEX(AW:AW,MATCH("World",AR:AR,0)) -> 0.00028340036 | H46: =IF(INDEX(Y:Y,MATCH(E46,W:W,0))=A46,"",INDEX(Y:Y,MATCH(E46,W:W,0))) | I46: =IF(INDEX(AC:AC,MATCH(E46,AA:AA,0))=A46,"",INDEX(AC:AC,MATCH(E46,AA:AA,0))) | J46: =IF(INDEX(U:U,MATCH(E46,T:T,0))=A46,"",INDEX(U:U,MATCH(E46,T:T,0))) | K46: =IF(INDEX(AH:AH,MATCH(E46,AE:AE,0))=A46,"",INDEX(AH:AH,MATCH(E46,AE:AE,0))) | S46: RSA | T46: CRI | U46: OSA | W46: PRT | X46: Portugal | Y46: EUR | AA46: ECU | AB46: Rest South America | AC46: OSA | AE46: THA | AF46: tha | AG46: SEA | AH46: SEA | AJ46: CHL | AK46: CHL | AL46: OSA | AM46: OAM | AN46: WLD | AQ46: CHN | AR46: China | AS46: Total Population - Both sexes | AT46: Population - Est. & Proj. | AU46: 2014 | AV46: 1000 persons | AW46: 1430670.8
A47: EUR | B47: =INDEX(Regions!B:B,MATCH(A47,Regions!A:A,0)) -> Europe | C47: Spain | D47: ES | E47: ESP | F47: 724 | G47: =INDEX(AW:AW,MATCH(E47,AQ:AQ,0))/INDEX(AW:AW,MATCH("World",AR:AR,0)) -> 0.0064120714 | H47: =IF(INDEX(Y:Y,MATCH(E47,W:W,0))=A47,"",INDEX(Y:Y,MATCH(E47,W:W,0))) | I47: =IF(INDEX(AC:AC,MATCH(E47,AA:AA,0))=A47,"",INDEX(AC:AC,MATCH(E47,AA:AA,0))) | J47: =IF(INDEX(U:U,MATCH(E47,T:T,0))=A47,"",INDEX(U:U,MATCH(E47,T:T,0))) | K47: =IF(INDEX(AH:AH,MATCH(E47,AE:AE,0))=A47,"",INDEX(AH:AH,MATCH(E47,AE:AE,0))) | S47: MSA_ACP | T47: CUB | U47: OSA | W47: ESP | X47: Spain | Y47: EUR | AA47: FLK | AB47: Rest South America | AC47: OSA | AE47: VNM | AF47: vnm | AG47: SEA | AH47: SEA | AJ47: CHN | AK47: CHM | AL47: CHN | AM47: SAS | AN47: WLD | AQ47: HKG | AR47: China, Hong Kong SAR | AS47: Total Population - Both sexes | AT47: Population - Est. & Proj. | AU47: 2014 | AV47: 1000 persons | AW47: 7134.67
A48: EUR | B48: =INDEX(Regions!B:B,MATCH(A48,Regions!A:A,0)) -> Europe | C48: Sweden | D48: SE | E48: SWE | F48: 752 | G48: =INDEX(AW:AW,MATCH(E48,AQ:AQ,0))/INDEX(AW:AW,MATCH("World",AR:AR,0)) -> 0.0013285462 | H48: =IF(INDEX(Y:Y,MATCH(E48,W:W,0))=A48,"",INDEX(Y:Y,MATCH(E48,W:W,0))) | I48: =IF(INDEX(AC:AC,MATCH(E48,AA:AA,0))=A48,"",INDEX(AC:AC,MATCH(E48,AA:AA,0))) | J48: =IF(INDEX(U:U,MATCH(E48,T:T,0))=A48,"",INDEX(U:U,MATCH(E48,T:T,0))) | K48: =IF(INDEX(AH:AH,MATCH(E48,AE:AE,0))=A48,"",INDEX(AH:AH,MATCH(E48,AE:AE,0))) | S48: #N/A | T48: CYM | U48: #N/A | W48: ARM | X48: Armenia | Y48: FSU | AA48: GUF | AB48: Rest South America | AC48: OSA | AE48: BRN | AF48: brn | AG48: SEA | AH48: SEA | AJ48: CIV | AK48: CIV | AL48: SSA | AM48: AME | AN48: WLD | AQ48: MAC | AR48: China, Macao SAR | AS48: Total Population - Both sexes | AT48: Population - Est. & Proj. | AU48: 2014 | AV48: 1000 persons | AW48: 590.208
A49: EUR | B49: =INDEX(Regions!B:B,MATCH(A49,Regions!A:A,0)) -> Europe | C49: Switzerland | D49: CH | E49: CHE | F49: 756 | G49: =INDEX(AW:AW,MATCH(E49,AQ:AQ,0))/INDEX(AW:AW,MATCH("World",AR:AR,0)) -> 0.0011248355 | H49: =IF(INDEX(Y:Y,MATCH(E49,W:W,0))=A49,"",INDEX(Y:Y,MATCH(E49,W:W,0))) | I49: =IF(INDEX(AC:AC,MATCH(E49,AA:AA,0))=A49,"",INDEX(AC:AC,MATCH(E49,AA:AA,0))) | J49: =IF(INDEX(U:U,MATCH(E49,T:T,0))=A49,"",INDEX(U:U,MATCH(E49,T:T,0))) | K49: =IF(INDEX(AH:AH,MATCH(E49,AE:AE,0))=A49,"",INDEX(AH:AH,MATCH(E49,AE:AE,0))) | S49: CY000000 | T49: CYP | U49: EUR | W49: AZE | X49: Azerbaijan | Y49: FSU | AA49: GUY | AB49: Rest South America | AC49: OSA | AE49: MMR | AF49: xse | AG49: SEA | AH49: SEA | AJ49: CMR | AK49: CMR | AL49: SSA | AM49: AME | AN49: WLD | AQ49: F41 | AR49: China, mainland | AS49: Total Population - Both sexes | AT49: Population - Est. & Proj. | AU49: 2014 | AV49: 1000 persons | AW49: 1399454
A50: EUR | B50: =INDEX(Regions!B:B,MATCH(A50,Regions!A:A,0)) -> Europe | C50: Macedonia | D50: MK | E50: MKD | F50: 807 | G50: =INDEX(AW:AW,MATCH(E50,AQ:AQ,0))/INDEX(AW:AW,MATCH("World",AR:AR,0)) -> 0.00028481044 | H50: =IF(INDEX(Y:Y,MATCH(E50,W:W,0))=A50,"",INDEX(Y:Y,MATCH(E50,W:W,0))) | I50: =IF(INDEX(AC:AC,MATCH(E50,AA:AA,0))=A50,"",INDEX(AC:AC,MATCH(E50,AA:AA,0))) | J50: =IF(INDEX(U:U,MATCH(E50,T:T,0))=A50,"",INDEX(U:U,MATCH(E50,T:T,0))) | K50: =IF(INDEX(AH:AH,MATCH(E50,AE:AE,0))=A50,"",INDEX(AH:AH,MATCH(E50,AE:AE,0))) | S50: CZ000000 | T50: CZE | U50: EUR | W50: BLR | X50: Belarus | Y50: FSU | AA50: PRY | AB50: Rest South America | AC50: OSA | AE50: TLS | AF50: xse | AG50: SEA | AH50: SEA | AJ50: COD | AK50: COD | AL50: SSA | AM50: AME | AN50: WLD | AQ50: TWN | AR50: China, Taiwan Province of | AS50: Total Population - Both sexes | AT50: Population - Est. & Proj. | AU50: 2014 | AV50: 1000 persons | AW50: 23491.976
A51: EUR | B51: =INDEX(Regions!B:B,MATCH(A51,Regions!A:A,0)) -> Europe | C51: United Kingdom | D51: GB | E51: GBR | F51: 826 | G51: =INDEX(AW:AW,MATCH(E51,AQ:AQ,0))/INDEX(AW:AW,MATCH("World",AR:AR,0)) -> 0.0089678464 | H51: =IF(INDEX(Y:Y,MATCH(E51,W:W,0))=A51,"",INDEX(Y:Y,MATCH(E51,W:W,0))) | I51: =IF(INDEX(AC:AC,MATCH(E51,AA:AA,0))=A51,"",INDEX(AC:AC,MATCH(E51,AA:AA,0))) | J51: =IF(INDEX(U:U,MATCH(E51,T:T,0))=A51,"",INDEX(U:U,MATCH(E51,T:T,0))) | K51: =IF(INDEX(AH:AH,MATCH(E51,AE:AE,0))=A51,"",INDEX(AH:AH,MATCH(E51,AE:AE,0))) | S51: DE000000 | T51: DEU | U51: EUR | W51: GEO | X51: Georgia | Y51: FSU | AA51: PER | AB51: Rest South America | AC51: OSA | AE51: BGD | AF51: bgd | AG51: RSA | AH51: OAS | AJ51: COG | AK51: COG | AL51: SSA | AM51: AME | AN51: WLD | AQ51: COL | AR51: Colombia | AS51: Total Population - Both sexes | AT51: Population - Est. & Proj. | AU51: 2014 | AV51: 1000 persons | AW51: 46967.696
A52: EUR | B52: =INDEX(Regions!B:B,MATCH(A52,Regions!A:A,0)) -> Europe | C52: Greenland | D52: GL | E52: GRL | F52: 304 | G52: =INDEX(AW:AW,MATCH(E52,AQ:AQ,0))/INDEX(AW:AW,MATCH("World",AR:AR,0)) -> 7.7284103e-06 | H52: =IF(INDEX(Y:Y,MATCH(E52,W:W,0))=A52,"",INDEX(Y:Y,MATCH(E52,W:W,0))) | I52: =IF(INDEX(AC:AC,MATCH(E52,AA:AA,0))=A52,"",INDEX(AC:AC,MATCH(E52,AA:AA,0))) -> #N/A | J52: =IF(INDEX(U:U,MATCH(E52,T:T,0))=A52,"",INDEX(U:U,MATCH(E52,T:T,0))) -> #N/A | K52: =IF(INDEX(AH:AH,MATCH(E52,AE:AE,0))=A52,"",INDEX(AH:AH,MATCH(E52,AE:AE,0))) -> USA | S52: AFR_LDC | T52: DJI | U52: SSA | W52: KAZ | X52: Kazakhstan | Y52: FSU | AA52: SGS | AB52: Rest South America | AC52: OSA | AE52: IND | AF52: ind | AG52: IND | AH52: IND | AJ52: COK | AK52: OPO | AL52: OAS | AN52: WLD | AQ52: COM | AR52: Comoros | AS52: Total Population - Both sexes | AT52: Population - Est. & Proj. | AU52: 2014 | AV52: 1000 persons | AW52: 759.39
A53: EUR | B53: =INDEX(Regions!B:B,MATCH(A53,Regions!A:A,0)) -> Europe | C53: Svalbard and Jan Mayen | D53: SJ | E53: SJM | F53: 744 | G53: =INDEX(AW:AW,MATCH(E53,AQ:AQ,0))/INDEX(AW:AW,MATCH("World",AR:AR,0)) -> #N/A | H53: =IF(INDEX(Y:Y,MATCH(E53,W:W,0))=A53,"",INDEX(Y:Y,MATCH(E53,W:W,0))) -> NotAccounted | I53: =IF(INDEX(AC:AC,MATCH(E53,AA:AA,0))=A53,"",INDEX(AC:AC,MATCH(E53,AA:AA,0))) | J53: =IF(INDEX(U:U,MATCH(E53,T:T,0))=A53,"",INDEX(U:U,MATCH(E53,T:T,0))) -> #N/A | K53: =IF(INDEX(AH:AH,MATCH(E53,AE:AE,0))=A53,"",INDEX(AH:AH,MATCH(E53,AE:AE,0))) | L53: **Part of Atlantic Ocean aggregation, assigned to SSA | S53: MSA_ACP | T53: DMA | U53: OSA | W53: KGZ | X53: Kyrgyzstan | Y53: FSU | AA53: SUR | AB53: Rest South America | AC53: OSA | AE53: PAK | AF53: pak | AG53: RSA | AH53: OAS | AJ53: COL | AK53: COL | AL53: OSA | AM53: OAM | AN53: WLD | AQ53: COG | AR53: Congo | AS53: Total Population - Both sexes | AT53: Population - Est. & Proj. | AU53: 2014 | AV53: 1000 persons | AW53: 4736.976
A54: EUR | B54: =INDEX(Regions!B:B,MATCH(A54,Regions!A:A,0)) -> Europe | C54: Isle of Man | D54: IM | E54: IMN | F54: 833 | G54: =INDEX(AW:AW,MATCH(E54,AQ:AQ,0))/INDEX(AW:AW,MATCH("World",AR:AR,0)) -> 1.1444095e-05 | H54: =IF(INDEX(Y:Y,MATCH(E54,W:W,0))=A54,"",INDEX(Y:Y,MATCH(E54,W:W,0))) -> NotAccounted | I54: =IF(INDEX(AC:AC,MATCH(E54,AA:AA,0))=A54,"",INDEX(AC:AC,MATCH(E54,AA:AA,0))) -> #N/A | J54: =IF(INDEX(U:U,MATCH(E54,T:T,0))=A54,"",INDEX(U:U,MATCH(E54,T:T,0))) -> #N/A | K54: =IF(INDEX(AH:AH,MATCH(E54,AE:AE,0))=A54,"",INDEX(AH:AH,MATCH(E54,AE:AE,0))) | S54: DK000000 | T54: DNK | U54: EUR | W54: MDA | X54: MoldovaRep | Y54: FSU | AA54: URY | AB54: Rest South America | AC54: OSA | AE54: LKA | AF54: lka | AG54: RSA | AH54: OAS | AJ54: COM | AK54: OIO | AL54: SSA | AN54: WLD | AQ54: COK | AR54: Cook Islands | AS54: Total Population - Both sexes | AT54: Population - Est. & Proj. | AU54: 2014 | AV54: 1000 persons | AW54: 17.691
A55: EUR | B55: =INDEX(Regions!B:B,MATCH(A55,Regions!A:A,0)) -> Europe | C55: Jersey | D55: JE | E55: JEY | F55: 832 | G55: =INDEX(AW:AW,MATCH(E55,AQ:AQ,0))/INDEX(AW:AW,MATCH("World",AR:AR,0)) -> #N/A | H55: =IF(INDEX(Y:Y,MATCH(E55,W:W,0))=A55,"",INDEX(Y:Y,MATCH(E55,W:W,0))) -> NotAccounted | I55: =IF(INDEX(AC:AC,MATCH(E55,AA:AA,0))=A55,"",INDEX(AC:AC,MATCH(E55,AA:AA,0))) -> #N/A | J55: =IF(INDEX(U:U,MATCH(E55,T:T,0))=A55,"",INDEX(U:U,MATCH(E55,T:T,0))) -> #N/A | K55: =IF(INDEX(AH:AH,MATCH(E55,AE:AE,0))=A55,"",INDEX(AH:AH,MATCH(E55,AE:AE,0))) | S55: MSA_ACP | T55: DOM | U55: OSA | W55: TJK | X55: Tajikistan | Y55: FSU | AA55: VEN | AB55: Rest South America | AC55: OSA | AE55: AFG | AF55: xsa | AG55: RSA | AH55: OAS | AJ55: CPV | AK55: OAO | AL55: SSA | AN55: WLD | AQ55: CRI | AR55: Costa Rica | AS55: Total Population - Both sexes | AT55: Population - Est. & Proj. | AU55: 2014 | AV55: 1000 persons | AW55: 4795.396
A56: EUR | B56: =INDEX(Regions!B:B,MATCH(A56,Regions!A:A,0)) -> Europe | C56: Guernsey | D56: GG | E56: GGY | F56: 831 | G56: =INDEX(AW:AW,MATCH(E56,AQ:AQ,0))/INDEX(AW:AW,MATCH("World",AR:AR,0)) -> #N/A | H56: =IF(INDEX(Y:Y,MATCH(E56,W:W,0))=A56,"",INDEX(Y:Y,MATCH(E56,W:W,0))) -> NotAccounted | I56: =IF(INDEX(AC:AC,MATCH(E56,AA:AA,0))=A56,"",INDEX(AC:AC,MATCH(E56,AA:AA,0))) -> #N/A | J56: =IF(INDEX(U:U,MATCH(E56,T:T,0))=A56,"",INDEX(U:U,MATCH(E56,T:T,0))) -> #N/A | K56: =IF(INDEX(AH:AH,MATCH(E56,AE:AE,0))=A56,"",INDEX(AH:AH,MATCH(E56,AE:AE,0))) | S56: ALG | T56: DZA | U56: MEN | W56: TKM | X56: Turkmenistan | Y56: FSU | AA56: DZA | AB56: Northern Africa | AC56: MEN | AE56: BTN | AF56: xsa | AG56: RSA | AH56: OAS | AJ56: CRI | AK56: CRI | AL56: OSA | AM56: OAM | AN56: WLD | AQ56: CIV | AR56: Côte d'Ivoire | AS56: Total Population - Both sexes | AT56: Population - Est. & Proj. | AU56: 2014 | AV56: 1000 persons | AW56: 22647.684
A57: FSU | B57: =INDEX(Regions!B:B,MATCH(A57,Regions!A:A,0)) -> Former Soviet Union | C57: Armenia | D57: AM | E57: ARM | F57: 51 | G57: =INDEX(AW:AW,MATCH(E57,AQ:AQ,0))/INDEX(AW:AW,MATCH("World",AR:AR,0)) -> 0.00039921767 | H57: =IF(INDEX(Y:Y,MATCH(E57,W:W,0))=A57,"",INDEX(Y:Y,MATCH(E57,W:W,0))) | I57: =IF(INDEX(AC:AC,MATCH(E57,AA:AA,0))=A57,"",INDEX(AC:AC,MATCH(E57,AA:AA,0))) | J57: =IF(INDEX(U:U,MATCH(E57,T:T,0))=A57,"",INDEX(U:U,MATCH(E57,T:T,0))) | K57: =IF(INDEX(AH:AH,MATCH(E57,AE:AE,0))=A57,"",INDEX(AH:AH,MATCH(E57,AE:AE,0))) | S57: RSA | T57: ECU | U57: OSA | W57: UZB | X57: Uzbekistan | Y57: FSU | AA57: EGY | AB57: Northern Africa | AC57: MEN | AE57: MDV | AF57: xsa | AG57: RSA | AH57: OAS | AJ57: CUB | AK57: CUB | AL57: OSA | AM57: OAM | AN57: WLD | AQ57: HRV | AR57: Croatia | AS57: Total Population - Both sexes | AT57: Population - Est. & Proj. | AU57: 2014 | AV57: 1000 persons | AW57: 4255.512
A58: FSU | B58: =INDEX(Regions!B:B,MATCH(A58,Regions!A:A,0)) -> Former Soviet Union | C58: Azerbaijan | D58: AZ | E58: AZE | F58: 31 | G58: =INDEX(AW:AW,MATCH(E58,AQ:AQ,0))/INDEX(AW:AW,MATCH("World",AR:AR,0)) -> 0.0013029806 | H58: =IF(INDEX(Y:Y,MATCH(E58,W:W,0))=A58,"",INDEX(Y:Y,MATCH(E58,W:W,0))) | I58: =IF(INDEX(AC:AC,MATCH(E58,AA:AA,0))=A58,"",INDEX(AC:AC,MATCH(E58,AA:AA,0))) | J58: =IF(INDEX(U:U,MATCH(E58,T:T,0))=A58,"",INDEX(U:U,MATCH(E58,T:T,0))) | K58: =IF(INDEX(AH:AH,MATCH(E58,AE:AE,0))=A58,"",INDEX(AH:AH,MATCH(E58,AE:AE,0))) | S58: EGY | T58: EGY | U58: MEN | W58: IND | X58: India | Y58: IND | AA58: LBY | AB58: Northern Africa | AC58: MEN | AE58: NPL | AF58: npl | AG58: RSA | AH58: OAS | AJ58: CUW | AK58: CRB | AL58: OSA | AN58: WLD | AO58: Curaçao | AQ58: CUB | AR58: Cuba | AS58: Total Population - Both sexes | AT58: Population - Est. & Proj. | AU58: 2014 | AV58: 1000 persons | AW58: 11306.904
A59: FSU | B59: =INDEX(Regions!B:B,MATCH(A59,Regions!A:A,0)) -> Former Soviet Union | C59: Belarus | D59: BY | E59: BLR | F59: 112 | G59: =INDEX(AW:AW,MATCH(E59,AQ:AQ,0))/INDEX(AW:AW,MATCH("World",AR:AR,0)) -> 0.0012928525 | H59: =IF(INDEX(Y:Y,MATCH(E59,W:W,0))=A59,"",INDEX(Y:Y,MATCH(E59,W:W,0))) | I59: =IF(INDEX(AC:AC,MATCH(E59,AA:AA,0))=A59,"",INDEX(AC:AC,MATCH(E59,AA:AA,0))) | J59: =IF(INDEX(U:U,MATCH(E59,T:T,0))=A59,"",INDEX(U:U,MATCH(E59,T:T,0))) | K59: =IF(INDEX(AH:AH,MATCH(E59,AE:AE,0))=A59,"",INDEX(AH:AH,MATCH(E59,AE:AE,0))) | S59: #N/A | T59: ERI | U59: #N/A | W59: IDN | X59: Indonesia | Y59: SEA | AA59: MAR | AB59: Northern Africa | AC59: MEN | AE59: CAN | AF59: can | AG59: CAN | AH59: CAN | AJ59: CXR | AK59: OIO | AL59: SSA | AN59: WLD | AO59: Christmas Island | AQ59: CUW | AR59: Curaçao | AS59: Total Population - Both sexes | AT59: Population - Est. & Proj. | AU59: 2014 | AV59: 1000 persons | AW59: 158.422
A60: FSU | B60: =INDEX(Regions!B:B,MATCH(A60,Regions!A:A,0)) -> Former Soviet Union | C60: Georgia | D60: GE | E60: GEO | F60: 268 | G60: =INDEX(AW:AW,MATCH(E60,AQ:AQ,0))/INDEX(AW:AW,MATCH("World",AR:AR,0)) -> 0.00055313916 | H60: =IF(INDEX(Y:Y,MATCH(E60,W:W,0))=A60,"",INDEX(Y:Y,MATCH(E60,W:W,0))) | I60: =IF(INDEX(AC:AC,MATCH(E60,AA:AA,0))=A60,"",INDEX(AC:AC,MATCH(E60,AA:AA,0))) | J60: =IF(INDEX(U:U,MATCH(E60,T:T,0))=A60,"",INDEX(U:U,MATCH(E60,T:T,0))) | K60: =IF(INDEX(AH:AH,MATCH(E60,AE:AE,0))=A60,"",INDEX(AH:AH,MATCH(E60,AE:AE,0))) | S60: #N/A | T60: ESH | U60: #N/A | W60: JPN | X60: Japan | Y60: SEA | AA60: TUN | AB60: Northern Africa | AC60: MEN | AE60: USA | AF60: usa | AG60: USA | AH60: USA | AJ60: CYM | AK60: CRB | AL60: OSA | AN60: WLD | AQ60: CYP | AR60: Cyprus | AS60: Total Population - Both sexes | AT60: Population - Est. & Proj. | AU60: 2014 | AV60: 1000 persons | AW60: 1152.285
A61: FSU | B61: =INDEX(Regions!B:B,MATCH(A61,Regions!A:A,0)) -> Former Soviet Union | C61: Kazakhstan | D61: KZ | E61: KAZ | F61: 398 | G61: =INDEX(AW:AW,MATCH(E61,AQ:AQ,0))/INDEX(AW:AW,MATCH("World",AR:AR,0)) -> 0.0023717513 | H61: =IF(INDEX(Y:Y,MATCH(E61,W:W,0))=A61,"",INDEX(Y:Y,MATCH(E61,W:W,0))) | I61: =IF(INDEX(AC:AC,MATCH(E61,AA:AA,0))=A61,"",INDEX(AC:AC,MATCH(E61,AA:AA,0))) | J61: =IF(INDEX(U:U,MATCH(E61,T:T,0))=A61,"",INDEX(U:U,MATCH(E61,T:T,0))) | K61: =IF(INDEX(AH:AH,MATCH(E61,AE:AE,0))=A61,"",INDEX(AH:AH,MATCH(E61,AE:AE,0))) | S61: ES000000 | T61: ESP | U61: EUR | W61: MYS | X61: Malaysia | Y61: SEA | AA61: ESH | AB61: Northern Africa | AC61: MEN | AE61: MEX | AF61: mex | AG61: MEX | AH61: OSA | AJ61: CYP | AK61: CYP | AL61: EUR | AN61: WLD | AQ61: CZE | AR61: Czechia | AS61: Total Population - Both sexes | AT61: Population - Est. & Proj. | AU61: 2014 | AV61: 1000 persons | AW61: 10591.108
A62: FSU | B62: =INDEX(Regions!B:B,MATCH(A62,Regions!A:A,0)) -> Former Soviet Union | C62: Kyrgyzstan | D62: KG | E62: KGZ | F62: 417 | G62: =INDEX(AW:AW,MATCH(E62,AQ:AQ,0))/INDEX(AW:AW,MATCH("World",AR:AR,0)) -> 0.00080113764 | H62: =IF(INDEX(Y:Y,MATCH(E62,W:W,0))=A62,"",INDEX(Y:Y,MATCH(E62,W:W,0))) | I62: =IF(INDEX(AC:AC,MATCH(E62,AA:AA,0))=A62,"",INDEX(AC:AC,MATCH(E62,AA:AA,0))) | J62: =IF(INDEX(U:U,MATCH(E62,T:T,0))=A62,"",INDEX(U:U,MATCH(E62,T:T,0))) | K62: =IF(INDEX(AH:AH,MATCH(E62,AE:AE,0))=A62,"",INDEX(AH:AH,MATCH(E62,AE:AE,0))) | S62: EE000000 | T62: EST | U62: EUR | W62: MEX | X62: Mexico | Y62: OSA | AA62: BEN | AB62: Western Africa | AC62: SSA | AE62: BMU | AF62: xna | AG62: USA | AH62: USA | AJ62: CZE | AK62: CZE | AL62: EUR | AN62: WLD | AQ62: PRK | AR62: Democratic People's Republic of Korea | AS62: Total Population - Both sexes | AT62: Population - Est. & Proj. | AU62: 2014 | AV62: 1000 persons | AW62: 25057.79
A63: FSU | B63: =INDEX(Regions!B:B,MATCH(A63,Regions!A:A,0)) -> Former Soviet Union | C63: Rep. of Moldova | D63: MD | E63: MDA | F63: 498 | G63: =INDEX(AW:AW,MATCH(E63,AQ:AQ,0))/INDEX(AW:AW,MATCH("World",AR:AR,0)) -> 0.00055836116 | H63: =IF(INDEX(Y:Y,MATCH(E63,W:W,0))=A63,"",INDEX(Y:Y,MATCH(E63,W:W,0))) | I63: =IF(INDEX(AC:AC,MATCH(E63,AA:AA,0))=A63,"",INDEX(AC:AC,MATCH(E63,AA:AA,0))) | J63: =IF(INDEX(U:U,MATCH(E63,T:T,0))=A63,"",INDEX(U:U,MATCH(E63,T:T,0))) | K63: =IF(INDEX(AH:AH,MATCH(E63,AE:AE,0))=A63,"",INDEX(AH:AH,MATCH(E63,AE:AE,0))) | S63: ETH | T63: ETH | U63: SSA | W63: BHR | X63: Bahrain | Y63: MEN | AA63: BFA | AB63: Western Africa | AC63: SSA | AE63: GRL | AF63: xna | AG63: USA | AH63: USA | AJ63: DEU | AK63: DEU | AL63: EUR | AN63: WLD | AQ63: COD | AR63: Democratic Republic of the Congo | AS63: Total Population - Both sexes | AT63: Population - Est. & Proj. | AU63: 2014 | AV63: 1000 persons | AW63: 73767.447
A64: FSU | B64: =INDEX(Regions!B:B,MATCH(A64,Regions!A:A,0)) -> Former Soviet Union | C64: Russian Federation | D64: RU | E64: RUS | F64: 643 | G64: =INDEX(AW:AW,MATCH(E64,AQ:AQ,0))/INDEX(AW:AW,MATCH("World",AR:AR,0)) -> 0.019829894 | H64: =IF(INDEX(Y:Y,MATCH(E64,W:W,0))=A64,"",INDEX(Y:Y,MATCH(E64,W:W,0))) | I64: =IF(INDEX(AC:AC,MATCH(E64,AA:AA,0))=A64,"",INDEX(AC:AC,MATCH(E64,AA:AA,0))) | J64: =IF(INDEX(U:U,MATCH(E64,T:T,0))=A64,"",INDEX(U:U,MATCH(E64,T:T,0))) | K64: =IF(INDEX(AH:AH,MATCH(E64,AE:AE,0))=A64,"",INDEX(AH:AH,MATCH(E64,AE:AE,0))) | S64: FI000000 | T64: FIN | U64: EUR | W64: IRN | X64: Iran | Y64: MEN | AA64: CMR | AB64: Western Africa | AC64: SSA | AE64: SPM | AF64: xna | AG64: USA | AH64: USA | AJ64: DJI | AK64: DJI | AL64: SSA | AM64: AME | AN64: WLD | AQ64: DNK | AR64: Denmark | AS64: Total Population - Both sexes | AT64: Population - Est. & Proj. | AU64: 2014 | AV64: 1000 persons | AW64: 5664.196
A65: FSU | B65: =INDEX(Regions!B:B,MATCH(A65,Regions!A:A,0)) -> Former Soviet Union | C65: Tajikistan | D65: TJ | E65: TJK | F65: 762 | G65: =INDEX(AW:AW,MATCH(E65,AQ:AQ,0))/INDEX(AW:AW,MATCH("World",AR:AR,0)) -> 0.0011312548 | H65: =IF(INDEX(Y:Y,MATCH(E65,W:W,0))=A65,"",INDEX(Y:Y,MATCH(E65,W:W,0))) | I65: =IF(INDEX(AC:AC,MATCH(E65,AA:AA,0))=A65,"",INDEX(AC:AC,MATCH(E65,AA:AA,0))) | J65: =IF(INDEX(U:U,MATCH(E65,T:T,0))=A65,"",INDEX(U:U,MATCH(E65,T:T,0))) | K65: =IF(INDEX(AH:AH,MATCH(E65,AE:AE,0))=A65,"",INDEX(AH:AH,MATCH(E65,AE:AE,0))) | S65: ASOCE_REST | T65: FJI | U65: OAS | W65: IRQ | X65: Iraq | Y65: MEN | AA65: CPV | AB65: Western Africa | AC65: SSA | AE65: ARG | AF65: arg | AG65: RSM | AH65: OSA | AJ65: DMA | AK65: CRB | AL65: OSA | AN65: WLD | AQ65: DJI | AR65: Djibouti | AS65: Total Population - Both sexes | AT65: Population - Est. & Proj. | AU65: 2014 | AV65: 1000 persons | AW65: 898.695
A66: FSU | B66: =INDEX(Regions!B:B,MATCH(A66,Regions!A:A,0)) -> Former Soviet Union | C66: Turkmenistan | D66: TM | E66: TKM | F66: 795 | G66: =INDEX(AW:AW,MATCH(E66,AQ:AQ,0))/INDEX(AW:AW,MATCH("World",AR:AR,0)) -> 0.00074929543 | H66: =IF(INDEX(Y:Y,MATCH(E66,W:W,0))=A66,"",INDEX(Y:Y,MATCH(E66,W:W,0))) | I66: =IF(INDEX(AC:AC,MATCH(E66,AA:AA,0))=A66,"",INDEX(AC:AC,MATCH(E66,AA:AA,0))) | J66: =IF(INDEX(U:U,MATCH(E66,T:T,0))=A66,"",INDEX(U:U,MATCH(E66,T:T,0))) | K66: =IF(INDEX(AH:AH,MATCH(E66,AE:AE,0))=A66,"",INDEX(AH:AH,MATCH(E66,AE:AE,0))) | S66: #N/A | T66: FLK | U66: #N/A | W66: ISR | X66: Israel | Y66: MEN | AA66: CAF | AB66: Western Africa | AC66: SSA | AE66: BOL | AF66: bol | AG66: RSM | AH66: OSA | AJ66: DNK | AK66: DNK | AL66: EUR | AN66: WLD | AQ66: DMA | AR66: Dominica | AS66: Total Population - Both sexes | AT66: Population - Est. & Proj. | AU66: 2014 | AV66: 1000 persons | AW66: 71.085
A67: FSU | B67: =INDEX(Regions!B:B,MATCH(A67,Regions!A:A,0)) -> Former Soviet Union | C67: Ukraine | D67: UA | E67: UKR | F67: 804 | G67: =INDEX(AW:AW,MATCH(E67,AQ:AQ,0))/INDEX(AW:AW,MATCH("World",AR:AR,0)) -> 0.006183651 | H67: =IF(INDEX(Y:Y,MATCH(E67,W:W,0))=A67,"",INDEX(Y:Y,MATCH(E67,W:W,0))) | I67: =IF(INDEX(AC:AC,MATCH(E67,AA:AA,0))=A67,"",INDEX(AC:AC,MATCH(E67,AA:AA,0))) | J67: =IF(INDEX(U:U,MATCH(E67,T:T,0))=A67,"",INDEX(U:U,MATCH(E67,T:T,0))) | K67: =IF(INDEX(AH:AH,MATCH(E67,AE:AE,0))=A67,"",INDEX(AH:AH,MATCH(E67,AE:AE,0))) | S67: FR000000 | T67: FRA | U67: EUR | W67: JOR | X67: Jordan | Y67: MEN | AA67: TCD | AB67: Western Africa | AC67: SSA | AE67: BRA | AF67: bra | AG67: BRA | AH67: BRA | AJ67: DOM | AK67: DOM | AL67: OSA | AM67: OAM | AN67: WLD | AQ67: DOM | AR67: Dominican Republic | AS67: Total Population - Both sexes | AT67: Population - Est. & Proj. | AU67: 2014 | AV67: 1000 persons | AW67: 10165.183
A68: FSU | B68: =INDEX(Regions!B:B,MATCH(A68,Regions!A:A,0)) -> Former Soviet Union | C68: Uzbekistan | D68: UZ | E68: UZB | F68: 860 | G68: =INDEX(AW:AW,MATCH(E68,AQ:AQ,0))/INDEX(AW:AW,MATCH("World",AR:AR,0)) -> 0.0041706889 | H68: =IF(INDEX(Y:Y,MATCH(E68,W:W,0))=A68,"",INDEX(Y:Y,MATCH(E68,W:W,0))) | I68: =IF(INDEX(AC:AC,MATCH(E68,AA:AA,0))=A68,"",INDEX(AC:AC,MATCH(E68,AA:AA,0))) | J68: =IF(INDEX(U:U,MATCH(E68,T:T,0))=A68,"",INDEX(U:U,MATCH(E68,T:T,0))) | K68: =IF(INDEX(AH:AH,MATCH(E68,AE:AE,0))=A68,"",INDEX(AH:AH,MATCH(E68,AE:AE,0))) | S68: #N/A | T68: FRO | U68: #N/A | W68: KWT | X68: Kuwait | Y68: MEN | AA68: COG | AB68: Western Africa | AC68: SSA | AE68: CHL | AF68: chl | AG68: RSM | AH68: OSA | AJ68: DZA | AK68: DZA | AL68: MEN | AM68: AME | AN68: WLD | AQ68: ECU | AR68: Ecuador | AS68: Total Population - Both sexes | AT68: Population - Est. & Proj. | AU68: 2014 | AV68: 1000 persons | AW68: 15951.84
A69: IND | B69: =INDEX(Regions!B:B,MATCH(A69,Regions!A:A,0)) -> India | C69: India | D69: IN | E69: IND | F69: 356 | G69: =INDEX(AW:AW,MATCH(E69,AQ:AQ,0))/INDEX(AW:AW,MATCH("World",AR:AR,0)) -> 0.17759412 | H69: =IF(INDEX(Y:Y,MATCH(E69,W:W,0))=A69,"",INDEX(Y:Y,MATCH(E69,W:W,0))) | I69: =IF(INDEX(AC:AC,MATCH(E69,AA:AA,0))=A69,"",INDEX(AC:AC,MATCH(E69,AA:AA,0))) | J69: =IF(INDEX(U:U,MATCH(E69,T:T,0))=A69,"",INDEX(U:U,MATCH(E69,T:T,0))) | K69: =IF(INDEX(AH:AH,MATCH(E69,AE:AE,0))=A69,"",INDEX(AH:AH,MATCH(E69,AE:AE,0))) | S69: AFR_REST | T69: GAB | U69: SSA | W69: LBN | X69: Lebanon | Y69: MEN | AA69: COD | AB69: Western Africa | AC69: SSA | AE69: COL | AF69: col | AG69: RSM | AH69: OSA | AJ69: ECU | AK69: ECU | AL69: OSA | AM69: OAM | AN69: WLD | AQ69: EGY | AR69: Egypt | AS69: Total Population - Both sexes | AT69: Population - Est. & Proj. | AU69: 2014 | AV69: 1000 persons | AW69: 90424.656
A70: MEN | B70: =INDEX(Regions!B:B,MATCH(A70,Regions!A:A,0)) -> Middle-East/North Afr. | C70: Algeria | D70: DZ | E70: DZA | F70: 12 | G70: =INDEX(AW:AW,MATCH(E70,AQ:AQ,0))/INDEX(AW:AW,MATCH("World",AR:AR,0)) -> 0.0053354545 | H70: =IF(INDEX(Y:Y,MATCH(E70,W:W,0))=A70,"",INDEX(Y:Y,MATCH(E70,W:W,0))) | I70: =IF(INDEX(AC:AC,MATCH(E70,AA:AA,0))=A70,"",INDEX(AC:AC,MATCH(E70,AA:AA,0))) | J70: =IF(INDEX(U:U,MATCH(E70,T:T,0))=A70,"",INDEX(U:U,MATCH(E70,T:T,0))) | K70: =IF(INDEX(AH:AH,MATCH(E70,AE:AE,0))=A70,"",INDEX(AH:AH,MATCH(E70,AE:AE,0))) | S70: UK000000 | T70: GBR | U70: EUR | W70: OMN | X70: Oman | Y70: MEN | AA70: CIV | AB70: Western Africa | AC70: SSA | AE70: ECU | AF70: ecu | AG70: RSM | AH70: OSA | AJ70: EGY | AK70: EGY | AL70: MEN | AM70: AME | AN70: WLD | AQ70: SLV | AR70: El Salvador | AS70: Total Population - Both sexes | AT70: Population - Est. & Proj. | AU70: 2014 | AV70: 1000 persons | AW70: 6295.128
A71: MEN | B71: =INDEX(Regions!B:B,MATCH(A71,Regions!A:A,0)) -> Middle-East/North Afr. | C71: Bahrain | D71: BH | E71: BHR | F71: 48 | G71: =INDEX(AW:AW,MATCH(E71,AQ:AQ,0))/INDEX(AW:AW,MATCH("World",AR:AR,0)) -> 0.00018314212 | H71: =IF(INDEX(Y:Y,MATCH(E71,W:W,0))=A71,"",INDEX(Y:Y,MATCH(E71,W:W,0))) | I71: =IF(INDEX(AC:AC,MATCH(E71,AA:AA,0))=A71,"",INDEX(AC:AC,MATCH(E71,AA:AA,0))) | J71: =IF(INDEX(U:U,MATCH(E71,T:T,0))=A71,"",INDEX(U:U,MATCH(E71,T:T,0))) -> #N/A | K71: =IF(INDEX(AH:AH,MATCH(E71,AE:AE,0))=A71,"",INDEX(AH:AH,MATCH(E71,AE:AE,0))) | S71: FSU | T71: GEO | U71: FSU | W71: PSE | X71: Palestin | Y71: MEN | AA71: GNQ | AB71: Western Africa | AC71: SSA | AE71: PRY | AF71: pry | AG71: RSM | AH71: OSA | AJ71: ERI | AK71: ERI | AL71: SSA | AM71: AME | AN71: WLD | AQ71: GNQ | AR71: Equatorial Guinea | AS71: Total Population - Both sexes | AT71: Population - Est. & Proj. | AU71: 2014 | AV71: 1000 persons | AW71: 1122.277
A72: MEN | B72: =INDEX(Regions!B:B,MATCH(A72,Regions!A:A,0)) -> Middle-East/North Afr. | C72: Egypt | D72: EG | E72: EGY | F72: 818 | G72: =INDEX(AW:AW,MATCH(E72,AQ:AQ,0))/INDEX(AW:AW,MATCH("World",AR:AR,0)) -> 0.012394935 | H72: =IF(INDEX(Y:Y,MATCH(E72,W:W,0))=A72,"",INDEX(Y:Y,MATCH(E72,W:W,0))) | I72: =IF(INDEX(AC:AC,MATCH(E72,AA:AA,0))=A72,"",INDEX(AC:AC,MATCH(E72,AA:AA,0))) | J72: =IF(INDEX(U:U,MATCH(E72,T:T,0))=A72,"",INDEX(U:U,MATCH(E72,T:T,0))) | K72: =IF(INDEX(AH:AH,MATCH(E72,AE:AE,0))=A72,"",INDEX(AH:AH,MATCH(E72,AE:AE,0))) | S72: AFR_REST | T72: GHA | U72: SSA | W72: QAT | X72: Qatar | Y72: MEN | AA72: GAB | AB72: Western Africa | AC72: SSA | AE72: PER | AF72: per | AG72: RSM | AH72: OSA | AJ72: ESH | AK72: MOR | AL72: MEN | AM72: AME | AN72: WLD | AQ72: ERI | AR72: Eritrea | AS72: Total Population - Both sexes | AT72: Population - Est. & Proj. | AU72: 2014 | AV72: 1000 persons | AW72: 3311.449
A73: MEN | B73: =INDEX(Regions!B:B,MATCH(A73,Regions!A:A,0)) -> Middle-East/North Afr. | C73: Iran | D73: IR | E73: IRN | F73: 364 | G73: =INDEX(AW:AW,MATCH(E73,AQ:AQ,0))/INDEX(AW:AW,MATCH("World",AR:AR,0)) -> 0.010618599 | H73: =IF(INDEX(Y:Y,MATCH(E73,W:W,0))=A73,"",INDEX(Y:Y,MATCH(E73,W:W,0))) | I73: =IF(INDEX(AC:AC,MATCH(E73,AA:AA,0))=A73,"",INDEX(AC:AC,MATCH(E73,AA:AA,0))) | J73: =IF(INDEX(U:U,MATCH(E73,T:T,0))=A73,"",INDEX(U:U,MATCH(E73,T:T,0))) | K73: =IF(INDEX(AH:AH,MATCH(E73,AE:AE,0))=A73,"",INDEX(AH:AH,MATCH(E73,AE:AE,0))) | S73: AFR_LDC | T73: GIN | U73: SSA | W73: SAU | X73: SaudiArabia | Y73: MEN | AA73: GMB | AB73: Western Africa | AC73: SSA | AE73: URY | AF73: ury | AG73: RSM | AH73: OSA | AJ73: ESP | AK73: SPP | AL73: EUR | AN73: WLD | AQ73: EST | AR73: Estonia | AS73: Total Population - Both sexes | AT73: Population - Est. & Proj. | AU73: 2014 | AV73: 1000 persons | AW73: 1316.277
A74: MEN | B74: =INDEX(Regions!B:B,MATCH(A74,Regions!A:A,0)) -> Middle-East/North Afr. | C74: Iraq | D74: IQ | E74: IRQ | F74: 368 | G74: =INDEX(AW:AW,MATCH(E74,AQ:AQ,0))/INDEX(AW:AW,MATCH("World",AR:AR,0)) -> 0.0047170088 | H74: =IF(INDEX(Y:Y,MATCH(E74,W:W,0))=A74,"",INDEX(Y:Y,MATCH(E74,W:W,0))) | I74: =IF(INDEX(AC:AC,MATCH(E74,AA:AA,0))=A74,"",INDEX(AC:AC,MATCH(E74,AA:AA,0))) | J74: =IF(INDEX(U:U,MATCH(E74,T:T,0))=A74,"",INDEX(U:U,MATCH(E74,T:T,0))) | K74: =IF(INDEX(AH:AH,MATCH(E74,AE:AE,0))=A74,"",INDEX(AH:AH,MATCH(E74,AE:AE,0))) | S74: #N/A | T74: GLP | U74: #N/A | W74: SYR | X74: Syria | Y74: MEN | AA74: GHA | AB74: Western Africa | AC74: SSA | AE74: VEN | AF74: ven | AG74: RSM | AH74: OSA | AJ74: EST | AK74: BLT | AL74: EUR | AN74: WLD | AQ74: SWZ | AR74: Eswatini | AS74: Total Population - Both sexes | AT74: Population - Est. & Proj. | AU74: 2014 | AV74: 1000 persons | AW74: 1095.019
A75: MEN | B75: =INDEX(Regions!B:B,MATCH(A75,Regions!A:A,0)) -> Middle-East/North Afr. | C75: Israel | D75: IL | E75: ISR | F75: 376 | G75: =INDEX(AW:AW,MATCH(E75,AQ:AQ,0))/INDEX(AW:AW,MATCH("World",AR:AR,0)) -> 0.0010766141 | H75: =IF(INDEX(Y:Y,MATCH(E75,W:W,0))=A75,"",INDEX(Y:Y,MATCH(E75,W:W,0))) | I75: =IF(INDEX(AC:AC,MATCH(E75,AA:AA,0))=A75,"",INDEX(AC:AC,MATCH(E75,AA:AA,0))) | J75: =IF(INDEX(U:U,MATCH(E75,T:T,0))=A75,"",INDEX(U:U,MATCH(E75,T:T,0))) | K75: =IF(INDEX(AH:AH,MATCH(E75,AE:AE,0))=A75,"",INDEX(AH:AH,MATCH(E75,AE:AE,0))) | S75: AFR_LDC | T75: GMB | U75: SSA | W75: ARE | X75: UntdArabEm | Y75: MEN | AA75: GIN | AB75: Western Africa | AC75: SSA | AE75: FLK | AF75: xsm | AG75: RSM | AH75: OSA | AJ75: ETH | AK75: ETH | AL75: SSA | AM75: AME | AN75: WLD | AQ75: ETH | AR75: Ethiopia | AS75: Total Population - Both sexes | AT75: Population - Est. & Proj. | AU75: 2014 | AV75: 1000 persons | AW75: 98094.265
A76: MEN | B76: =INDEX(Regions!B:B,MATCH(A76,Regions!A:A,0)) -> Middle-East/North Afr. | C76: Jordan | D76: JO | E76: JOR | F76: 400 | G76: =INDEX(AW:AW,MATCH(E76,AQ:AQ,0))/INDEX(AW:AW,MATCH("World",AR:AR,0)) -> 0.0012225459 | H76: =IF(INDEX(Y:Y,MATCH(E76,W:W,0))=A76,"",INDEX(Y:Y,MATCH(E76,W:W,0))) | I76: =IF(INDEX(AC:AC,MATCH(E76,AA:AA,0))=A76,"",INDEX(AC:AC,MATCH(E76,AA:AA,0))) | J76: =IF(INDEX(U:U,MATCH(E76,T:T,0))=A76,"",INDEX(U:U,MATCH(E76,T:T,0))) | K76: =IF(INDEX(AH:AH,MATCH(E76,AE:AE,0))=A76,"",INDEX(AH:AH,MATCH(E76,AE:AE,0))) | S76: AFR_LDC | T76: GNB | U76: SSA | W76: YEM | X76: Yemen | Y76: MEN | AA76: GNB | AB76: Western Africa | AC76: SSA | AE76: GUF | AF76: xsm | AG76: RSM | AH76: OSA | AJ76: FIN | AK76: FNP | AL76: EUR | AN76: WLD | AQ76: FLK | AR76: Falkland Islands (Malvinas) | AS76: Total Population - Both sexes | AT76: Population - Est. & Proj. | AU76: 2014 | AV76: 1000 persons | AW76: 2.792
A77: MEN | B77: =INDEX(Regions!B:B,MATCH(A77,Regions!A:A,0)) -> Middle-East/North Afr. | C77: Kuwait | D77: KW | E77: KWT | F77: 414 | G77: =INDEX(AW:AW,MATCH(E77,AQ:AQ,0))/INDEX(AW:AW,MATCH("World",AR:AR,0)) -> 0.00050593474 | H77: =IF(INDEX(Y:Y,MATCH(E77,W:W,0))=A77,"",INDEX(Y:Y,MATCH(E77,W:W,0))) | I77: =IF(INDEX(AC:AC,MATCH(E77,AA:AA,0))=A77,"",INDEX(AC:AC,MATCH(E77,AA:AA,0))) | J77: =IF(INDEX(U:U,MATCH(E77,T:T,0))=A77,"",INDEX(U:U,MATCH(E77,T:T,0))) | K77: =IF(INDEX(AH:AH,MATCH(E77,AE:AE,0))=A77,"",INDEX(AH:AH,MATCH(E77,AE:AE,0))) | S77: #N/A | T77: GNQ | U77: #N/A | W77: NZL | X77: NewZealand | Y77: ANZ | AA77: LBR | AB77: Western Africa | AC77: SSA | AE77: SGS | AF77: xsm | AG77: RSM | AH77: OSA | AJ77: FJI | AK77: FJI | AL77: OAS | AN77: WLD | AQ77: FRO | AR77: Faroe Islands | AS77: Total Population - Both sexes | AT77: Population - Est. & Proj. | AU77: 2014 | AV77: 1000 persons | AW77: 47.96
A78: MEN | B78: =INDEX(Regions!B:B,MATCH(A78,Regions!A:A,0)) -> Middle-East/North Afr. | C78: Lebanon | D78: LB | E78: LBN | F78: 422 | G78: =INDEX(AW:AW,MATCH(E78,AQ:AQ,0))/INDEX(AW:AW,MATCH("World",AR:AR,0)) -> 0.00085823091 | H78: =IF(INDEX(Y:Y,MATCH(E78,W:W,0))=A78,"",INDEX(Y:Y,MATCH(E78,W:W,0))) | I78: =IF(INDEX(AC:AC,MATCH(E78,AA:AA,0))=A78,"",INDEX(AC:AC,MATCH(E78,AA:AA,0))) | J78: =IF(INDEX(U:U,MATCH(E78,T:T,0))=A78,"",INDEX(U:U,MATCH(E78,T:T,0))) | K78: =IF(INDEX(AH:AH,MATCH(E78,AE:AE,0))=A78,"",INDEX(AH:AH,MATCH(E78,AE:AE,0))) | S78: EL000000 | T78: GRC | U78: EUR | W78: DZA | X78: Algeria | Y78: MEN | AA78: MLI | AB78: Western Africa | AC78: SSA | AE78: SUR | AF78: xsm | AG78: RSM | AH78: OSA | AJ78: FLK | AK78: OAO | AL78: SSA | AN78: WLD | AO78: **Part of Atlantic Ocean aggregation, assigned to SSA | AQ78: FJI | AR78: Fiji | AS78: Total Population - Both sexes | AT78: Population - Est. & Proj. | AU78: 2014 | AV78: 1000 persons | AW78: 866.453
A79: MEN | B79: =INDEX(Regions!B:B,MATCH(A79,Regions!A:A,0)) -> Middle-East/North Afr. | C79: Libyan Arab Jamahiriya | D79: LY | E79: LBY | F79: 434 | G79: =INDEX(AW:AW,MATCH(E79,AQ:AQ,0))/INDEX(AW:AW,MATCH("World",AR:AR,0)) -> 0.00087207449 | H79: =IF(INDEX(Y:Y,MATCH(E79,W:W,0))=A79,"",INDEX(Y:Y,MATCH(E79,W:W,0))) | I79: =IF(INDEX(AC:AC,MATCH(E79,AA:AA,0))=A79,"",INDEX(AC:AC,MATCH(E79,AA:AA,0))) | J79: =IF(INDEX(U:U,MATCH(E79,T:T,0))=A79,"",INDEX(U:U,MATCH(E79,T:T,0))) -> #N/A | K79: =IF(INDEX(AH:AH,MATCH(E79,AE:AE,0))=A79,"",INDEX(AH:AH,MATCH(E79,AE:AE,0))) | S79: MSA_ACP | T79: GRD | U79: OSA | W79: EGY | X79: Egypt | Y79: MEN | AA79: MRT | AB79: Western Africa | AC79: SSA | AE79: CRI | AF79: cri | AG79: CAM | AH79: OSA | AJ79: FRA | AK79: FRP | AL79: EUR | AN79: WLD | AQ79: FIN | AR79: Finland | AS79: Total Population - Both sexes | AT79: Population - Est. & Proj. | AU79: 2014 | AV79: 1000 persons | AW79: 5461.411
A80: MEN | B80: =INDEX(Regions!B:B,MATCH(A80,Regions!A:A,0)) -> Middle-East/North Afr. | C80: Morocco | D80: MA | E80: MAR | F80: 504 | G80: =INDEX(AW:AW,MATCH(E80,AQ:AQ,0))/INDEX(AW:AW,MATCH("World",AR:AR,0)) -> 0.004686908 | H80: =IF(INDEX(Y:Y,MATCH(E80,W:W,0))=A80,"",INDEX(Y:Y,MATCH(E80,W:W,0))) | I80: =IF(INDEX(AC:AC,MATCH(E80,AA:AA,0))=A80,"",INDEX(AC:AC,MATCH(E80,AA:AA,0))) | J80: =IF(INDEX(U:U,MATCH(E80,T:T,0))=A80,"",INDEX(U:U,MATCH(E80,T:T,0))) | K80: =IF(INDEX(AH:AH,MATCH(E80,AE:AE,0))=A80,"",INDEX(AH:AH,MATCH(E80,AE:AE,0))) | S80: RSA | T80: GTM | U80: OSA | W80: LBY | X80: Libya | Y80: MEN | AA80: NER | AB80: Western Africa | AC80: SSA | AE80: GTM | AF80: gtm | AG80: CAM | AH80: OSA | AJ80: FRO | AK80: OAO | AL80: SSA | AN80: WLD | AO80: Faroe Islands | AQ80: FRA | AR80: France | AS80: Total Population - Both sexes | AT80: Population - Est. & Proj. | AU80: 2014 | AV80: 1000 persons | AW80: 64193.55
A81: MEN | B81: =INDEX(Regions!B:B,MATCH(A81,Regions!A:A,0)) -> Middle-East/North Afr. | C81: Oman | D81: OM | E81: OMN | F81: 512 | G81: =INDEX(AW:AW,MATCH(E81,AQ:AQ,0))/INDEX(AW:AW,MATCH("World",AR:AR,0)) -> 0.00055203557 | H81: =IF(INDEX(Y:Y,MATCH(E81,W:W,0))=A81,"",INDEX(Y:Y,MATCH(E81,W:W,0))) | I81: =IF(INDEX(AC:AC,MATCH(E81,AA:AA,0))=A81,"",INDEX(AC:AC,MATCH(E81,AA:AA,0))) | J81: =IF(INDEX(U:U,MATCH(E81,T:T,0))=A81,"",INDEX(U:U,MATCH(E81,T:T,0))) | K81: =IF(INDEX(AH:AH,MATCH(E81,AE:AE,0))=A81,"",INDEX(AH:AH,MATCH(E81,AE:AE,0))) | S81: #N/A | T81: GUF | U81: #N/A | W81: MAR | X81: Morocco | Y81: MEN | AA81: NGA | AB81: Western Africa | AC81: SSA | AE81: NIC | AF81: nic | AG81: CAM | AH81: OSA | AJ81: FSM | AK81: OPO | AL81: OAS | AN81: WLD | AQ81: GUF | AR81: French Guyana | AS81: Total Population - Both sexes | AT81: Population - Est. & Proj. | AU81: 2014 | AV81: 1000 persons | AW81: 254.773
A82: MEN | B82: =INDEX(Regions!B:B,MATCH(A82,Regions!A:A,0)) -> Middle-East/North Afr. | C82: Palestinian Territories | D82: PS | E82: PSE | F82: 275 | G82: =INDEX(AW:AW,MATCH(E82,AQ:AQ,0))/INDEX(AW:AW,MATCH("World",AR:AR,0)) -> 0.00060705449 | H82: =IF(INDEX(Y:Y,MATCH(E82,W:W,0))=A82,"",INDEX(Y:Y,MATCH(E82,W:W,0))) | I82: =IF(INDEX(AC:AC,MATCH(E82,AA:AA,0))=A82,"",INDEX(AC:AC,MATCH(E82,AA:AA,0))) -> #N/A | J82: =IF(INDEX(U:U,MATCH(E82,T:T,0))=A82,"",INDEX(U:U,MATCH(E82,T:T,0))) -> #N/A | K82: =IF(INDEX(AH:AH,MATCH(E82,AE:AE,0))=A82,"",INDEX(AH:AH,MATCH(E82,AE:AE,0))) | S82: #N/A | T82: GUM | U82: #N/A | W82: TUN | X82: Tunisia | Y82: MEN | AA82: SHN | AB82: Western Africa | AC82: SSA | AE82: PAN | AF82: pan | AG82: CAM | AH82: OSA | AJ82: GAB | AK82: GAB | AL82: SSA | AM82: AME | AN82: WLD | AQ82: PYF | AR82: French Polynesia | AS82: Total Population - Both sexes | AT82: Population - Est. & Proj. | AU82: 2014 | AV82: 1000 persons | AW82: 271.705
A83: MEN | B83: =INDEX(Regions!B:B,MATCH(A83,Regions!A:A,0)) -> Middle-East/North Afr. | C83: Qatar | D83: QA | E83: QAT | F83: 634 | G83: =INDEX(AW:AW,MATCH(E83,AQ:AQ,0))/INDEX(AW:AW,MATCH("World",AR:AR,0)) -> 0.0003370939 | H83: =IF(INDEX(Y:Y,MATCH(E83,W:W,0))=A83,"",INDEX(Y:Y,MATCH(E83,W:W,0))) | I83: =IF(INDEX(AC:AC,MATCH(E83,AA:AA,0))=A83,"",INDEX(AC:AC,MATCH(E83,AA:AA,0))) | J83: =IF(INDEX(U:U,MATCH(E83,T:T,0))=A83,"",INDEX(U:U,MATCH(E83,T:T,0))) -> #N/A | K83: =IF(INDEX(AH:AH,MATCH(E83,AE:AE,0))=A83,"",INDEX(AH:AH,MATCH(E83,AE:AE,0))) | S83: MSA_ACP | T83: GUY | U83: OSA | W83: ESH | X83: WestSahara | Y83: MEN | AA83: STP | AB83: Western Africa | AC83: SSA | AE83: BLZ | AF83: xca | AG83: CAM | AH83: OSA | AJ83: GBR | AK83: UKP | AL83: EUR | AN83: WLD | AQ83: GAB | AR83: Gabon | AS83: Total Population - Both sexes | AT83: Population - Est. & Proj. | AU83: 2014 | AV83: 1000 persons | AW83: 1883.8
A84: MEN | B84: =INDEX(Regions!B:B,MATCH(A84,Regions!A:A,0)) -> Middle-East/North Afr. | C84: Saudi Arabia | D84: SA | E84: SAU | F84: 682 | G84: =INDEX(AW:AW,MATCH(E84,AQ:AQ,0))/INDEX(AW:AW,MATCH("World",AR:AR,0)) -> 0.0042378841 | H84: =IF(INDEX(Y:Y,MATCH(E84,W:W,0))=A84,"",INDEX(Y:Y,MATCH(E84,W:W,0))) | I84: =IF(INDEX(AC:AC,MATCH(E84,AA:AA,0))=A84,"",INDEX(AC:AC,MATCH(E84,AA:AA,0))) | J84: =IF(INDEX(U:U,MATCH(E84,T:T,0))=A84,"",INDEX(U:U,MATCH(E84,T:T,0))) | K84: =IF(INDEX(AH:AH,MATCH(E84,AE:AE,0))=A84,"",INDEX(AH:AH,MATCH(E84,AE:AE,0))) | S84: RSA | T84: HND | U84: OSA | W84: FJI | X84: FijiIslands | Y84: OAS | AA84: SEN | AB84: Western Africa | AC84: SSA | AE84: SLV | AF84: slv | AG84: CAM | AH84: OSA | AJ84: GEO | AK84: GEO | AL84: FSU | AN84: WLD | AQ84: GMB | AR84: Gambia | AS84: Total Population - Both sexes | AT84: Population - Est. & Proj. | AU84: 2014 | AV84: 1000 persons | AW84: 2024.042
A85: MEN | B85: =INDEX(Regions!B:B,MATCH(A85,Regions!A:A,0)) -> Middle-East/North Afr. | C85: Syrian Arab Republic | D85: SY | E85: SYR | F85: 760 | G85: =INDEX(AW:AW,MATCH(E85,AQ:AQ,0))/INDEX(AW:AW,MATCH("World",AR:AR,0)) -> 0.0025647656 | H85: =IF(INDEX(Y:Y,MATCH(E85,W:W,0))=A85,"",INDEX(Y:Y,MATCH(E85,W:W,0))) | I85: =IF(INDEX(AC:AC,MATCH(E85,AA:AA,0))=A85,"",INDEX(AC:AC,MATCH(E85,AA:AA,0))) | J85: =IF(INDEX(U:U,MATCH(E85,T:T,0))=A85,"",INDEX(U:U,MATCH(E85,T:T,0))) -> #N/A | K85: =IF(INDEX(AH:AH,MATCH(E85,AE:AE,0))=A85,"",INDEX(AH:AH,MATCH(E85,AE:AE,0))) | S85: HR000000 | T85: HRV | U85: EUR | W85: PYF | X85: FrPolynesia | Y85: OAS | AA85: SLE | AB85: Western Africa | AC85: SSA | AE85: HND | AF85: hnd | AG85: CAM | AH85: OSA | AJ85: GGY | AK85: UKP | AL85: EUR | AN85: WLD | AQ85: GEO | AR85: Georgia | AS85: Total Population - Both sexes | AT85: Population - Est. & Proj. | AU85: 2014 | AV85: 1000 persons | AW85: 4035.311
A86: MEN | B86: =INDEX(Regions!B:B,MATCH(A86,Regions!A:A,0)) -> Middle-East/North Afr. | C86: Tunisia | D86: TN | E86: TUN | F86: 788 | G86: =INDEX(AW:AW,MATCH(E86,AQ:AQ,0))/INDEX(AW:AW,MATCH("World",AR:AR,0)) -> 0.0015164853 | H86: =IF(INDEX(Y:Y,MATCH(E86,W:W,0))=A86,"",INDEX(Y:Y,MATCH(E86,W:W,0))) | I86: =IF(INDEX(AC:AC,MATCH(E86,AA:AA,0))=A86,"",INDEX(AC:AC,MATCH(E86,AA:AA,0))) | J86: =IF(INDEX(U:U,MATCH(E86,T:T,0))=A86,"",INDEX(U:U,MATCH(E86,T:T,0))) | K86: =IF(INDEX(AH:AH,MATCH(E86,AE:AE,0))=A86,"",INDEX(AH:AH,MATCH(E86,AE:AE,0))) | S86: MSA_ACP | T86: HTI | U86: OSA | W86: NCL | X86: NewCaledonia | Y86: OAS | AA86: TGO | AB86: Western Africa | AC86: SSA | AE86: AIA | AF86: xcb | AG86: CAM | AH86: OSA | AJ86: GHA | AK86: GHA | AL86: SSA | AM86: AME | AN86: WLD | AQ86: DEU | AR86: Germany | AS86: Total Population - Both sexes | AT86: Population - Est. & Proj. | AU86: 2014 | AV86: 1000 persons | AW86: 81450.378
A87: MEN | B87: =INDEX(Regions!B:B,MATCH(A87,Regions!A:A,0)) -> Middle-East/North Afr. | C87: Turkey | D87: TR | E87: TUR | F87: 792 | G87: =INDEX(AW:AW,MATCH(E87,AQ:AQ,0))/INDEX(AW:AW,MATCH("World",AR:AR,0)) -> 0.010586179 | H87: =IF(INDEX(Y:Y,MATCH(E87,W:W,0))=A87,"",INDEX(Y:Y,MATCH(E87,W:W,0))) | I87: =IF(INDEX(AC:AC,MATCH(E87,AA:AA,0))=A87,"",INDEX(AC:AC,MATCH(E87,AA:AA,0))) | J87: =IF(INDEX(U:U,MATCH(E87,T:T,0))=A87,"",INDEX(U:U,MATCH(E87,T:T,0))) | K87: =IF(INDEX(AH:AH,MATCH(E87,AE:AE,0))=A87,"",INDEX(AH:AH,MATCH(E87,AE:AE,0))) | S87: HU000000 | T87: HUN | U87: EUR | W87: PNG | X87: PapuaNGuin | Y87: OAS | AA87: BDI | AB87: Eastern Africa | AC87: SSA | AE87: ATG | AF87: xcb | AG87: CAM | AH87: OSA | AJ87: GIB | AK87: SPP | AL87: EUR | AN87: WLD | AQ87: GHA | AR87: Ghana | AS87: Total Population - Both sexes | AT87: Population - Est. & Proj. | AU87: 2014 | AV87: 1000 persons | AW87: 27224.473
A88: MEN | B88: =INDEX(Regions!B:B,MATCH(A88,Regions!A:A,0)) -> Middle-East/North Afr. | C88: United Arab Emirates | D88: AE | E88: ARE | F88: 784 | G88: =INDEX(AW:AW,MATCH(E88,AQ:AQ,0))/INDEX(AW:AW,MATCH("World",AR:AR,0)) -> 0.0012630305 | H88: =IF(INDEX(Y:Y,MATCH(E88,W:W,0))=A88,"",INDEX(Y:Y,MATCH(E88,W:W,0))) | I88: =IF(INDEX(AC:AC,MATCH(E88,AA:AA,0))=A88,"",INDEX(AC:AC,MATCH(E88,AA:AA,0))) | J88: =IF(INDEX(U:U,MATCH(E88,T:T,0))=A88,"",INDEX(U:U,MATCH(E88,T:T,0))) | K88: =IF(INDEX(AH:AH,MATCH(E88,AE:AE,0))=A88,"",INDEX(AH:AH,MATCH(E88,AE:AE,0))) | S88: INDO | T88: IDN | U88: SEA | W88: WSM | X88: Samoa | Y88: OAS | AA88: COM | AB88: Eastern Africa | AC88: SSA | AE88: ABW | AF88: xcb | AG88: CAM | AH88: OSA | AJ88: GIN | AK88: GIN | AL88: SSA | AM88: AME | AN88: WLD | AQ88: GIB | AR88: Gibraltar | AS88: Total Population - Both sexes | AT88: Population - Est. & Proj. | AU88: 2014 | AV88: 1000 persons | AW88: 33.725
A89: MEN | B89: =INDEX(Regions!B:B,MATCH(A89,Regions!A:A,0)) -> Middle-East/North Afr. | C89: Yemen | D89: YE | E89: YEM | F89: 887 | G89: =INDEX(AW:AW,MATCH(E89,AQ:AQ,0))/INDEX(AW:AW,MATCH("World",AR:AR,0)) -> 0.0035397472 | H89: =IF(INDEX(Y:Y,MATCH(E89,W:W,0))=A89,"",INDEX(Y:Y,MATCH(E89,W:W,0))) | I89: =IF(INDEX(AC:AC,MATCH(E89,AA:AA,0))=A89,"",INDEX(AC:AC,MATCH(E89,AA:AA,0))) | J89: =IF(INDEX(U:U,MATCH(E89,T:T,0))=A89,"",INDEX(U:U,MATCH(E89,T:T,0))) -> OAS | K89: =IF(INDEX(AH:AH,MATCH(E89,AE:AE,0))=A89,"",INDEX(AH:AH,MATCH(E89,AE:AE,0))) | S89: #N/A | T89: IMN | U89: #N/A | W89: SLB | X89: SolomonIs | Y89: OAS | AA89: DJI | AB89: Eastern Africa | AC89: SSA | AE89: BHS | AF89: xcb | AG89: CAM | AH89: OSA | AJ89: GLP | AK89: CRB | AL89: OSA | AN89: WLD | AQ89: GRC | AR89: Greece | AS89: Total Population - Both sexes | AT89: Population - Est. & Proj. | AU89: 2014 | AV89: 1000 persons | AW89: 10701.456
A90: MEN | B90: =INDEX(Regions!B:B,MATCH(A90,Regions!A:A,0)) -> Middle-East/North Afr. | C90: Western Sahara | D90: EH | E90: ESH | F90: 732 | G90: =INDEX(AW:AW,MATCH(E90,AQ:AQ,0))/INDEX(AW:AW,MATCH("World",AR:AR,0)) -> 7.05928e-05 | H90: =IF(INDEX(Y:Y,MATCH(E90,W:W,0))=A90,"",INDEX(Y:Y,MATCH(E90,W:W,0))) | I90: =IF(INDEX(AC:AC,MATCH(E90,AA:AA,0))=A90,"",INDEX(AC:AC,MATCH(E90,AA:AA,0))) | J90: =IF(INDEX(U:U,MATCH(E90,T:T,0))=A90,"",INDEX(U:U,MATCH(E90,T:T,0))) -> #N/A | K90: =IF(INDEX(AH:AH,MATCH(E90,AE:AE,0))=A90,"",INDEX(AH:AH,MATCH(E90,AE:AE,0))) | S90: IND | T90: IND | U90: IND | W90: VUT | X90: Vanuatu | Y90: OAS | AA90: ERI | AB90: Eastern Africa | AC90: SSA | AE90: BRB | AF90: xcb | AG90: CAM | AH90: OSA | AJ90: GMB | AK90: GMB | AL90: SSA | AM90: AME | AN90: WLD | AQ90: GRL | AR90: Greenland | AS90: Total Population - Both sexes | AT90: Population - Est. & Proj. | AU90: 2014 | AV90: 1000 persons | AW90: 56.381
A91: OAS | B91: =INDEX(Regions!B:B,MATCH(A91,Regions!A:A,0)) -> Other Asia | C91: Afghanistan | D91: AF | E91: AFG | F91: 4 | G91: =INDEX(AW:AW,MATCH(E91,AQ:AQ,0))/INDEX(AW:AW,MATCH("World",AR:AR,0)) -> 0.0045742925 | H91: =IF(INDEX(Y:Y,MATCH(E91,W:W,0))=A91,"",INDEX(Y:Y,MATCH(E91,W:W,0))) -> NotAccounted | I91: =IF(INDEX(AC:AC,MATCH(E91,AA:AA,0))=A91,"",INDEX(AC:AC,MATCH(E91,AA:AA,0))) | J91: =IF(INDEX(U:U,MATCH(E91,T:T,0))=A91,"",INDEX(U:U,MATCH(E91,T:T,0))) | K91: =IF(INDEX(AH:AH,MATCH(E91,AE:AE,0))=A91,"",INDEX(AH:AH,MATCH(E91,AE:AE,0))) | S91: IR000000 | T91: IRL | U91: EUR | W91: BHS | X91: Bahamas | Y91: OSA | AA91: ETH | AB91: Eastern Africa | AC91: SSA | AE91: CYM | AF91: xcb | AG91: CAM | AH91: OSA | AJ91: GNB | AK91: GNB | AL91: SSA | AM91: AME | AN91: WLD | AQ91: GRD | AR91: Grenada | AS91: Total Population - Both sexes | AT91: Population - Est. & Proj. | AU91: 2014 | AV91: 1000 persons | AW91: 108.902
A92: OAS | B92: =INDEX(Regions!B:B,MATCH(A92,Regions!A:A,0)) -> Other Asia | C92: Bangladesh | D92: BD | E92: BGD | F92: 50 | G92: =INDEX(AW:AW,MATCH(E92,AQ:AQ,0))/INDEX(AW:AW,MATCH("World",AR:AR,0)) -> 0.021180428 | H92: =IF(INDEX(Y:Y,MATCH(E92,W:W,0))=A92,"",INDEX(Y:Y,MATCH(E92,W:W,0))) | I92: =IF(INDEX(AC:AC,MATCH(E92,AA:AA,0))=A92,"",INDEX(AC:AC,MATCH(E92,AA:AA,0))) | J92: =IF(INDEX(U:U,MATCH(E92,T:T,0))=A92,"",INDEX(U:U,MATCH(E92,T:T,0))) | K92: =IF(INDEX(AH:AH,MATCH(E92,AE:AE,0))=A92,"",INDEX(AH:AH,MATCH(E92,AE:AE,0))) | S92: MIDEAST | T92: IRN | U92: MEN | W92: BLZ | X92: Belize | Y92: OSA | AA92: KEN | AB92: Eastern Africa | AC92: SSA | AE92: CUB | AF92: xcb | AG92: CAM | AH92: OSA | AJ92: GNQ | AK92: GNQ | AL92: SSA | AM92: AME | AN92: WLD | AQ92: GLP | AR92: Guadeloupe | AS92: Total Population - Both sexes | AT92: Population - Est. & Proj. | AU92: 2014 | AV92: 1000 persons | AW92: 401.314
A93: OAS | B93: =INDEX(Regions!B:B,MATCH(A93,Regions!A:A,0)) -> Other Asia | C93: Bhutan | D93: BT | E93: BTN | F93: 64 | G93: =INDEX(AW:AW,MATCH(E93,AQ:AQ,0))/INDEX(AW:AW,MATCH("World",AR:AR,0)) -> 9.8564269e-05 | H93: =IF(INDEX(Y:Y,MATCH(E93,W:W,0))=A93,"",INDEX(Y:Y,MATCH(E93,W:W,0))) | I93: =IF(INDEX(AC:AC,MATCH(E93,AA:AA,0))=A93,"",INDEX(AC:AC,MATCH(E93,AA:AA,0))) | J93: =IF(INDEX(U:U,MATCH(E93,T:T,0))=A93,"",INDEX(U:U,MATCH(E93,T:T,0))) -> #N/A | K93: =IF(INDEX(AH:AH,MATCH(E93,AE:AE,0))=A93,"",INDEX(AH:AH,MATCH(E93,AE:AE,0))) | S93: MIDEAST | T93: IRQ | U93: MEN | W93: CRI | X93: CostaRica | Y93: OSA | AA93: MDG | AB93: Eastern Africa | AC93: SSA | AE93: DMA | AF93: xcb | AG93: CAM | AH93: OSA | AJ93: GRC | AK93: GRC | AL93: EUR | AN93: WLD | AQ93: GUM | AR93: Guam | AS93: Total Population - Both sexes | AT93: Population - Est. & Proj. | AU93: 2014 | AV93: 1000 persons | AW93: 161.016
A94: OAS | B94: =INDEX(Regions!B:B,MATCH(A94,Regions!A:A,0)) -> Other Asia | C94: Cook Islands | D94: CK | E94: COK | F94: 184 | G94: =INDEX(AW:AW,MATCH(E94,AQ:AQ,0))/INDEX(AW:AW,MATCH("World",AR:AR,0)) -> 2.424989e-06 | H94: =IF(INDEX(Y:Y,MATCH(E94,W:W,0))=A94,"",INDEX(Y:Y,MATCH(E94,W:W,0))) -> NotAccounted | I94: =IF(INDEX(AC:AC,MATCH(E94,AA:AA,0))=A94,"",INDEX(AC:AC,MATCH(E94,AA:AA,0))) -> ANZ | J94: =IF(INDEX(U:U,MATCH(E94,T:T,0))=A94,"",INDEX(U:U,MATCH(E94,T:T,0))) -> #N/A | K94: =IF(INDEX(AH:AH,MATCH(E94,AE:AE,0))=A94,"",INDEX(AH:AH,MATCH(E94,AE:AE,0))) -> SEA | S94: REU | T94: ISL | U94: EUR | W94: CUB | X94: Cuba | Y94: OSA | AA94: MUS | AB94: Eastern Africa | AC94: SSA | AE94: DOM | AF94: dom | AG94: CAM | AH94: OSA | AJ94: GRD | AK94: CRB | AL94: OSA | AN94: WLD | AQ94: GTM | AR94: Guatemala | AS94: Total Population - Both sexes | AT94: Population - Est. & Proj. | AU94: 2014 | AV94: 1000 persons | AW94: 15923.236
A95: OAS | B95: =INDEX(Regions!B:B,MATCH(A95,Regions!A:A,0)) -> Other Asia | C95: Fiji | D95: FJ | E95: FJI | F95: 242 | G95: =INDEX(AW:AW,MATCH(E95,AQ:AQ,0))/INDEX(AW:AW,MATCH("World",AR:AR,0)) -> 0.00011876881 | H95: =IF(INDEX(Y:Y,MATCH(E95,W:W,0))=A95,"",INDEX(Y:Y,MATCH(E95,W:W,0))) | I95: =IF(INDEX(AC:AC,MATCH(E95,AA:AA,0))=A95,"",INDEX(AC:AC,MATCH(E95,AA:AA,0))) -> ANZ | J95: =IF(INDEX(U:U,MATCH(E95,T:T,0))=A95,"",INDEX(U:U,MATCH(E95,T:T,0))) | K95: =IF(INDEX(AH:AH,MATCH(E95,AE:AE,0))=A95,"",INDEX(AH:AH,MATCH(E95,AE:AE,0))) -> SEA | S95: ISR | T95: ISR | U95: MEN | W95: DOM | X95: DominicanRp | Y95: OSA | AA95: MYT | AB95: Eastern Africa | AC95: SSA | AE95: GRD | AF95: xcb | AG95: CAM | AH95: OSA | AJ95: GRL | AK95: GRL | AL95: EUR | AN95: WLD | AQ95: GIN | AR95: Guinea | AS95: Total Population - Both sexes | AT95: Population - Est. & Proj. | AU95: 2014 | AV95: 1000 persons | AW95: 11150.982
A96: OAS | B96: =INDEX(Regions!B:B,MATCH(A96,Regions!A:A,0)) -> Other Asia | C96: French Polynesia | D96: PF | E96: PYF | F96: 258 | G96: =INDEX(AW:AW,MATCH(E96,AQ:AQ,0))/INDEX(AW:AW,MATCH("World",AR:AR,0)) -> 3.7243889e-05 | H96: =IF(INDEX(Y:Y,MATCH(E96,W:W,0))=A96,"",INDEX(Y:Y,MATCH(E96,W:W,0))) | I96: =IF(INDEX(AC:AC,MATCH(E96,AA:AA,0))=A96,"",INDEX(AC:AC,MATCH(E96,AA:AA,0))) -> ANZ | J96: =IF(INDEX(U:U,MATCH(E96,T:T,0))=A96,"",INDEX(U:U,MATCH(E96,T:T,0))) | K96: =IF(INDEX(AH:AH,MATCH(E96,AE:AE,0))=A96,"",INDEX(AH:AH,MATCH(E96,AE:AE,0))) -> SEA | S96: IT000000 | T96: ITA | U96: EUR | W96: SLV | X96: ElSalvador | Y96: OSA | AA96: REU | AB96: Eastern Africa | AC96: SSA | AE96: HTI | AF96: xcb | AG96: CAM | AH96: OSA | AJ96: GTM | AK96: GTM | AL96: OSA | AM96: OAM | AN96: WLD | AQ96: GNB | AR96: Guinea-Bissau | AS96: Total Population - Both sexes | AT96: Population - Est. & Proj. | AU96: 2014 | AV96: 1000 persons | AW96: 1692.437
A97: OAS | B97: =INDEX(Regions!B:B,MATCH(A97,Regions!A:A,0)) -> Other Asia | C97: Kiribati | D97: KI | E97: KIR | F97: 296 | G97: =INDEX(AW:AW,MATCH(E97,AQ:AQ,0))/INDEX(AW:AW,MATCH("World",AR:AR,0)) -> 1.4994742e-05 | H97: =IF(INDEX(Y:Y,MATCH(E97,W:W,0))=A97,"",INDEX(Y:Y,MATCH(E97,W:W,0))) -> NotAccounted | I97: =IF(INDEX(AC:AC,MATCH(E97,AA:AA,0))=A97,"",INDEX(AC:AC,MATCH(E97,AA:AA,0))) -> ANZ | J97: =IF(INDEX(U:U,MATCH(E97,T:T,0))=A97,"",INDEX(U:U,MATCH(E97,T:T,0))) | K97: =IF(INDEX(AH:AH,MATCH(E97,AE:AE,0))=A97,"",INDEX(AH:AH,MATCH(E97,AE:AE,0))) -> SEA | S97: MSA_ACP | T97: JAM | U97: OSA | W97: GLP | X97: Guadeloupe | Y97: OSA | AA97: RWA | AB97: Eastern Africa | AC97: SSA | AE97: JAM | AF97: jam | AG97: CAM | AH97: OSA | AJ97: GUF | AK97: GSA | AL97: OSA | AM97: OAM | AN97: WLD | AQ97: GUY | AR97: Guyana | AS97: Total Population - Both sexes | AT97: Population - Est. & Proj. | AU97: 2014 | AV97: 1000 persons | AW97: 763.38
A98: OAS | B98: =INDEX(Regions!B:B,MATCH(A98,Regions!A:A,0)) -> Other Asia | C98: Maldives | D98: MV | E98: MDV | F98: 462 | G98: =INDEX(AW:AW,MATCH(E98,AQ:AQ,0))/INDEX(AW:AW,MATCH("World",AR:AR,0)) -> 5.9629563e-05 | H98: =IF(INDEX(Y:Y,MATCH(E98,W:W,0))=A98,"",INDEX(Y:Y,MATCH(E98,W:W,0))) -> NotAccounted | I98: =IF(INDEX(AC:AC,MATCH(E98,AA:AA,0))=A98,"",INDEX(AC:AC,MATCH(E98,AA:AA,0))) | J98: =IF(INDEX(U:U,MATCH(E98,T:T,0))=A98,"",INDEX(U:U,MATCH(E98,T:T,0))) | K98: =IF(INDEX(AH:AH,MATCH(E98,AE:AE,0))=A98,"",INDEX(AH:AH,MATCH(E98,AE:AE,0))) | L98: **Part of Indian Ocean aggregation, assigned to SSA | S98: MIDEAST | T98: JOR | U98: MEN | W98: GTM | X98: Guatemala | Y98: OSA | AA98: SYC | AB98: Eastern Africa | AC98: SSA | AE98: MSR | AF98: xcb | AG98: CAM | AH98: OSA | AJ98: GUM | AK98: OPO | AL98: OAS | AN98: WLD | AO98: Guam | AQ98: HTI | AR98: Haiti | AS98: Total Population - Both sexes | AT98: Population - Est. & Proj. | AU98: 2014 | AV98: 1000 persons | AW98: 10549.009
A99: OAS | B99: =INDEX(Regions!B:B,MATCH(A99,Regions!A:A,0)) -> Other Asia | C99: Marshall Islands | D99: MH | E99: MHL | F99: 584 | G99: =INDEX(AW:AW,MATCH(E99,AQ:AQ,0))/INDEX(AW:AW,MATCH("World",AR:AR,0)) -> 7.8377959e-06 | H99: =IF(INDEX(Y:Y,MATCH(E99,W:W,0))=A99,"",INDEX(Y:Y,MATCH(E99,W:W,0))) -> NotAccounted | I99: =IF(INDEX(AC:AC,MATCH(E99,AA:AA,0))=A99,"",INDEX(AC:AC,MATCH(E99,AA:AA,0))) -> ANZ | J99: =IF(INDEX(U:U,MATCH(E99,T:T,0))=A99,"",INDEX(U:U,MATCH(E99,T:T,0))) -> #N/A | K99: =IF(INDEX(AH:AH,MATCH(E99,AE:AE,0))=A99,"",INDEX(AH:AH,MATCH(E99,AE:AE,0))) -> SEA | S99: JAP | T99: JPN | U99: SEA | W99: HTI | X99: Haiti | Y99: OSA | AA99: SOM | AB99: Eastern Africa | AC99: SSA | AE99: ANT | AF99: xcb | AG99: CAM | AH99: OSA | AJ99: GUY | AK99: GSA | AL99: OSA | AM99: OAM | AN99: WLD | AQ99: VAT | AR99: Holy See | AS99: Total Population - Both sexes | AT99: Population - Est. & Proj. | AU99: 2014 | AV99: 1000 persons | AW99: 0.8
A100: OAS | B100: =INDEX(Regions!B:B,MATCH(A100,Regions!A:A,0)) -> Other Asia | C100: Micronesia (Federated States of) | D100: FM | E100: FSM | F100: 583 | G100: =INDEX(AW:AW,MATCH(E100,AQ:AQ,0))/INDEX(AW:AW,MATCH("World",AR:AR,0)) -> 1.4728131e-05 | H100: =IF(INDEX(Y:Y,MATCH(E100,W:W,0))=A100,"",INDEX(Y:Y,MATCH(E100,W:W,0))) -> NotAccounted | I100: =IF(INDEX(AC:AC,MATCH(E100,AA:AA,0))=A100,"",INDEX(AC:AC,MATCH(E100,AA:AA,0))) -> ANZ | J100: =IF(INDEX(U:U,MATCH(E100,T:T,0))=A100,"",INDEX(U:U,MATCH(E100,T:T,0))) -> #N/A | K100: =IF(INDEX(AH:AH,MATCH(E100,AE:AE,0))=A100,"",INDEX(AH:AH,MATCH(E100,AE:AE,0))) -> SEA | S100: KAZ | T100: KAZ | U100: FSU | W100: HND | X100: Honduras | Y100: OSA | AA100: SDN | AB100: Eastern Africa | AC100: SSA | AE100: PRI | AF100: pri | AG100: CAM | AH100: OSA | AJ100: HKG | AK100: CHM | AL100: CHN | AM100: SAS | AN100: WLD | AQ100: HND | AR100: Honduras | AS100: Total Population - Both sexes | AT100: Population - Est. & Proj. | AU100: 2014 | AV100: 1000 persons | AW100: 8955.589
...

Sheet DM_Conversion_rates
A1: Fresh matter to dry matter conversion used in models
A2: Item | B2: MAGNET | D2: IMAGE categories | E2: AGMIP item | F2: value
A3: RIC | B3: 0.87 | D3: Grass | E3: GRS | F3: 0.16
A4: WHT | B4: 0.88 | D4: Wheat | E4: WHT | F4: 0.88
A5: CGR | B5: 0.88 | D5: Rice | E5: RIC | F5: 0.87
A6: VFN|VEG | B6: 0.2 | D6: Maize | E6: CGR | F6: 0.88
A7: VFN|FRU | B7: 0.2 | D7: Tropical cereals | E7: CGR | F7: 0.88
A8: VFN|NUT | B8: 0.2 | D8: Other temperate cereals | E8: CGR | F8: 0.88
A9: VFN|ROOT | B9: 0.85 | D9: Pulses | E9: VFN | F9: 0.9
A10: VFN|PULS | B10: 0.25 | D10: Soybeans | E10: OSD | F10: 0.91
A11: OSD | B11: 0.92 | D11: Temperate oil crops | E11: OSD | F11: 0.925
A12: SGC | B12: 0.25 | D12: Tropical oil crops | E12: OSD | F12: 0.94
A13: PFB | B13: 0.92 | D13: Temperate roots & tubers | E13: VFN | F13: 0.24
A14: PCR | B14: 0.8 | D14: Tropical roots & tubers | E14: VFN | F14: 0.35
... A18: FSH | B18: 0.7 | D18: Other non-food, luxury, spices | E18: OCR | F18: 0.9
D19: Plant based fibres | E19: PFB | F19: 0.912
D20: Beef | E20: RUM | F20: 0.5
D21: Dairy | E21: DRY | F21: 0.125
D22: Pigs | E22: NRUM | F22: 0.5
D23: Sheep&goats | E23: RUM | F23: 0.5
D24: Poultry | E24: NRUM | F24: 0.5
